Workbook

Sheet 汇总
C1: 菲律宾 07月01- | S1: 26 | AJ1: 菲律宾 06月01- | AZ1: 30 | BQ1: 菲律宾 05月01- | CI1: 31 | CX1: 菲律宾 04月01- | DP1: 30 | EE1: 菲律宾 03月01- | EW1: 31 | FN1: 菲律宾 02月01 - | GF1: 28 | GU1: 31 | GV1: 菲律宾 01月01 - | HL1: 31 | ID1: 天成 12月01 - | IT1: 31 | JL1: 天成 11月01 - | KB1: 30 | KT1: 天成 10月01 - | LJ1: 31 | MB1: 天成 9月01- | MR1: 30 | NJ1: 天成 8月01- | NZ1: 31 | OS1: 天成 7月01 - 7月 | PF1: 31 | QF1: 天成 6月01 - 6月 | QG1: 30 | QU1: 天成 5月01 - 5月31 | RQ1: 天成 4月1-30 | SM1: 天成 3月1-31 | TH1: 2月1-28 | UD1: 天成 1月1-31 | UZ1: 天成 12月1-31
C2: 平台 | D2: 现场人数 | E2: 转线上人数 | F2: 线上人数 | G2: 人均开发 | H2: 总注册 | I2: 总开发人数 | J2: 首存金额 | K2: 首存总金额 | L2: 首提总金额 | M2: 新客总存 | N2: 新客总提 | O2: 新客存提差 | P2: 一级首存 | Q2: 一级存款 | R2: 一级提款 | S2: 充值人数 | T2: 复存人数 | U2: 存款 | V2: 提款 | W2: 存提差 | X2: 线上员工资 | Y2: 平台盈亏 | Z2: 充值 手续费3.5% | AA2: 平台 服务费20% | AB2: 现场员工资 | AC2: 转线上员工资 | AD2: 净利润 | AE2: 新客单价 | AF2: 客单价 | AG2: 支出回报率 | AH2: 投产比 | AJ2: 平台 | AK2: 现场人数 | AL2: 转线上人数 | AM2: 线上人数 | AN2: 人均开发 | AO2: 总注册 | AP2: 总开发人数 | AQ2: 首存金额 | AR2: 首存总金额 | AS2: 首提总金额 | AT2: 新客总存 | AU2: 新客总提 | AV2: 新客存提差 | AW2: 一级首存 | AX2: 一级存款 | AY2: 一级提款 | AZ2: 充值人数 | BA2: 复存人数 | BB2: 存款 | BC2: 提款 | BD2: 存提差 | BE2: 线上员工资 | BF2: 平台盈亏 | BG2: 充值 手续费3.5% | BH2: 平台 服务费20% | BI2: 现场员工资 | BJ2: 转线上员工资 | BK2: 净利润 | BL2: 新客单价 | BM2: 客单价 | BN2: 支出回报率 | BO2: 投产比 | BQ2: 平台 | BR2: 现场人数 | BS2: 转线上人数 | BT2: 线上人数 | BU2: 人均开发 | BV2: 总注册 | BW2: 总开发人数 | BX2: 首存金额 | BY2: 首存总金额 | BZ2: 首提总金额 | CA2: 新客总存 | CB2: 新客总提 | CC2: 新客存提差 | CD2: 一级首存 | CE2: 一级存款 | CF2: 一级提款 | CG2: 充值人数 | CH2: 复存人数 | CI2: 存款 | CJ2: 提款 | CK2: 存提差 | CL2: 线上员工资 | CM2: 平台盈亏 | CN2: 充值 手续费3.5% | CO2: 平台 服务费20% | CP2: 现场员工资 | CQ2: 转线上员工资 | CR2: 净利润 | CS2: 新客单价 | CT2: 客单价 | CU2: 支出回报率 | CV2: 投产比 | CX2: 平台 | CY2: 现场人数 | CZ2: 转线上人数 | DA2: 线上人数 | DB2: 人均开发 | DC2: 总注册 | DD2: 总开发人数 | DE2: 首存金额 | DF2: 首存总金额 | DG2: 首提总金额 | DH2: 新客总存 | DI2: 新客总提 | DJ2: 新客存提差 | DK2: 一级首存 | DL2: 一级存款 | DM2: 一级提款 | DN2: 充值人数 | DO2: 复存人数 | DP2: 存款 | DQ2: 提款 | DR2: 存提差 | DS2: 线上员工资 | DT2: 平台盈亏 | DU2: 充值 手续费3.5% | DV2: 平台 服务费20% | DW2: 现场员工资 | DX2: 转线上员工资 | DY2: 净利润 | DZ2: 新客单价 | EA2: 客单价 | EB2: 支出回报率 | EC2: 投产比 | EE2: 平台 | EF2: 现场人数 | EG2: 转线上人数 | EH2: 线上人数 | EI2: 人均开发 | EJ2: 总注册 | EK2: 总开发人数 | EL2: 首存金额 | EM2: 首存总金额 | EN2: 首提总金额 | EO2: 新客总存 | EP2: 新客总提 | EQ2: 新客存提差 | ER2: 一级首存 | ES2: 一级存款 | ET2: 一级提款 | EU2: 充值人数 | EV2: 复存人数 | EW2: 存款 | EX2: 提款 | EY2: 存提差 | EZ2: 线上员工资 | FA2: 平台盈亏 | FB2: 充值 手续费3.5% | FC2: 平台 服务费20% | FD2: 现场员工资 | FE2: 转线上员工资 | FF2: 净利润 | FG2: 新客单价 | FH2: 客单价 | FI2: 支出回报率 | FJ2: 投产比 | FN2: 平台 | FO2: 现场人数 | FP2: 转线上人数 | FQ2: 线上人数 | FR2: 人均开发 | FS2: 总注册 | FT2: 总开发人数 | FU2: 首存金额 | FV2: 首存总金额 | FW2: 首提总金额 | FX2: 新客总存 | FY2: 新客总提 | FZ2: 新客存提差 | GA2: 一级首存 | GB2: 一级存款 | GC2: 一级提款 | GD2: 充值人数 | GE2: 复存人数 | GF2: 存款 | GG2: 提款 | GH2: 存提差 | GI2: 线上员工资 | GJ2: 平台盈亏 | GK2: 充值 手续费3.5% | GL2: 平台 服务费20% | GM2: 现场员工资 | GN2: 转线上员工资 | GO2: 净利润 | GP2: 新客单价 | GQ2: 客单价 | GR2: 支出回报率 | GS2: 投产比 | GV2: 平台 | GW2: 现场人数 | GX2: 转线上人数 | GY2: 线上人数 | GZ2: 人均开发 | HA2: 总注册 | HB2: 总开发人数 | HC2: 首存金额 | HD2: 首存总金额 | HE2: 首提总金额 | HF2: 新客总存 | HG2: 新客总提 | HH2: 新客存提差 | HI2: 一级首存 | HJ2: 一级存款 | HK2: 一级提款 | HL2: 充值人数 | HM2: 复存人数 | HN2: 存款 | HO2: 提款 | HP2: 存提差 | HQ2: 线上员工资 | HR2: 平台盈亏 | HS2: 充值 手续费3.5% | HT2: 平台 服务费20% | HU2: 现场员工资 | HV2: 转线上员工资 | HW2: 净利润 | HX2: 新客单价 | HY2: 客单价 | HZ2: 支出回报率 | IA2: 投产比 | ID2: 平台 | IE2: 现场人数 | IF2: 转线上人数 | IG2: 线上人数 | IH2: 人均开发 | II2: 总注册 | IJ2: 总开发人数 | IK2: 首存金额 | IL2: 首存总金额 | IM2: 首提总金额 | IN2: 新客总存 | IO2: 新客总提 | IP2: 新客存提差 | IQ2: 一级首存 | IR2: 一级存款 | IS2: 一级提款 | IT2: 充值人数 | IU2: 复存人数 | IV2: 存款 | IW2: 提款 | IX2: 存提差 | IY2: 线上员工资 | IZ2: 平台盈亏 | JA2: 充值 手续费3.5% | JB2: 平台 服务费20% | JC2: 现场员工资 | JD2: 转线上员工资 | JE2: 净利润 | JF2: 新客单价 | JG2: 客单价 | JH2: 支出回报率 | JI2: 投产比 | JL2: 平台 | JM2: 现场人数 | JN2: 转线上人数 | JO2: 线上人数 | JP2: 人均开发 | JQ2: 总注册 | JR2: 总开发人数 | JS2: 首存金额 | JT2: 首存总金额 | JU2: 首提总金额 | JV2: 新客总存 | JW2: 新客总提 | JX2: 新客存提差 | JY2: 一级首存 | JZ2: 一级存款 | KA2: 一级提款 | KB2: 充值人数 | KC2: 复存人数 | KD2: 存款 | KE2: 提款 | KF2: 存提差 | KG2: 线上员工资 | KH2: 平台盈亏 | KI2: 充值 手续费3.5% | KJ2: 平台 服务费20% | KK2: 现场员工资 | KL2: 转线上员工资 | KM2: 净利润 | KN2: 新客单价 | KO2: 客单价 | KP2: 支出回报率 | KQ2: 投产比 | KT2: 平台 | KU2: 现场人数 | KV2: 转线上人数 | KW2: 线上人数 | KX2: 人均开发 | KY2: 总注册 | KZ2: 总开发人数 | LA2: 首存金额 | LB2: 首存总金额 | LC2: 首提总金额 | LD2: 新客总存 | LE2: 新客总提 | LF2: 新客存提差 | LG2: 一级首存 | LH2: 一级存款 | LI2: 一级提款 | LJ2: 充值人数 | LK2: 复存人数 | LL2: 存款 | LM2: 提款 | LN2: 存提差 | LO2: 线上员工资 | LP2: 平台盈亏 | LQ2: 充值 手续费3.5% | LR2: 平台 服务费20% | LS2: 现场员工资 | LT2: 转线上员工资 | LU2: 净利润 | LV2: 新客单价 | LW2: 客单价 | LX2: 支出回报率 | LY2: 投产比 | MB2: 平台 | MC2: 现场人数 | MD2: 转线上人数 | ME2: 线上人数 | MF2: 人均开发 | MG2: 总注册 | MH2: 总开发人数 | MI2: 首存金额 | MJ2: 首存总金额 | MK2: 首提总金额 | ML2: 新客总存 | MM2: 新客总提 | MN2: 新客存提差 | MO2: 一级首存 | MP2: 一级存款 | MQ2: 一级提款 | MR2: 充值人数 | MS2: 复存人数 | MT2: 存款 | MU2: 提款 | MV2: 存提差 | MW2: 线上员工资 | MX2: 平台盈亏 | MY2: 充值 手续费3.5% | MZ2: 平台 服务费20% | NA2: 现场员工资 | NB2: 转线上员工资 | NC2: 净利润 | ND2: 新客单价 | NE2: 客单价 | NF2: 支出回报率 | NG2: 投产比 | NJ2: 平台 | NK2: 现场人数 | NL2: 转线上人数 | NM2: 线上人数 | NN2: 人均开发 | NO2: 总注册 | NP2: 总开发人数 | NQ2: 首存金额 | NR2: 首存总金额 | NS2: 首提总金额 | NT2: 新客总存 | NU2: 新客总提 | NV2: 新客存提差 | NW2: 一级首存 | NX2: 一级存款 | NY2: 一级提款 | NZ2: 充值人数 | OA2: 复存人数 | OB2: 存款 | OC2: 提款 | OD2: 存提差 | OE2: 线上员工资 | OF2: 平台盈亏 | OG2: 充值 手续费3.5% | OH2: 平台 服务费20% | OI2: 现场员工资 | OJ2: 转线上员工资 | OK2: 净利润 | OL2: 新客单价 | OM2: 客单价 | ON2: 支出回报率 | OO2: 投产比 | OS2: 平台 | OT2: 现场人数 | OU2: 线上人数 | OV2: 总注册 | OW2: 总开发人数 | OX2: 首存金额 | OY2: 首存总金额 | OZ2: 首提总金额 | PA2: 新客总存 | PB2: 新客总提 | PC2: 充值人数 | PD2: 复存人数 | PE2: 存款 | PF2: 提款 | PG2: 存提差 | PH2: 线上员工资 | PI2: 平台盈亏 | PJ2: 充值手续费3.5% | PK2: 平台服务费20% | PL2: 现场员工资 | PM2: 净利润 | PN2: 新客单价 | PO2: 客单价 | PP2: 支出回报率 | PQ2: 投产比 | PU2: 平台 | PV2: 现场人数 | PW2: 线上人数 | PX2: 注册 | PY2: 首存 | PZ2: 首存金额 | QA2: 新客首存总金额 | QB2: 新客首提总金额 | QC2: 充值人数 | QD2: 复存人数 | QE2: 存款 | QF2: 提款 | QG2: 存提差 | QH2: 外部人员工资 | QI2: 平台盈亏 | QJ2: 充值手续费3.5% | QK2: 平台服务费20% | QL2: 现场人员工资 | QM2: 净利润 | QN2: 新款客单价 | QO2: 人均客单价 | QP2: 支出回报率 | QQ2: 投产比 | QU2: 平台 | QV2: 人数 | QW2: 注册 | QX2: 首存 | QY2: 首存/总存金额 | QZ2: 充值人数 | RA2: 存款 | RB2: 提款 | RC2: 提款 | RD2: 存提差 | RE2: 外部人员工资 | RF2: 平台盈亏 | RG2: 充值手续费3.5% | RH2: 平台服务费10% | RI2: 现场人员工资 | RJ2: 净利润 | RK2: 人均客单价 | RL2: 支出回报率 | RM2: 投产比 | RQ2: 平台 | RR2: 人数 | RS2: 注册 | RT2: 首存 | RU2: 首存/总存金额 | RV2: 充值人数 | RW2: 存款 | RX2: 提款 | RY2: 存提差 | RZ2: 外部人员工资 | SA2: - | SB2: 平台盈亏 | SC2: 充值手续费3.5% | SD2: 平台服务费10% | SE2: 现场人员工资 | SF2: 净利润 | SG2: 人均客单价 | SH2: 支出回报率 | SI2: 投产比 | SM2: 平台 | SN2: 人数 | SO2: 注册 | SP2: 首存 | SQ2: 首存/总存金额 | SR2: 充值人数 | SS2: 存款 | ST2: 提款 | SU2: 存提差 | SV2: 外部人员工资 | SW2: - | SX2: 平台盈亏 | SY2: 充值手续费3.5% | SZ2: 平台服务费10% | TA2: 现场人员工资 | TB2: 净利润 | TC2: 人均客单价 | TD2: 支出回报率 | TE2: 投产比 | TH2: 平台 | TI2: 人数 | TJ2: 注册 | TK2: 首存 | TL2: 首存/总存金额 | TM2: 充值人数 | TN2: 存款 | TO2: 提款 | TP2: 存提差 | TQ2: 外部人员工资 | TR2: - | TS2: 平台盈亏 | TT2: 充值手续费4% | TU2: 平台服务费10% | TV2: 现场人员工资 | TW2: 净利润 | TX2: 人均客单价 | TY2: 支出回报率 | TZ2: 投产比 | UD2: 平台 | UE2: 人数 | UF2: 注册 | UG2: 首存 | UH2: 首存/总存金额 | UI2: 充值人数 | UJ2: 存款 | UK2: 提款 | UL2: 存提差 | UM2: 外部人员工资 | UN2: - | UO2: 平台盈亏 | UP2: 充值手续费4% | UQ2: 平台服务费10% | UR2: 现场人员工资 | US2: 净利润 | UT2: 人均客单价 | UU2: 支出回报率 | UV2: 投产比 | UZ2: 平台 | VA2: 人数 | VB2: 注册 | VC2: 首存 | VD2: 首存/总存金额 | VE2: 充值人数 | VF2: 存款 | VG2: 提款 | VH2: 存提差 | VI2: 外部人员工资 | VJ2: - | VK2: 平台盈亏 | VL2: 充值手续费4% | VM2: 平台服务费10% | VN2: 现场人员工资 | VO2: 净利润 | VP2: 人均客单价 | VQ2: 支出回报率 | VR2: 投产比
C3: Platform | D3: Onsite HC | E3: Transfer HC | F3: Online HC | G3: Avg FTD | H3: Total Reg | I3: Total FTD | J3: FTD Amt | K3: Total FTD Amt | L3: Total WD Amt | M3: New Dep | N3: New WD | O3: New Net | P3: L1 FTD | Q3: L1 Dep | R3: L1 WD | S3: Dep Users | T3: Re-Dep Users | U3: Dep | V3: WD | W3: Net Dep | X3: Online Salary | Y3: Platform P/L | Z3: Dep Fee 3.5% | AA3: Platform Fee 20% | AB3: Onsite Salary | AC3: Transfer Salary | AD3: Net Profit | AE3: New AOV | AF3: AOV | AG3: ROAS | AH3: ROI | AJ3: Platform | AK3: Onsite HC | AL3: Transfer HC | AM3: Online HC | AN3: Avg FTD | AO3: Total Reg | AP3: Total FTD | AQ3: FTD Amt | AR3: Total FTD Amt | AS3: Total WD Amt | AT3: New Dep | AU3: New WD | AV3: New Net | AW3: L1 FTD | AX3: L1 Dep | AY3: L1 WD | AZ3: Dep Users | BA3: Re-Dep Users | BB3: Dep | BC3: WD | BD3: Net Dep | BE3: Online Salary | BF3: Platform P/L | BG3: Dep Fee 3.5% | BH3: Platform Fee 20% | BI3: Onsite Salary | BJ3: Transfer Salary | BK3: Net Profit | BL3: New AOV | BM3: AOV | BN3: ROAS | BO3: ROI | BQ3: Platform | BR3: Onsite HC | BS3: Transfer HC | BT3: Online HC | BU3: Avg FTD | BV3: Total Reg | BW3: Total FTD | BX3: FTD Amt | BY3: Total FTD Amt | BZ3: Total WD Amt | CA3: New Dep | CB3: New WD | CC3: New Net | CD3: L1 FTD | CE3: L1 Dep | CF3: L1 WD | CG3: Dep Users | CH3: Re-Dep Users | CI3: Dep | CJ3: WD | CK3: Net Dep | CL3: Online Salary | CM3: Platform P/L | CN3: Dep Fee 3.5% | CO3: Platform Fee 20% | CP3: Onsite Salary | CQ3: Transfer Salary | CR3: Net Profit | CS3: New AOV | CT3: AOV | CU3: ROAS | CV3: ROI | CX3: Platform | CY3: Onsite HC | CZ3: Transfer HC | DA3: Online HC | DB3: Avg FTD | DC3: Total Reg | DD3: Total FTD | DE3: FTD Amt | DF3: Total FTD Amt | DG3: Total WD Amt | DH3: New Dep | DI3: New WD | DJ3: New Net | DK3: L1 FTD | DL3: L1 Dep | DM3: L1 WD | DN3: Dep Users | DO3: Re-Dep Users | DP3: Dep | DQ3: WD | DR3: Net Dep | DS3: Online Salary | DT3: Platform P/L | DU3: Dep Fee 3.5% | DV3: Platform Fee 20% | DW3: Onsite Salary | DX3: Transfer Salary | DY3: Net Profit | DZ3: New AOV | EA3: AOV | EB3: ROAS | EC3: ROI | EE3: Platform | EF3: Onsite HC | EG3: Transfer HC | EH3: Online HC | EI3: Avg FTD | EJ3: Total Reg | EK3: Total FTD | EL3: FTD Amt | EM3: Total FTD Amt | EN3: Total WD Amt | EO3: New Dep | EP3: New WD | EQ3: New Net | ER3: L1 FTD | ES3: L1 Dep | ET3: L1 WD | EU3: Dep Users | EV3: Re-Dep Users | EW3: Dep | EX3: WD | EY3: Net Dep | EZ3: Online Salary | FA3: Platform P/L | FB3: Dep Fee 3.5% | FC3: Platform Fee 20% | FD3: Onsite Salary | FE3: Transfer Salary | FF3: Net Profit | FG3: New AOV | FH3: AOV | FI3: ROAS | FJ3: ROI | FN3: Platform | FO3: Onsite HC | FP3: Transfer HC | FQ3: Online HC | FR3: Avg FTD | FS3: Total Reg | FT3: Total FTD | FU3: FTD Amt | FV3: Total FTD Amt | FW3: Total WD Amt | FX3: New Dep | FY3: New WD | FZ3: New Net | GA3: L1 FTD | GB3: L1 Dep | GC3: L1 WD | GD3: Dep Users | GE3: Re-Dep Users | GF3: Dep | GG3: WD | GH3: Net Dep | GI3: Online Salary | GJ3: Platform P/L | GK3: Dep Fee 3.5% | GL3: Platform Fee 20% | GM3: Onsite Salary | GN3: Transfer Salary | GO3: Net Profit | GP3: New AOV | GQ3: AOV | GR3: ROAS | GS3: ROI | GV3: Platform | GW3: Onsite HC | GX3: Transfer HC | GY3: Online HC | GZ3: Avg FTD | HA3: Total Reg | HB3: Total FTD | HC3: FTD Amt | HD3: Total FTD Amt | HE3: Total WD Amt | HF3: New Dep | HG3: New WD | HH3: New Net | HI3: L1 FTD | HJ3: L1 Dep | HK3: L1 WD | HL3: Dep Users | HM3: Re-Dep Users | HN3: Dep | HO3: WD | HP3: Net Dep | HQ3: Online Salary | HR3: Platform P/L | HS3: Dep Fee 3.5% | HT3: Platform Fee 20% | HU3: Onsite Salary | HV3: Transfer Salary | HW3: Net Profit | HX3: New AOV | HY3: AOV | HZ3: ROAS | IA3: ROI | ID3: Platform | IE3: Onsite HC | IF3: Transfer HC | IG3: Online HC | IH3: Avg FTD | II3: Total Reg | IJ3: Total FTD | IK3: FTD Amt | IL3: Total FTD Amt | IM3: Total WD Amt | IN3: New Dep | IO3: New WD | IP3: New Net | IQ3: L1 FTD | IR3: L1 Dep | IS3: L1 WD | IT3: Dep Users | IU3: Re-Dep Users | IV3: Dep | IW3: WD | IX3: Net Dep | IY3: Online Salary | IZ3: Platform P/L | JA3: Dep Fee 3.5% | JB3: Platform Fee 20% | JC3: Onsite Salary | JD3: Transfer Salary | JE3: Net Profit | JF3: New AOV | JG3: AOV | JH3: ROAS | JI3: ROI | JL3: Platform | JM3: Onsite HC | JN3: Transfer HC | JO3: Online HC | JP3: Avg FTD | JQ3: Total Reg | JR3: Total FTD | JS3: FTD Amt | JT3: Total FTD Amt | JU3: Total WD Amt | JV3: New Dep | JW3: New WD | JX3: New Net | JY3: L1 FTD | JZ3: L1 Dep | KA3: L1 WD | KB3: Dep Users | KC3: Re-Dep Users | KD3: Dep | KE3: WD | KF3: Net Dep | KG3: Online Salary | KH3: Platform P/L | KI3: Dep Fee 3.5% | KJ3: Platform Fee 20% | KK3: Onsite Salary | KL3: Transfer Salary | KM3: Net Profit | KN3: New AOV | KO3: AOV | KP3: ROAS | KQ3: ROI | KT3: Platform | KU3: Onsite HC | KV3: Transfer HC | KW3: Online HC | KX3: Avg FTD | KY3: Total Reg | KZ3: Total FTD | LA3: FTD Amt | LB3: Total FTD Amt | LC3: Total WD Amt | LD3: New Dep | LE3: New WD | LF3: New Net | LG3: L1 FTD | LH3: L1 Dep | LI3: L1 WD | LJ3: Dep Users | LK3: Re-Dep Users | LL3: Dep | LM3: WD | LN3: Net Dep | LO3: Online Salary | LP3: Platform P/L | LQ3: Dep Fee 3.5% | LR3: Platform Fee 20% | LS3: Onsite Salary | LT3: Transfer Salary | LU3: Net Profit | LV3: New AOV | LW3: AOV | LX3: ROAS | LY3: ROI | MB3: Platform | MC3: Onsite HC | MD3: Transfer HC | ME3: Online HC | MF3: Avg FTD | MG3: Total Reg | MH3: Total FTD | MI3: FTD Amt | MJ3: Total FTD Amt | MK3: Total WD Amt | ML3: New Dep | MM3: New WD | MN3: New Net | MO3: L1 FTD | MP3: L1 Dep | MQ3: L1 WD | MR3: Dep Users | MS3: Re-Dep Users | MT3: Dep | MU3: WD | MV3: Net Dep | MW3: Online Salary | MX3: Platform P/L | MY3: Dep Fee 3.5% | MZ3: Platform Fee 20% | NA3: Onsite Salary | NB3: Transfer Salary | NC3: Net Profit | ND3: New AOV | NE3: AOV | NF3: ROAS | NG3: ROI | NJ3: Platform | NK3: Onsite HC | NL3: Transfer HC | NM3: Online HC | NN3: Avg FTD | NO3: Total Reg | NP3: Total FTD | NQ3: FTD Amt | NR3: Total FTD Amt | NS3: Total WD Amt | NT3: New Dep | NU3: New WD | NV3: New Net | NW3: L1 FTD | NX3: L1 Dep | NY3: L1 WD | NZ3: Dep Users | OA3: Re-Dep Users | OB3: Dep | OC3: WD | OD3: Net Dep | OE3: Online Salary | OF3: Platform P/L | OG3: Dep Fee 3.5% | OH3: Platform Fee 20% | OI3: Onsite Salary | OJ3: Transfer Salary | OK3: Net Profit | OL3: New AOV | OM3: AOV | ON3: ROAS | OO3: ROI | OS3: Platform | OT3: Onsite HC | OU3: Online HC | OV3: Total Reg | OW3: Total FTD | OX3: FTD Amt | OY3: Total FTD Amt | OZ3: Total WD Amt | PA3: New Dep | PB3: New WD | PC3: Dep Users | PD3: Re-Dep Users | PE3: Dep | PF3: WD | PG3: Net Dep | PH3: Online Salary | PI3: Platform P/L | PJ3: Dep Fee 3.5% | PK3: Platform Fee 20% | PL3: Onsite Salary | PM3: Net Profit | PN3: New AOV | PO3: AOV | PP3: ROAS | PQ3: ROI | PS3: 异常提款 | PU3: Platform | PV3: Mainpower | PX3: Register | PY3: FTD | QA3: Ftd Total All DPS Amount | QC3: Depositors | QE3: Deposit | QF3: Withdraw | QG3: Different | QH3: WFH Staff Salary | QI3: Platform Profit | QJ3: Deposit Fee 3.5% | QK3: Platform Service Fee 10% | QL3: Office Staff Salary | QM3: Net Profit | QO3: Average Spend per Customer | QP3: Return on Advertising Spend | QQ3: Return on Investment % | QS3: 玩家异常提款： | QU3: Platform | QV3: Mainpower | QW3: Register | QX3: FTD | QY3: Ftd Total All DPS Amount | QZ3: Depositors | RA3: Deposit | RB3: Withdraw | RC3: Withdraw | RD3: Different | RE3: WFH Staff Salary | RF3: Platform Profit | RG3: Deposit Fee 3.5% | RH3: Platform Service Fee 10% | RI3: Office Staff Salary | RJ3: Net Profit | RK3: Average Spend per Customer | RL3: Return on Advertising Spend | RM3: Return on Investment % | RQ3: Platform | RR3: Mainpower | RS3: Register | RT3: FTD | RU3: Ftd Total All DPS Amount | RV3: Depositors | RW3: Deposit | RX3: Withdraw | RY3: Different | RZ3: WFH Staff Salary | SA3: - | SB3: Platform Profit | SC3: Deposit Fee 3.5% | SD3: Platform Service Fee 10% | SE3: Office Staff Salary | SF3: Net Profit | SG3: Average Spend per Customer | SH3: Return on Advertising Spend | SI3: Return on Investment % | SM3: Platform | SN3: Mainpower | SO3: Register | SP3: FTD | SQ3: Ftd Total All DPS Amount | SR3: Depositors | SS3: Deposit | ST3: Withdraw | SU3: Different | SV3: WFH Staff Salary | SW3: - | SX3: Platform Profit | SY3: Deposit Fee 3.5% | SZ3: Platform Service Fee 10% | TA3: Office Staff Salary | TB3: Net Profit | TC3: Average Spend per Customer | TD3: Return on Advertising Spend | TE3: Return on Investment % | TH3: Platform | TI3: Mainpower | TJ3: Register | TK3: FTD | TL3: Ftd Total All DPS Amount | TM3: Depositors | TN3: Deposit | TO3: Withdraw | TP3: Different | TQ3: WFH Staff Salary | TR3: - | TS3: Platform Profit | TT3: Deposit Fee 3.5% | TU3: Platform Service Fee 10% | TV3: Office Staff Salary | TW3: Net Profit | TX3: Average Spend per Customer | TY3: Return on Advertising Spend | TZ3: Return on Investment % | UD3: Platform | UE3: Mainpower | UF3: Register | UG3: FTD | UH3: Ftd Total All DPS Amount | UI3: Depositors | UJ3: Deposit | UK3: Withdraw | UL3: Different | UM3: WFH Staff Salary | UN3: - | UO3: Platform Profit | UP3: Deposit Fee 3.5% | UQ3: Platform Service Fee 10% | UR3: Office Staff Salary | US3: Net Profit | UT3: Average Spend per Customer | UU3: Return on Advertising Spend | UV3: Return on Investment % | UZ3: Platform | VA3: Mainpower | VB3: Register | VC3: FTD | VD3: Ftd Total All DPS Amount | VE3: Depositors | VF3: Deposit | VG3: Withdraw | VH3: Different | VI3: WFH Staff Salary | VJ3: - | VK3: Platform Profit | VL3: Deposit Fee 3.5% | VM3: Platform Service Fee 10% | VN3: Office Staff Salary | VO3: Net Profit | VP3: Average Spend per Customer | VQ3: Return on Advertising Spend | VR3: Return on Investment %
C4: PH09 | D4: 3 | E4: 2 | F4: ='PH09'!AJ4 -> 45 | G4: =(I4/F4)/S1 -> 4.6803419 | H4: ='PH09'!G4 -> 9462 | I4: ='PH09'!H4 -> 5476 | J4: ='PH09'!T4 -> 829366 | K4: ='PH09'!U4 -> 1150492 | L4: ='[1]PH09'!V4 -> 666493.12 | M4: =1379384+1309192 -> 2688576 | N4: =1296422.25+1155050 -> 2451472.2 | O4: =M4-N4 -> 237103.75 | P4: ='PH09'!J4 -> 4267 | Q4: ='PH09'!R4 -> 895925 | R4: ='PH09'!S4 -> 670308.88 | S4: ='PH09'!K4 -> 37917 | T4: =S4-I4 -> 32441 | U4: ='PH09'!W4 -> 25783720 | V4: ='PH09'!X4 -> 21822575 | W4: =U4-V4 -> 3961145.4 | X4: ='PH09'!D4 -> 981915 | Y4: =2980321.9+651197.33 -> 3631519.2 | Z4: =U4*3.5% -> 902430.2 | AA4: =IF(Y4>0,Y4*20%,0) -> 726303.85 | AB4: =(D4*3200)*S1 -> 249600 | AC4: =(E4*1733)*S1 -> 90116 | AD4: =W4-Z4-AA4-X4-AB4-AC4 -> 1010780.3 | AE4: =K4/I4 -> 210.09715 | AF4: =U4/S4 -> 680.00422 | AG4: =M4/(Z4+AA4+X4+AB4+AC4) -> 0.91126893 | AH4: =W4/(Z4+AA4+X4+AB4+AC4) -> 1.342595 | AJ4: PH09 | AK4: 1 | AL4: 2 | AM4: 66 | AN4: =(AP4/AM4)/AZ1 -> 3.0616162 | AO4: 11277 | AP4: 6062 | AQ4: 888457 | AR4: 1207999 | AS4: 860977.4 | AT4: 3346155 | AU4: 2829610.8 | AV4: =AT4-AU4 -> 516544.18 | AW4: 1006928 | AX4: 1006928 | AY4: 707035.4 | AZ4: 43237 | BA4: 37175 | BB4: 27807396 | BC4: 23414005 | BD4: =BB4-BC4 -> 4393391.2 | BE4: 902275 | BF4: 4291954.7 | BG4: =BB4*3.5% -> 973258.86 | BH4: =IF(BF4>0,BF4*20%,0) -> 858390.93 | BI4: =(AK4*3200)*AZ1 -> 96000 | BJ4: =(AL4*1733)*AZ1 -> 103980 | BK4: =BD4-BG4-BH4-BE4-BI4-BJ4 -> 1459486.4 | BL4: =AR4/AP4 -> 199.274 | BM4: =BB4/AZ4 -> 643.13889 | BN4: =AT4/(BG4+BH4+BE4+BI4) -> 1.1824183 | BO4: =BD4/(BG4+BH4+BE4+BI4+BJ4) -> 1.4974553 | BQ4: PH09 | BR4: 1 | BS4: 2 | BT4: 68 | BU4: 2.2969639 | BV4: 10666 | BW4: 4842 | BX4: 770219 | BY4: 1085316 | BZ4: 742565.75 | CA4: 3937326 | CB4: 3888711.9 | CC4: 48614.09 | CD4: 4060 | CE4: 891415 | CF4: 604527.8 | CG4: 41794 | CH4: 38285 | CI4: 29140944 | CJ4: 24995726 | CK4: =CI4-CJ4 -> 4145218 | CL4: 742860 | CM4: 3662705.5 | CN4: =CI4*3.5% -> 1019933 | CO4: =IF(CM4>0,CM4*20%,0) -> 732541.11 | CP4: =(BR4*3200)*CI1 -> 99200 | CQ4: =(BS4*1733)*CI1 -> 107446 | CR4: =CK4-CN4-CO4-CL4-CP4-CQ4 -> 1443237.9 | CS4: =BY4/BW4 -> 224.14622 | CT4: =CI4/CG4 -> 697.25185 | CU4: =CA4/(CN4+CO4+CL4+CP4) -> 1.5175464 | CV4: =CK4/(CN4+CO4+CL4+CP4+CQ4) -> 1.5341408 | CX4: PH09 | CY4: 1 | CZ4: 0 | DA4: 54 | DB4: 2.9345679 | DC4: 9056 | DD4: 4754 | DE4: 679684 | DF4: 900282 | DG4: 557096.5 | DH4: 2556554 | DI4: 2330008.1 | DJ4: =DH4-DI4 -> 226545.88 | DK4: 4028 | DL4: 740980 | DM4: 466823.8 | DN4: 44966 | DO4: 40212 | DP4: 27624918 | DQ4: 25212389 | DR4: =DP4-DQ4 -> 2412529 | DS4: 793280 | DT4: 2008792.4 | DU4: =DP4*3.5% -> 966872.13 | DV4: =IF(DT4>0,DT4*20%,0) -> 401758.48 | DW4: =(CY4*3200)*DP1 -> 96000 | DX4: =(CZ4*1733)*DP1 -> 0 | DY4: =DR4-DU4-DV4-DS4-DW4-DX4 -> 154618.39 | DZ4: =DF4/DD4 -> 189.37358 | EA4: =DP4/DN4 -> 614.35124 | EB4: =DH4/(DU4+DV4+DS4+DW4) -> 1.1322654 | EC4: =DR4/(DU4+DV4+DS4+DW4+DX4) -> 1.0684785 | EE4: PH09 | EF4: 2 | EG4: 0 | EH4: 56 | EI4: 3.8778802 | EJ4: 12711 | EK4: 6732 | EL4: 999267 | EM4: 1357410 | EN4: 830117.5 | EO4: 3444254 | EP4: 2898980.5 | EQ4: 545273.5 | ER4: 5573 | ES4: 1145516 | ET4: 668323 | EU4: 54550 | EV4: 47818 | EW4: 29505387 | EX4: 25972679 | EY4: 3532708 | EZ4: 1099330 | FA4: 3059662.1 | FB4: =EW4*3.5% -> 1032688.5 | FC4: =FA4*20% -> 611932.43 | FD4: =(EF4*3200)*EW1 -> 198400 | FE4: =(EG4*1733)*EW1 -> 0 | FF4: 512253.03 | FG4: 201.63547 | FH4: 540.88702 | FI4: 1.157578 | FJ4: 1.1695947 | FN4: PH09 | FO4: 2 | FP4: 2 | FQ4: 91 | FR4: =(FT4/FQ4)/GF1 -> 3.2366562 | FS4: 16683 | FT4: 8247 | FU4: 1265120 | FV4: 1814282 | FW4: 1247205 | FX4: 6084614 | FY4: 5961969 | FZ4: =FX4-FY4 -> 122645 | GA4: 6720 | GB4: 1533163 | GC4: 1013578 | GD4: 61216 | GE4: 52969 | GF4: 32341719 | GG4: 29693868 | GH4: 2647851 | GI4: 1199250 | GJ4: 2324928.2 | GK4: 1131960.2 | GL4: 464985.64 | GM4: =(FO4*3200)*GF1 -> 179200 | GN4: =(FP4*1733)*GF1 -> 97048 | GO4: -454440.8 | GP4: 219.99297 | GQ4: 528.32134 | GR4: =FX4/(GK4+GL4+GI4+GM4) -> 2.0449763 | GS4: =GH4/(GK4+GL4+GI4+GM4+GN4) -> 0.86180616 | GV4: PH09 | GW4: 2 | GX4: 2 | GY4: 58 | GZ4: =(HB4/GY4)/HL1 -> 4.416574 | HA4: 16975 | HB4: 7941 | HC4: 1238681 | HD4: 1831129 | HE4: 1266189 | HF4: 5391677 | HG4: 5097164 | HH4: =HF4-HG4 -> 294513 | HI4: 6378 | HJ4: 1485963 | HK4: 1020087 | HL4: 69375 | HM4: 61434 | HN4: 35674099 | HO4: 32415093 | HP4: 3259006 | HQ4: 1253970 | HR4: 2951240.3 | HS4: 1248593.5 | HT4: 102961.03 | HU4: =(GW4*3200)*31 -> 198400 | HV4: =(GX4*1733)*31 -> 107446 | HW4: 314589.51 | HX4: 230.59174 | HY4: 514.22125 | HZ4: =HF4/(HS4+HT4+HQ4+HU4) -> 1.9229038 | IA4: =HP4/(HS4+HT4+HQ4+HU4+HV4) -> 1.1194061 | ID4: PH09 | IE4: 5 | IF4: 0 | IG4: 71 | IH4: =(IJ4/IG4)/IT1 -> 4.1440254 | II4: 20971 | IJ4: 9121 | IK4: 1451145 | IL4: 2090288 | IM4: 1312613.6 | IN4: 6534114.9 | IO4: 5871295.6 | IP4: =IN4-IO4 -> 662819.3 | IQ4: 7314 | IR4: 1702261 | IS4: 1040854 | IT4: 79569 | IU4: 70448 | IV4: 42115966 | IW4: 36314609 | IX4: =IV4-IW4 -> 5801357.4 | IY4: 1177430 | IZ4: 5044170.5 | JA4: =IV4*3.5% -> 1474058.8 | JB4: =IZ4*20% -> 1008834.1 | JC4: 301542 | JD4: 0 | JE4: =IX4-JA4-JB4-IY4-JC4 -> 1839492.4 | JF4: =IL4/IJ4 -> 229.17312 | JG4: =IV4/IT4 -> 529.30119 | JH4: =IL4/(JA4+JB4+IY4+JC4) -> 0.52760204 | JI4: =IX4/(JA4+JB4+IY4+JC4) -> 1.4642996 | JL4: PH09 | JM4: 6 | JN4: 0 | JO4: 78 | JP4: =(JR4/JO4)/KB1 -> 2.7837607 | JQ4: 19053 | JR4: 6514 | JS4: 1018622 | JT4: 1391848 | JU4: 802364 | JV4: 3087973 | JW4: 2335691 | JX4: =JV4-JW4 -> 752282 | JY4: 5411 | JZ4: 1110685 | KA4: 595930 | KB4: 59831 | KC4: 53317 | KD4: 32700069 | KE4: 27732806 | KF4: =KD4-KE4 -> 4967263 | KG4: 1057260 | KH4: 4611073.9 | KI4: =KD4*3.5% -> 1144502.4 | KJ4: =KH4*20% -> 922214.78 | KK4: 311940 | KL4: 0 | KM4: =KF4-KI4-KJ4-KG4-KK4 -> 1531345.8 | KN4: =JT4/JR4 -> 213.67025 | KO4: =KD4/KB4 -> 546.54057 | KP4: =JT4/(KI4+KJ4+KG4+KK4) -> 0.40508776 | KQ4: =KF4/(KI4+KJ4+KG4+KK4) -> 1.4456876 | KT4: PH09 | KU4: 6 | KV4: 0 | KW4: 231 | KX4: =(KZ4/KW4)/LJ1 -> 1.7295071 | KY4: 33171 | KZ4: 12385 | LA4: 1916641 | LB4: 2855776 | LC4: 1824188 | LD4: 8110593 | LE4: 6917018 | LF4: =LE4 -> 6917018 | LG4: 9925 | LH4: 2304912 | LI4: 1432878 | LJ4: 92176 | LK4: 79791 | LL4: 45380021 | LM4: 38099220 | LN4: 7280801 | LO4: 1477360 | LP4: 6805456.4 | LQ4: 1588300.7 | LR4: 1361091.3 | LS4: 322338 | LT4: 0 | LU4: 2531711 | LV4: 230.58345 | LW4: 492.31927 | LX4: 0.6013312 | LY4: 1.5330939 | MB4: PH09 | MC4: 7 | MD4: 0 | ME4: 306 | MF4: =(MH4/ME4)/MR1 -> 2.5518519 | MG4: 69667 | MH4: 23426 | MI4: 3480755 | MJ4: 5384982 | MK4: 3595018 | ML4: 15019924 | MM4: 12445640 | MN4: =ML4-MM4 -> 2574284.4 | MO4: 18854 | MP4: 4390192 | MQ4: 2688747 | MR4: 111717 | MS4: 88291 | MT4: 48487088 | MU4: 39856326 | MV4: =MT4-MU4 -> 8630762 | MW4: 2031430 | MX4: 8135533 | MY4: =MT4*3.5% -> 1697048.1 | MZ4: =MX4*20% -> 1627106.6 | NA4: 363930 | NB4: =MV4-MY4-MZ4-MW4-NA4 -> 2911247.3 | NC4: 0 | ND4: =MJ4/MH4 -> 229.87202 | NE4: =MT4/MR4 -> 434.0171 | NF4: =MJ4/(MY4+MZ4+MW4+NA4) -> 0.9415103 | NG4: =MV4/(MY4+MZ4+MW4+NA4) -> 1.5090025 | NJ4: PH09 | NK4: 7 | NL4: 0 | NM4: 247 | NN4: =(NP4/NM4)/NZ1 -> 3.0506726 | NO4: 55995 | NP4: 23359 | NQ4: 3334508 | NR4: 5051782 | NS4: 3245513 | NT4: 14020716 | NU4: 11195306 | NV4: =NT4-NU4 -> 2825410 | NW4: 18559 | NX4: 4048818 | NY4: 2541617 | NZ4: 117490 | OA4: =NZ4-NP4 -> 94131 | OB4: 48043927 | OC4: 40150658 | OD4: =OB4-OC4 -> 7893269 | OE4: 2231090 | OF4: 7017500.7 | OG4: =OB4*3.5% -> 1681537.4 | OH4: =OF4*20% -> 1403500.1 | OI4: 389925 | OJ4: 0 | OK4: =OD4-OG4-OH4-OE4-OI4 -> 2187216.4 | OL4: =NR4/NP4 -> 216.26705 | OM4: =OB4/NZ4 -> 408.91929 | ON4: =NR4/(OG4+OH4+OE4+OI4) -> 0.88533744 | OO4: =OD4/(OG4+OH4+OE4+OI4) -> 1.3833152 | OS4: PH09 | OT4: 7 | OU4: 365 | OV4: 84885 | OW4: 37089 | OX4: 5193519 | OY4: 7227060 | OZ4: 4253474 | PA4: 18428987 | PB4: 14729529 | PC4: 141267 | PD4: 104178 | PE4: 51384327 | PF4: 41982348 | PG4: =PE4-PF4 -> 9401979 | PH4: 3400670 | PI4: 8059405.1 | PJ4: =PE4*3.5% -> 1798451.4 | PK4: =PI4*20% -> 1611881 | PL4: =OT4*1733*PF1+1 -> 376062 | PM4: =PG4-PJ4-PK4-PH4-PL4 -> 2214914.5 | PN4: =OY4/OW4 -> 194.85724 | PO4: =PE4/PC4 -> 363.73907 | PP4: =OY4/(PH4+PJ4+PK4+PL4) -> 1.0055649 | PQ4: =PG4/(PJ4+PK4+PH4+PL4) -> 1.3081807 | PU4: PH09 | PV4: 7 | PW4: 523 | PX4: 91325 | PY4: 36534 | PZ4: 5261580 | QA4: 7247298 | QB4: 4224782 | QC4: 133093 | QD4: 96559 | QE4: 47902598 | QF4: 41952271 | QG4: 5950327 | QH4: 3697460 | QI4: 4193645.5 | QJ4: =QE4*3.5% -> 1676590.9 | QK4: =QI4*20% -> 838729.1 | QL4: =PV4*3306*QG1+1 -> 694261 | QM4: =QG4-QJ4-QK4 -> 3435007 | QN4: =PZ4/PY4 -> 144.01872 | QO4: =QE4/QC4 -> 359.91824 | QP4: =QA4/(QH4+QJ4+QK4+QL4) -> 1.0492623 | QQ4: =QG4/(QJ4+QK4) -> 2.3656342 | QR4: 披索 | QS4: 303213.11 | QT4: 5-01玩家提款：31,751.17/ 5-14玩家提款：273,883.59 + 109,767.49/ 5-16大客提款：25,021.73/ 5-24玩家提款：85,500.93 + 20,943.89 + 20,106.13/ 5-28玩家提款：105,574.71 总提款= 672,549.64 | QU4: PH09 | QV4: 6 | QW4: 97858 | QX4: 36306 | QY4: 17609748 | QZ4: 54338 | RA4: 49818115 | RB4: 43272062 | RC4: =RB4-RE4 -> 40116122 | RD4: =RA4-RC4 -> 9701992.9 | RE4: 3155940 | RF4: 5061477.3 | RG4: =RA4*3.5% -> 1743634 | RH4: =RF4*10% -> 506147.73 | RI4: =QV4*3306*31 -> 614916 | RJ4: =RD4-RG4-RH4 -> 7452211.1 | RK4: =RA4/QZ4 -> 916.81908 | RL4: =QY4/(RE4+RG4+RH4+RI4) -> 2.9248974 | RM4: =RD4/(RG4+RH4) -> 4.3124151 | RQ4: PH09 | RR4: 6 | RS4: 100622 | RT4: 30267 | RU4: 17609748 | RV4: 51424 | RW4: 44335230 | RX4: 38764713 | RY4: =RW4-RX4 -> 5570517 | RZ4: 2809020 | SA4: 0 | SB4: 4103408.8 | SC4: =RW4*3.5% -> 1551733.1 | SD4: =SB4*10% -> 410340.88 | SE4: =RR4*3306*30 -> 595080 | SF4: =RY4-SC4-SD4-SE4 -> 3013363.1 | SG4: =RW4/RV4 -> 862.15055 | SH4: =RU4/(RZ4+SC4+SD4+SE4) -> 3.2816208 | SI4: =RY4/(SC4+SD4+SE4) -> 2.178405 | SM4: PH09 | SN4: 6 | SO4: 102338 | SP4: 34205 | SQ4: 16317065 | SR4: 48451 | SS4: 45913823 | ST4: 41190794 | SU4: =SS4-ST4 -> 4723029.2 | SV4: 3323280 | SW4: 0 | SX4: 3655223 | SY4: =SS4*3.5% -> 1606983.8 | SZ4: =SX4*10% -> 365522.3 | TA4: =SN4*4000*31 -> 744000 | TB4: =SU4-SY4-SZ4-TA4 -> 2006523.1 | TC4: =SS4/SR4 -> 947.63417 | TD4: =SQ4/(SV4+SY4+SZ4+TA4) -> 2.7015964 | TE4: =SU4/(SY4+SZ4+TA4) -> 1.7386411 | TH4: PH09 | TI4: 7 | TJ4: 95013 | TK4: 32302 | TL4: 15575511 | TM4: 44925 | TN4: 39279311 | TO4: 36616179 | TP4: =TN4-TO4 -> 2663131.6 | TQ4: 3609840 | TR4: 0 | TS4: 2501870.9 | TT4: =TN4*4% -> 1571172.4 | TU4: =TS4*10% -> 250187.09 | TV4: =TI4*4000*28 -> 784000 | TW4: =TP4-TT4-TU4-TV4 -> 57772.07 | TX4: =TN4/TM4 -> 874.33079 | TY4: =TL4/(TQ4+TT4+TU4+TV4) -> 2.5060356 | TZ4: =TP4/(TT4+TU4+TV4) -> 1.0221743 | UD4: PH09 | UE4: 7 | UF4: 100544 | UG4: 32866 | UH4: 18440364 | UI4: 45284 | UJ4: 42920731 | UK4: 39723751 | UL4: =UJ4-UK4 -> 3196979.7 | UM4: 3285990 | UN4: 0 | UO4: 2318924 | UP4: =UJ4*4% -> 1716829.2 | UQ4: =UO4*10% -> 231892.39 | UR4: =UE4*4000*31 -> 868000 | US4: =UL4-UP4-UQ4-UR4 -> 380258.06 | UT4: =UJ4/UI4 -> 947.81227 | UU4: =UH4/(UM4+UP4+UQ4+UR4) -> 3.0216672 | UV4: =UL4/(UP4+UQ4+UR4) -> 1.1350002 | UZ4: PH09 | VA4: 7 | VB4: 94446 | VC4: 31254 | VD4: 18784599 | VE4: 41725 | VF4: 42382252 | VG4: 42892684 | VH4: =VF4-VG4 -> -510432.02 | VI4: 2865865 | VJ4: 0 | VK4: -1362500.4 | VL4: =VF4*4% -> 1695290.1 | VM4: 0 | VN4: =VA4*4000*31 -> 868000 | VO4: =VH4-VL4-VM4-VN4 -> -3073722.1 | VP4: =VF4/VE4 -> 1015.752 | VQ4: =VD4/(VI4+VL4+VM4+VN4) -> 3.4599488 | VR4: =VH4/(VL4+VM4+VN4) -> -0.19913159
C5: PH09-2 | AJ5: PH09-2 | BQ5: PH09-2 | BR5: 1 | BS5: 2 | BT5: 14 | BU5: 1.1428571 | BV5: 904 | BW5: 496 | BX5: 74657 | BY5: 770219 | BZ5: 80032 | CA5: 228677 | CB5: 195273 | CC5: 33404 | CD5: 427 | CE5: 88414 | CF5: 71196 | CG5: 3363 | CH5: 2867 | CI5: 1882774 | CJ5: 1454411 | CK5: =CI5-CJ5 -> 428363 | CL5: 55620 | CM5: 417270.92 | CN5: =CI5*3.5% -> 65897.09 | CO5: =IF(CM5>0,CM5*20%,0) -> 83454.184 | CP5: =(BR5*3200)*CI1 -> 99200 | CQ5: =(BS5*1733)*CI1 -> 107446 | CR5: =CK5-CN5-CO5-CL5-CP5-CQ5 -> 16745.726 | CS5: =BY5/BW5 -> 1552.8609 | CT5: =CI5/CG5 -> 559.84954 | CU5: =CA5/(CN5+CO5+CL5+CP5) -> 0.75180341 | CV5: =CK5/(CN5+CO5+CL5+CP5+CQ5) -> 1.0406828 | CX5: PH09-2 | CY5: 1 | CZ5: 2 | DA5: 19 | DB5: 1.4105263 | DC5: 1599 | DD5: 804 | DE5: 133621 | DF5: 679684 | DG5: 119260.95 | DH5: 437733 | DI5: 386719.95 | DJ5: =DH5-DI5 -> 51013.05 | DK5: 715 | DL5: 157493 | DM5: 108568.95 | DN5: 4678 | DO5: 3874 | DP5: 2231956 | DQ5: 1929115 | DR5: =DP5-DQ5 -> 302841 | DS5: 125950 | DT5: 259760.52 | DU5: =DP5*3.5% -> 78118.46 | DV5: =IF(DT5>0,DT5*20%,0) -> 51952.104 | DW5: =(CY5*3200)*DP1 -> 96000 | DX5: =(CZ5*1733)*DP1 -> 103980 | DY5: =DR5-DU5-DV5-DS5-DW5-DX5 -> -153159.56 | DZ5: =DF5/DD5 -> 845.37811 | EA5: =DP5/DN5 -> 477.11757 | EB5: =DH5/(DU5+DV5+DS5+DW5) -> 1.243487 | EC5: =DR5/(DU5+DV5+DS5+DW5+DX5) -> 0.66412418 | EE5: PH09-2 | EF5: 2 | EG5: 2 | EH5: 35 | EI5: 2.1898618 | EJ5: 4029 | EK5: 2376 | EL5: 353665 | EM5: 999267 | EN5: 266444 | EO5: 1012728 | EP5: 944540 | EQ5: 68188 | ER5: 2123 | ES5: 409413 | ET5: 239059 | EU5: 8699 | EV5: 6323 | EW5: 3565118 | EX5: 3042028 | EY5: 523090 | EZ5: 325240 | FA5: 460089.75 | FB5: 124779.13 | FC5: 92017.95 | FD5: =(EF5*3200)*EW1 -> 198400 | FE5: =(EG5*1733)*EW1 -> 107446 | FF5: -357839.08 | FG5: 420.56692 | FH5: 409.83079 | FI5: 1.3093085 | FJ5: 0.59379354 | FN5: PH09-2 | FO5: 2 | FP5: 2 | FQ5: 83 | FR5: =(FT5/FQ5)/GF1 -> 1.4229776 | FS5: 6443 | FT5: 3307 | FU5: 498795 | FV5: 1265120 | FW5: 453577 | FX5: 2727613 | FY5: 2873199 | FZ5: =FX5-FY5 -> -145586 | GA5: 2960 | GB5: 654904 | GC5: 409155 | GD5: 9792 | GE5: 6485 | GF5: 4306772 | GG5: 4383429 | GH5: -76657 | GI5: 255860 | GJ5: -172308.86 | GK5: 150737.02 | GL5: 0 | GM5: =(FO5*3200)*GF1 -> 179200 | GN5: =(FP5*1733)*GF1 -> 97048 | GO5: -789350.02 | GP5: 382.55821 | GQ5: 439.82557 | GR5: =FX5/(GK5+GL5+GI5+GM5) -> 4.6562425 | GS5: =GH5/(GK5+GL5+GI5+GM5+GN5) -> -0.1122612 | GV5: PH09-2 | GW5: 2 | GX5: 2 | GY5: 36 | GZ5: =(HB5/GY5)/HL1 -> 1.4139785 | HA5: 2993 | HB5: 1578 | HC5: 255690.22 | HD5: 305587 | HE5: 194082 | HF5: 815845 | HG5: 753481 | HH5: =HF5-HG5 -> 62364 | HI5: 1400 | HJ5: 262974 | HK5: 165798 | HL5: 5985 | HM5: 4407 | HN5: 2556760 | HO5: 2361932 | HP5: 194828 | HQ5: 106910 | HR5: 141617.22 | HS5: 89486.6 | HT5: 29721.344 | HU5: =(GW5*3200)*31 -> 198400 | HV5: =(GX5*1733)*31 -> 107446 | HW5: -370181.94 | HX5: 193.65463 | HY5: 427.19465 | HZ5: =HF5/(HS5+HT5+HQ5+HU5) -> 1.9218151 | IA5: =HP5/(HS5+HT5+HQ5+HU5+HV5) -> 0.36624287 | ID5: PH09-2 | IE5: 3 | IF5: 0 | IG5: 12 | IH5: =(IJ5/IG5)/IT1 -> 2.827957 | II5: 1883 | IJ5: 1052 | IK5: 147230 | IL5: 205763 | IM5: 125749 | IN5: 669065 | IO5: 641032 | IP5: =IN5-IO5 -> 28033 | IQ5: 932 | IR5: 177738 | IS5: 106734 | IT5: 5103 | IU5: 4051 | IV5: 2020978 | IW5: 1948689 | IX5: =IV5-IW5 -> 72289 | IY5: 75390 | IZ5: 46636.22 | JA5: =IV5*3.5% -> 70734.23 | JB5: =IZ5*20% -> 9327.244 | JC5: 161169 | JD5: 0 | JE5: =IX5-JA5-JB5-IY5-JC5 -> -244331.47 | JF5: =IL5/IJ5 -> 195.59221 | JG5: =IV5/IT5 -> 396.03723 | JH5: =IL5/(JA5+JB5+IY5+JC5) -> 0.64987269 | JI5: =IX5/(JA5+JB5+IY5+JC5) -> 0.22831436 | JL5: PH09-2 | JM5: 3 | JN5: 20 | JO5: 20 | JQ5: 1523 | JR5: 678 | JS5: 95981 | JT5: 133890 | JU5: 164430 | JV5: 295242 | JW5: 289044 | JX5: =JV5-JW5 -> 6198 | JY5: 544 | JZ5: 111429 | KA5: 92666 | KB5: 3880 | KC5: 3202 | KD5: 2678181 | KE5: 2233875 | KF5: =KD5-KE5 -> 444306 | KG5: 51780 | KH5: 479051.04 | KI5: =KD5*3.5% -> 93736.335 | KJ5: =KH5*20% -> 95810.208 | KK5: 155970 | KM5: =KF5-KI5-KJ5-KG5-KK5 -> 47009.457 | KN5: =JT5/JR5 -> 197.47788 | KO5: =KD5/KB5 -> 690.25284 | KP5: =JT5/(KI5+KJ5+KG5+KK5) -> 0.33700268 | KQ5: =KF5/(KI5+KJ5+KG5+KK5) -> 1.1183233 | KT5: PH09-2 | KU5: 3 | KW5: 71 | KY5: 3316 | KZ5: 1502 | LA5: 229851 | LB5: 331889 | LC5: 202390 | LD5: 815147 | LE5: 763027 | LF5: =LE5 -> 763027 | LG5: 1298 | LH5: 371405 | LI5: 229110 | LJ5: 6314 | LK5: 4812 | LL5: 3814842 | LM5: 4684513 | LN5: -869671 | LO5: 115140 | LP5: -871493.86 | LQ5: 133519.47 | LR5: 0 | LS5: 161169 | LU5: -1279499.5 | LV5: 220.96471 | LW5: 604.18784 | LX5: 0.80982417 | LY5: -2.1220366 | MB5: PH09-2 | MC5: 3 | ME5: 67 | MG5: 4654 | MH5: 2314 | MI5: 333138 | MJ5: 487443 | MK5: 333562 | ML5: 1353002 | MM5: 1025636 | MO5: 1975 | MP5: 407146 | MQ5: 265630 | MR5: 7517 | MS5: 5203 | MT5: 4683703 | MU5: 4058748 | MV5: =MT5-MU5 -> 624955 | MW5: 144420 | MX5: 574115.84 | MY5: =MT5*3.5% -> 163929.61 | MZ5: =MX5*20% -> 114823.17 | NA5: 169834 | NB5: =MV5-MY5-MZ5-MW5-NA5 -> 31948.227 | ND5: =MJ5/MH5 -> 210.64952 | NE5: =MT5/MR5 -> 623.08142 | NF5: =MJ5/(MY5+MZ5+MW5+NA5) -> 0.82198555 | NG5: =MV5/(MY5+MZ5+MW5+NA5) -> 1.053875 | NJ5: PH09-2 | NK5: 4 | NM5: 41 | NO5: 5663 | NP5: 2745 | NQ5: 390205 | NR5: 518864 | NS5: 347208 | NT5: 1235386 | NU5: 1041962 | NW5: 2337 | NX5: 438127 | NY5: 277775 | NZ5: 8156 | OA5: =NZ5-NP5 -> 5411 | OB5: 5423344 | OC5: 4603109 | OD5: =OB5-OC5 -> 820235 | OE5: 281580 | OF5: 673216.25 | OG5: =OB5*3.5% -> 189817.04 | OH5: =OF5*20% -> 134643.25 | OI5: 183698 | OK5: =OD5-OG5-OH5-OE5-OI5 -> 30496.71 | OL5: =NR5/NP5 -> 189.02149 | OM5: =OB5/NZ5 -> 664.95145 | ON5: =NR5/(OG5+OH5+OE5+OI5) -> 0.65700753 | OO5: =OD5/(OG5+OH5+OE5+OI5) -> 1.0386162 | OS5: PH09-2 | OT5: 2 | OU5: 57 | OV5: 7033 | OW5: 3511 | OX5: 508500 | OY5: 693167 | OZ5: 439928 | PA5: 1519533 | PB5: 1256288 | PC5: 9177 | PD5: 5666 | PE5: 4220235 | PF5: 3450673 | PG5: =PE5-PF5 -> 769562 | PH5: 318780 | PI5: 608186.35 | PJ5: =PE5*3.5% -> 147708.23 | PK5: =PI5*20% -> 121637.27 | PL5: =OT5*1733*PF1+1 -> 107447 | PM5: =PG5-PJ5-PK5-PH5-PL5 -> 73989.505 | PN5: =OY5/OW5 -> 197.42723 | PO5: =PE5/PC5 -> 459.87087 | PP5: =OY5/(PH5+PJ5+PK5+PL5) -> 0.9965417 | PQ5: =PG5/(PJ5+PK5+PH5+PL5) -> 1.1063721 | PU5: PH09-2 | PV5: 2 | PW5: 53 | PX5: 5332 | PY5: 2554 | PZ5: 385053 | QA5: 499804 | QB5: 294573 | QC5: 6940 | QD5: 4386 | QE5: 2509660 | QF5: 1929332 | QG5: 580328 | QH5: 215310 | QI5: 490437.98 | QJ5: =QE5*3.5% -> 87838.1 | QK5: =QI5*20% -> 98087.596 | QL5: =PV5*3306*QG1+1 -> 198361 | QM5: =QG5-QJ5-QK5 -> 394402.3 | QN5: =PZ5/PY5 -> 150.76468 | QO5: =QE5/QC5 -> 361.62248 | QP5: =QA5/(QH5+QJ5+QK5+QL5) -> 0.83356697 | QQ5: =QG5/(QJ5+QK5) -> 3.1212899 | QR5: 披索 | QT5: 5-01玩家提款：65,094.67/ 5-08玩家提款：77,014.39/ 5-22玩家提款：252,050.63/ 5-23玩家提款：721,994.11/ 5-24玩家提款：60,033.37/ 5-26玩家提款：106,918.90/ 5-28玩家提款：304,456.94 + 22,787.90 + 19,658.99 + 11,607.59 总提款：1,641,617.49 | QU5: PH09-2 | QV5: 2 | QW5: 5867 | QX5: 2582 | QY5: 1119036 | QZ5: 3407 | RA5: 5571451 | RB5: 5219226 | RC5: =RB5-RE5 -> 5047996 | RD5: =RA5-RB5 -> 352225 | RE5: 171230 | RF5: 218489.14 | RG5: =RA5*3.5% -> 195000.79 | RH5: =RF5*10% -> 21848.914 | RI5: =QV5*3306*31 -> 204972 | RJ5: =RD5-RG5-RH5 -> 135375.3 | RK5: =RA5/QZ5 -> 1635.2953 | RL5: =QY5/(RE5+RG5+RH5+RI5) -> 1.8869114 | RM5: =RD5/(RG5+RH5) -> 1.6242817 | RQ5: PH09-2 | RR5: 2 | RS5: 8051 | RT5: 3610 | RU5: 1119036 | RV5: 4382 | RW5: 3661277 | RX5: 3481353 | RY5: =RW5-RX5 -> 179924 | RZ5: 261770 | SA5: 0 | SB5: 7764.48 | SC5: =RW5*3.5% -> 128144.7 | SD5: =SB5*10% -> 776.448 | SE5: =RR5*3306*30 -> 198360 | SF5: =RY5-SC5-SD5-SE5 -> -147357.14 | SG5: =RW5/RV5 -> 835.52647 | SH5: =RU5/(RZ5+SC5+SD5+SE5) -> 1.8997264 | SI5: =RY5/(SC5+SD5+SE5) -> 0.54975364 | SM5: PH09-2 | SN5: 5 | SO5: 9472 | SP5: 3162 | SQ5: 1352512 | SR5: 3892 | SS5: 2121794.5 | ST5: 2039753 | SU5: =SS5-ST5 -> 82041.46 | SV5: 223470 | SW5: 0 | SX5: -32292.7 | SY5: =SS5*3.5% -> 74262.806 | SZ5: 0 | TA5: =SN5*4000*31 -> 620000 | TB5: =SU5-SY5-SZ5-TA5 -> -612221.35 | TC5: =SS5/SR5 -> 545.16816 | TD5: =SQ5/(SV5+SY5+SZ5+TA5) -> 1.4737536 | TE5: =SU5/(SY5+SZ5+TA5) -> 0.11817061 | TH5: PH09-2 | TI5: 6 | TJ5: 13676 | TK5: 5603 | TL5: 2166197.1 | TM5: 6086 | TN5: 2643162.4 | TO5: 2997447 | TP5: =TN5-TO5 -> -354284.6 | TQ5: 563590 | TR5: 0 | TS5: -364961.34 | TT5: =TN5*4% -> 105726.5 | TU5: 0 | TV5: =TI5*4000*28 -> 672000 | TW5: =TP5-TT5-TU5-TV5 -> -1132011.1 | TX5: =TN5/TM5 -> 434.30207 | TY5: =TL5/(TQ5+TT5+TU5+TV5) -> 1.6149784 | TZ5: =TP5/(TT5+TU5+TV5) -> -0.45553881 | UD5: PH09-2 | UE5: 4 | UF5: 7872 | UG5: 2386 | UH5: 921287 | UI5: 2386 | UJ5: 921287 | UK5: 916839 | UL5: =UJ5-UK5 -> 4448 | UM5: 148720 | UN5: 0 | UO5: -76572.68 | UP5: =UJ5*4% -> 36851.48 | UQ5: 0 | UR5: =UE5*4000*21 -> 336000 | US5: =UL5-UP5-UQ5-UR5 -> -368403.48 | UT5: =UJ5/UI5 -> 386.12196 | UU5: =UH5/(UM5+UP5+UQ5+UR5) -> 1.7663677 | UV5: =UL5/(UP5+UQ5+UR5) -> 0.011929683 | UW5: 1月11-31 | UZ5: PH09-2 | VH5: =VF5-VG5 -> 0 | VL5: =VF5*4% -> 0 | VM5: 0 | VN5: =VA5*4000*0 -> 0 | VO5: =VH5-VL5-VM5-VN5 -> 0 | VP5: =VF5/VE5 -> #DIV/0! | VQ5: =VD5/(VI5+VL5+VM5+VN5) -> #DIV/0! | VR5: =VH5/(VL5+VM5+VN5) -> #DIV/0! | VS5: 未开始
C6: PH25 | D6: 2 | E6: 4 | F6: ='PH25'!AJ4 -> 37 | G6: =(I6/F6)/S1 -> 2.6320166 | H6: ='PH25'!G4 -> 5130 | I6: ='PH25'!H4 -> 2532 | J6: ='PH25'!T4 -> 395999 | K6: ='PH25'!U4 -> 571810 | L6: ='PH25'!V4 -> 367848.8 | M6: =123553+1104499 -> 1228052 | N6: =88851+794379.8 -> 883230.8 | O6: =M6-N6 -> 344821.2 | P6: ='PH25'!J4 -> 2220 | Q6: ='PH25'!R4 -> 493879 | R6: ='PH25'!S4 -> 312594.8 | S6: ='PH25'!K4 -> 9423 | T6: =S6-I6 -> 6891 | U6: ='PH25'!W4 -> 4127611 | V6: ='PH25'!X4 -> 3335808.5 | W6: =U6-V6 -> 791802.51 | X6: ='PH25'!D4 -> 456003 | Y6: =326770.39+338089.67 -> 664860.06 | Z6: =U6*3.5% -> 144466.39 | AA6: =IF(Y6>0,Y6*20%,0) -> 132972.01 | AB6: =(D6*3200)*S1 -> 166400 | AC6: =(E6*1733)*S1 -> 180232 | AD6: =W6-Z6-AA6-X6-AB6-AC6 -> -288270.89 | AE6: =K6/I6 -> 225.83333 | AF6: =U6/S6 -> 438.03576 | AG6: =M6/(Z6+AA6+X6+AB6+AC6) -> 1.1370079 | AH6: =W6/(Z6+AA6+X6+AB6+AC6) -> 0.73310065 | AJ6: PH25 | AK6: 1 | AL6: 4 | AM6: 47 | AN6: =(AP6/AM6)/AZ1 -> 2.2120567 | AO6: 6705 | AP6: 3119 | AQ6: 453158 | AR6: 645933 | AS6: 387840.71 | AT6: 1333826 | AU6: 1086636.9 | AV6: =AT6-AU6 -> 247189.06 | AW6: 587951 | AX6: 587951 | AY6: 332130.75 | AZ6: 10789 | BA6: 7670 | BB6: 4735492 | BC6: 3777767.9 | BD6: =BB6-BC6 -> 957724.06 | BE6: 583747 | BF6: 830927.38 | BG6: =BB6*3.5% -> 165742.22 | BH6: =IF(BF6>0,BF6*20%,0) -> 166185.48 | BI6: =(AK6*3200)*AZ1 -> 96000 | BJ6: =(AL6*1733)*AZ1 -> 207960 | BK6: =BD6-BG6-BH6-BE6-BI6-BJ6 -> -261910.64 | BL6: =AR6/AP6 -> 207.09618 | BM6: =BB6/AZ6 -> 438.91853 | BN6: =AT6/(BG6+BH6+BE6+BI6) -> 1.3184337 | BO6: =BD6/(BG6+BH6+BE6+BI6+BJ6) -> 0.78525485 | BQ6: PH25 | BR6: 1 | BS6: 4 | BT6: 106 | BU6: 0.6923311 | BV6: 4632 | BW6: 2275 | BX6: 347172 | BY6: 486170 | BZ6: 267943.25 | CA6: 1217065 | CB6: 851211.25 | CC6: 365853.75 | CD6: 2007 | CE6: 424959 | CF6: 224939.25 | CG6: 9765 | CH6: 7490 | CI6: 5128130 | CJ6: 3883989 | CK6: =CI6-CJ6 -> 1244141 | CL6: 185570 | CM6: 1029091.4 | CN6: =CI6*3.5% -> 179484.55 | CO6: =IF(CM6>0,CM6*20%,0) -> 205818.29 | CP6: =(BR6*3200)*CI1 -> 99200 | CQ6: =(BS6*1733)*CI1 -> 214892 | CR6: =CK6-CN6-CO6-CL6-CP6-CQ6 -> 359176.16 | CS6: =BY6/BW6 -> 213.7011 | CT6: =CI6/CG6 -> 525.15412 | CU6: =CA6/(CN6+CO6+CL6+CP6) -> 1.8163175 | CV6: =CK6/(CN6+CO6+CL6+CP6+CQ6) -> 1.4058649 | CX6: PH25 | CY6: 0 | CZ6: 4 | DA6: 44 | DB6: 1.1575758 | DC6: 2984 | DD6: 1528 | DE6: 242580 | DF6: 329527 | DG6: 150434 | DH6: 765361 | DI6: 605872.07 | DJ6: =DH6-DI6 -> 159488.93 | DK6: 1297 | DL6: 273650 | DM6: 118785 | DN6: 9321 | DO6: 7793 | DP6: 4943536 | DQ6: 4132905 | DR6: =DP6-DQ6 -> 810631 | DS6: 242440 | DT6: 675976.49 | DU6: =DP6*3.5% -> 173023.76 | DV6: =IF(DT6>0,DT6*20%,0) -> 135195.3 | DW6: =(CY6*3200)*DP1 -> 0 | DX6: =(CZ6*1733)*DP1 -> 207960 | DY6: =DR6-DU6-DV6-DS6-DW6-DX6 -> 52011.942 | DZ6: =DF6/DD6 -> 215.65903 | EA6: =DP6/DN6 -> 530.36541 | EB6: =DH6/(DU6+DV6+DS6+DW6) -> 1.3899 | EC6: =DR6/(DU6+DV6+DS6+DW6+DX6) -> 1.0685613 | EE6: PH25 | EF6: 0 | EG6: 4 | EH6: 111 | EI6: 1.0340017 | EJ6: 6931 | EK6: 3558 | EL6: 555272 | EM6: 811949 | EN6: 461373.36 | EO6: 2026992 | EP6: 1742704.3 | EQ6: 284287.71 | ER6: 3083 | ES6: 712507 | ET6: 401116.76 | EU6: 14949 | EV6: 11391 | EW6: 6199233 | EX6: 5234837 | EY6: 964396 | EZ6: 486740 | FA6: 755538.81 | FB6: 216973.15 | FC6: 151107.76 | FD6: =(EF6*3200)*EW1 -> 0 | FE6: =(EG6*1733)*EW1 -> 214892 | FF6: -122646.92 | FG6: 228.20377 | FH6: 414.69215 | FI6: 2.3712475 | FJ6: 0.8871738 | FN6: PH25 | FO6: 0 | FP6: 5 | FQ6: 134 | FR6: =(FT6/FQ6)/GF1 -> 1.0013326 | FS6: 7766 | FT6: 3757 | FU6: 634256 | FV6: 909212 | FW6: 551697.2 | FX6: 2370398 | FY6: 1919135.2 | FZ6: =FX6-FY6 -> 451262.8 | GA6: 3212 | GB6: 771945 | GC6: 468516.2 | GD6: 14130 | GE6: 10373 | GF6: 6007821 | GG6: 5086933 | GH6: 920888 | GI6: 402970 | GJ6: 694386.66 | GK6: 210273.73 | GL6: 138877.33 | GM6: =(FO6*3200)*GF1 -> 0 | GN6: =(FP6*1733)*GF1 -> 242620 | GO6: -73853.067 | GP6: 242.00479 | GQ6: 425.18195 | GR6: =FX6/(GK6+GL6+GI6+GM6) -> 3.1516176 | GS6: =GH6/(GK6+GL6+GI6+GM6+GN6) -> 0.92575649 | GV6: PH25 | GW6: 1 | GX6: 4 | GY6: 110 | GZ6: =(HB6/GY6)/HL1 -> 0.84780059 | HA6: 6316 | HB6: 2891 | HC6: 460409 | HD6: 661223 | HE6: 421698 | HF6: 1595349 | HG6: 1270410 | HH6: =HF6-HG6 -> 324939 | HI6: 2439 | HJ6: 558544 | HK6: 346814 | HL6: 13540 | HM6: 10649 | HN6: 5612292 | HO6: 4683256 | HP6: 929036 | HQ6: 325250 | HR6: 763210.47 | HS6: 196430.22 | HT6: 53058.224 | HU6: =(GW6*3200)*31 -> 99200 | HV6: =(GX6*1733)*31 -> 214892 | HW6: 23682.556 | HX6: 228.71774 | HY6: 414.49719 | HZ6: =HF6/(HS6+HT6+HQ6+HU6) -> 2.3672028 | IA6: =HP6/(HS6+HT6+HQ6+HU6+HV6) -> 1.0452342 | ID6: PH25 | IE6: 5 | IF6: 0 | IG6: 104 | IH6: =(IJ6/IG6)/IT1 -> 1.0970844 | II6: 7609 | IJ6: 3537 | IK6: 540964.95 | IL6: 849098.95 | IM6: 533234 | IN6: 2451843.9 | IO6: 1859254 | IP6: =IN6-IO6 -> 592589.89 | IQ6: 3015 | IR6: 722404.99 | IS6: 406182 | IT6: 16869 | IU6: 13332 | IV6: 6927873.5 | IW6: 5478456 | IX6: =IV6-IW6 -> 1449417.5 | IY6: 368840 | IZ6: 1198363.1 | JA6: =IV6*3.5% -> 242475.57 | JB6: =IZ6*20% -> 239672.62 | JC6: 214892 | JD6: 0 | JE6: =IX6-JA6-JB6-IY6-JC6 -> 383537.32 | JF6: =IL6/IJ6 -> 240.0619 | JG6: =IV6/IT6 -> 410.68667 | JH6: =IL6/(JA6+JB6+IY6+JC6) -> 0.79661763 | JI6: =IX6/(JA6+JB6+IY6+JC6) -> 1.3598316 | JL6: PH25 | JM6: 5 | JN6: 0 | JO6: 145 | JP6: =(JR6/JO6)/KB1 -> 0.72551724 | JQ6: 7112 | JR6: 3156 | JS6: 461749 | JT6: 685804 | JU6: 460636 | JV6: 1732351 | JW6: 1392244 | JX6: =JV6-JW6 -> 340107 | JY6: 2711 | JZ6: 594570 | KA6: 386307 | KB6: 14859 | KC6: 11703 | KD6: 5692022 | KE6: 4766810 | KF6: =KD6-KE6 -> 925212 | KG6: 229600 | KH6: 676202.99 | KI6: =KD6*3.5% -> 199220.77 | KJ6: =KH6*20% -> 135240.6 | KK6: 246086 | KL6: 0 | KM6: =KF6-KI6-KJ6-KG6-KK6 -> 115064.63 | KN6: =JT6/JR6 -> 217.30165 | KO6: =KD6/KB6 -> 383.06898 | KP6: =JT6/(KI6+KJ6+KG6+KK6) -> 0.84651759 | KQ6: =KF6/(KI6+KJ6+KG6+KK6) -> 1.1420293 | KT6: PH25 | KU6: 5 | KV6: 0 | KW6: 155 | KX6: =(KZ6/KW6)/LJ1 -> 0.89469303 | KY6: 11017 | KZ6: 4299 | LA6: 607818 | LB6: 901094 | LC6: 649885.48 | LD6: 2488573 | LE6: 2179589.5 | LF6: =LE6 -> 2179589.5 | LG6: 3542 | LH6: 746219 | LI6: 492562.48 | LJ6: 20676 | LK6: 16377 | LL6: 7535790 | LM6: 6726566 | LN6: 809224 | LO6: 294730 | LP6: 382300.48 | LQ6: 263752.65 | LR6: 76460.096 | LS6: 254751 | LT6: 0 | LU6: -80469.746 | LV6: 209.60549 | LW6: 364.4704 | LX6: 1.0128137 | LY6: 0.90955343 | MB6: PH25 | MC6: 5 | MD6: 0 | ME6: 131 | MF6: =(MH6/ME6)/MR1 -> 1.540458 | MG6: 13408 | MH6: 6054 | MI6: 873944 | MJ6: 1257282 | MK6: 869933 | ML6: 3730819 | MM6: 2872836 | MN6: =ML6-MM6 -> 857983 | MO6: 5044 | MP6: 1045272 | MQ6: 729309 | MR6: 22982 | MS6: 16928 | MT6: 7954185 | MU6: 6396257 | MV6: =MT6-MU6 -> 1557928 | MW6: 447520 | MX6: 1233347.1 | MY6: =MT6*3.5% -> 278396.47 | MZ6: =MX6*20% -> 246669.41 | NA6: 259950 | NB6: =MV6-MY6-MZ6-MW6-NA6 -> 325392.11 | NC6: 0 | ND6: =MJ6/MH6 -> 207.6779 | NE6: =MT6/MR6 -> 346.105 | NF6: =MJ6/(MY6+MZ6+MW6+NA6) -> 1.0200774 | NG6: =MV6/(MY6+MZ6+MW6+NA6) -> 1.2640021 | NJ6: PH25 | NK6: 5 | NL6: 0 | NM6: 123 | NN6: =(NP6/NM6)/NZ1 -> 1.9470233 | NO6: 13747 | NP6: 7424 | NQ6: 1051397 | NR6: 1494151 | NS6: 889205 | NT6: 4337990 | NU6: 3520123 | NV6: =NT6-NU6 -> 817867 | NW6: 6084 | NX6: 1232526 | NY6: 716620 | NZ6: 24614 | OA6: =NZ6-NP6 -> 17190 | OB6: 7765222 | OC6: 6249417 | OD6: =OB6-OC6 -> 1515805 | OE6: 580460 | OF6: 1132100.3 | OG6: =OB6*3.5% -> 271782.77 | OH6: =OF6*20% -> 226420.07 | OI6: 202761 | OJ6: 0 | OK6: =OD6-OG6-OH6-OE6-OI6 -> 234381.16 | OL6: =NR6/NP6 -> 201.25956 | OM6: =OB6/NZ6 -> 315.47989 | ON6: =NR6/(OG6+OH6+OE6+OI6) -> 1.1660084 | OO6: =OD6/(OG6+OH6+OE6+OI6) -> 1.1829068 | OS6: PH25 | OT6: 5 | OU6: 93 | OV6: 17608 | OW6: 8174 | OX6: 1137991 | OY6: 1579435 | OZ6: 1082183 | PA6: 4162836 | PB6: 3914757 | PC6: 20460 | PD6: 12286 | PE6: 6338672 | PF6: 5888646 | PG6: =PE6-PF6 -> 450026 | PH6: 703870 | PI6: 94517.98 | PJ6: =PE6*3.5% -> 221853.52 | PK6: =PI6*20% -> 18903.596 | PL6: =OT6*1733*PF1+1 -> 268616 | PM6: =PG6-PJ6-PK6-PH6-PL6 -> -763217.12 | PN6: =OY6/OW6 -> 193.22669 | PO6: =PE6/PC6 -> 309.80802 | PP6: =OY6/(PH6+PJ6+PK6+PL6) -> 1.3018289 | PQ6: =PG6/(PJ6+PK6+PH6+PL6) -> 0.37092813 | PU6: PH25 | PV6: 5 | PW6: 74 | PX6: 5002 | PY6: 2154 | PZ6: 325352 | QA6: 433141 | QB6: 243203 | QC6: 7320 | QD6: 5166 | QE6: 2672222 | QF6: 2353291 | QG6: 318931 | QH6: 100050 | QI6: 195643.63 | QJ6: =QE6*3.5% -> 93527.77 | QK6: =QI6*20% -> 39128.726 | QL6: =PV6*3306*QG1+1 -> 495901 | QM6: =QG6-QJ6-QK6 -> 186274.5 | QN6: =PZ6/PY6 -> 151.0455 | QO6: =QE6/QC6 -> 365.05765 | QP6: =QA6/(QH6+QJ6+QK6+QL6) -> 0.59447783 | QQ6: =QG6/(QJ6+QK6) -> 2.4041868 | QR6: 披索 | QT6: 5-18玩家提款：10,236.73/ 5-23玩家提款：21,365.99/ 5-27玩家提款：20,993.34 总提款：52,596.06 | QU6: PH25 | QV6: 3 | QW6: 9095 | QX6: 2690 | QY6: 1436957 | QZ6: 3741 | RA6: 3457151 | RB6: 2777362 | RC6: =RB6-RE6 -> 2619292 | RD6: =RA6-RB6 -> 679789 | RE6: 158070 | RF6: 567308.18 | RG6: =RA6*3.5% -> 121000.29 | RH6: =RF6*10% -> 56730.818 | RI6: =QV6*3306*31 -> 307458 | RJ6: =RD6-RG6-RH6 -> 502057.9 | RK6: =RA6/QZ6 -> 924.12483 | RL6: =QY6/(RE6+RG6+RH6+RI6) -> 2.2338697 | RM6: =RD6/(RG6+RH6) -> 3.8248173 | RQ6: PH25 | RR6: 3 | RS6: 9571 | RT6: 2972 | RU6: 1483546 | RV6: 3976 | RW6: 3698674 | RX6: 3965456 | RY6: =RW6-RX6 -> -266782.01 | RZ6: 172230 | SA6: 0 | SB6: -427399.82 | SC6: =RW6*3.5% -> 129453.59 | SD6: 0 | SE6: =RR6*3306*30 -> 297540 | SF6: =RY6-SC6-SD6-SE6 -> -693775.6 | SG6: =RW6/RV6 -> 930.25 | SH6: =RU6/(RZ6+SC6+SD6+SE6) -> 2.4757804 | SI6: =RY6/(SC6+SD6+SE6) -> -0.6247916 | SM6: PH25 | SN6: 4 | SO6: 9342 | SP6: 2508 | SQ6: 1513168 | SR6: 3575 | SS6: 3212716.2 | ST6: 3233549 | SU6: =SS6-ST6 -> -20832.83 | SV6: 171630 | SW6: 0 | SX6: -138896.98 | SY6: =SS6*3.5% -> 112445.07 | SZ6: 0 | TA6: =SN6*4000*31 -> 496000 | TB6: =SU6-SY6-SZ6-TA6 -> -629277.9 | TC6: =SS6/SR6 -> 898.66187 | TD6: =SQ6/(SV6+SY6+SZ6+TA6) -> 1.9397723 | TE6: =SU6/(SY6+SZ6+TA6) -> -0.034239459 | TH6: PH25 | TI6: 4 | TJ6: 12618 | TK6: 4504 | TL6: 2135920 | TM6: 5483 | TN6: 3312495.9 | TO6: 3299113 | TP6: =TN6-TO6 -> 13382.89 | TQ6: 490980 | TR6: 0 | TS6: -133796.78 | TT6: =TN6*4% -> 132499.84 | TU6: 0 | TV6: =TI6*4000*28 -> 448000 | TW6: =TP6-TT6-TU6-TV6 -> -567116.95 | TX6: =TN6/TM6 -> 604.13932 | TY6: =TL6/(TQ6+TT6+TU6+TV6) -> 1.9934299 | TZ6: =TP6/(TT6+TU6+TV6) -> 0.023054081 | UD6: PH25 | UE6: 4 | UF6: 12769 | UG6: 5071 | UH6: 2872205.2 | UI6: 5126 | UJ6: 3012780.2 | UK6: 3259643 | UL6: =UJ6-UK6 -> -246862.76 | UM6: 310385 | UN6: 0 | UO6: -349214.9 | UP6: =UJ6*4% -> 120511.21 | UQ6: 0 | UR6: =UE6*4000*31 -> 496000 | US6: =UL6-UP6-UQ6-UR6 -> -863373.97 | UT6: =UJ6/UI6 -> 587.74488 | UU6: =UH6/(UM6+UP6+UQ6+UR6) -> 3.0987345 | UV6: =UL6/(UP6+UQ6+UR6) -> -0.40041893 | UZ6: PH25 | VA6: 4 | VB6: 311 | VC6: 132 | VD6: 49133 | VE6: 132 | VF6: 49133 | VG6: 45506 | VH6: =VF6-VG6 -> 3627 | VI6: 0 | VJ6: 0 | VK6: -577.76 | VL6: =VF6*4% -> 1965.32 | VM6: 0 | VN6: =VA6*4000*7 -> 112000 | VO6: =VH6-VL6-VM6-VN6 -> -110338.32 | VP6: =VF6/VE6 -> 372.2197 | VQ6: =VD6/(VI6+VL6+VM6+VN6) -> 0.43112238 | VR6: =VH6/(VL6+VM6+VN6) -> 0.031825471 | VS6: 12月25-31
C7: PH18 | D7: 3 | E7: 2 | F7: ='PH18'!AJ4 -> 37 | G7: =(I7/F7)/S1 -> 2.3534304 | H7: ='PH18'!G4 -> 4374 | I7: ='PH18'!H4 -> 2264 | J7: ='PH18'!T4 -> 351982 | K7: ='PH18'!U4 -> 489755 | L7: ='PH18'!V4 -> 405034.16 | M7: =178185+1151565 -> 1329750 | N7: =165390.3+1217405.32 -> 1382795.6 | O7: =M7-N7 -> -53045.62 | P7: ='PH18'!J4 -> 2034 | Q7: ='PH18'!R4 -> 396018 | R7: ='PH18'!S4 -> 262496 | S7: ='PH18'!K4 -> 8992 | T7: =S7-I7 -> 6728 | U7: ='PH18'!W4 -> 4557690.5 | V7: ='PH18'!X4 -> 4055648.6 | W7: =U7-V7 -> 502041.92 | X7: ='PH18'!D4 -> 331462 | Y7: =252642.65+114204.64 -> 366847.29 | Z7: =U7*3.5% -> 159519.17 | AA7: =IF(Y7>0,Y7*20%,0) -> 73369.458 | AB7: =(D7*3200)*S1 -> 249600 | AC7: =(E7*1733)*S1 -> 90116 | AD7: =W7-Z7-AA7-X7-AB7-AC7 -> -402024.71 | AE7: =K7/I7 -> 216.32288 | AF7: =U7/S7 -> 506.8606 | AG7: =M7/(Z7+AA7+X7+AB7+AC7) -> 1.470854 | AH7: =W7/(Z7+AA7+X7+AB7+AC7) -> 0.55531518 | AJ7: PH18 | AK7: 3 | AL7: 2 | AM7: 29 | AN7: =(AP7/AM7)/AZ1 -> 2.583908 | AO7: 3825 | AP7: 2248 | AQ7: 386665 | AR7: 1101256 | AS7: 312535.11 | AT7: 1923477.5 | AU7: 1267336.1 | AV7: =AT7-AU7 -> 656141.35 | AW7: 1062648 | AX7: 1062648 | AY7: 285088.11 | AZ7: 9211 | BA7: 6963 | BB7: 5873504.5 | BC7: 4026910.5 | BD7: =BB7-BC7 -> 1846594.1 | BE7: 305170 | BF7: 1827228.4 | BG7: =BB7*3.5% -> 205572.66 | BH7: =IF(BF7>0,BF7*20%,0) -> 365445.69 | BI7: =(AK7*3200)*AZ1 -> 288000 | BJ7: =(AL7*1733)*AZ1 -> 103980 | BK7: =BD7-BG7-BH7-BE7-BI7-BJ7 -> 578425.71 | BL7: =AR7/AP7 -> 489.88256 | BM7: =BB7/AZ7 -> 637.66198 | BN7: =AT7/(BG7+BH7+BE7+BI7) -> 1.6522047 | BO7: =BD7/(BG7+BH7+BE7+BI7+BJ7) -> 1.4561111 | BQ7: PH18 | BR7: 2 | BS7: 1 | BT7: 48 | BU7: 0.7936828 | BV7: 1938 | BW7: 1181 | BX7: 177747.4 | BY7: 262660 | BZ7: 152117 | CA7: 612944.4 | CB7: 525546 | CC7: 87398.4 | CD7: 1028 | CE7: 224524 | CF7: 132647 | CG7: 9246 | CH7: 8065 | CI7: 7210798 | CJ7: 5158838 | CK7: =CI7-CJ7 -> 2051960 | CL7: 167640 | CM7: 1787157.4 | CN7: =CI7*3.5% -> 252377.93 | CO7: =IF(CM7>0,CM7*20%,0) -> 357431.48 | CP7: =(BR7*3200)*CI1 -> 198400 | CQ7: =(BS7*1733)*CI1 -> 53723 | CR7: =CK7-CN7-CO7-CL7-CP7-CQ7 -> 1022387.6 | CS7: =BY7/BW7 -> 222.40474 | CT7: =CI7/CG7 -> 779.88298 | CU7: =CA7/(CN7+CO7+CL7+CP7) -> 0.62811371 | CV7: =CK7/(CN7+CO7+CL7+CP7+CQ7) -> 1.9930216 | CX7: PH18 | CY7: 2 | CZ7: 1 | DA7: 36 | DB7: 1.2916667 | DC7: 2361 | DD7: 1395 | DE7: 212835 | DF7: 291643 | DG7: 168420.4 | DH7: 1009913.8 | DI7: 830178.17 | DJ7: =DH7-DI7 -> 179735.66 | DK7: 1245 | DL7: 260759 | DM7: 144634.9 | DN7: 10172 | DO7: 8777 | DP7: 7516135.3 | DQ7: 6694214 | DR7: =DP7-DQ7 -> 821921.28 | DS7: 235810 | DT7: 582806.6 | DU7: =DP7*3.5% -> 263064.73 | DV7: =IF(DT7>0,DT7*20%,0) -> 116561.32 | DW7: =(CY7*3200)*DP1 -> 192000 | DX7: =(CZ7*1733)*DP1 -> 51990 | DY7: =DR7-DU7-DV7-DS7-DW7-DX7 -> -37504.775 | DZ7: =DF7/DD7 -> 209.06308 | EA7: =DP7/DN7 -> 738.90437 | EB7: =DH7/(DU7+DV7+DS7+DW7) -> 1.2507663 | EC7: =DR7/(DU7+DV7+DS7+DW7+DX7) -> 0.95636067 | EE7: PH18 | EF7: 2 | EG7: 1 | EH7: 40 | EI7: 1.9846774 | EJ7: 4811 | EK7: 2461 | EL7: 393279.41 | EM7: 532568.41 | EN7: 323728.38 | EO7: 1350562.4 | EP7: 1180889.4 | EQ7: 169673.05 | ER7: 2092 | ES7: 441874.41 | ET7: 264490.38 | EU7: 14566 | EV7: 12105 | EW7: 8250113.8 | EX7: 7568715 | EY7: 681398.78 | EZ7: 315490 | FA7: 427940.13 | FB7: 288753.98 | FC7: 85588.026 | FD7: =(EF7*3200)*EW1 -> 198400 | FE7: =(EG7*1733)*EW1 -> 53723 | FF7: -293602.23 | FG7: 216.40325 | FH7: 566.39529 | FI7: 1.4659662 | FJ7: 0.69886982 | FN7: PH18 | FO7: 2 | FP7: 1 | FQ7: 62 | FR7: =(FT7/FQ7)/GF1 -> 1.2713134 | FS7: 4966 | FT7: 2207 | FU7: 373153.07 | FV7: 521188.07 | FW7: 344679 | FX7: 1768725.3 | FY7: 1658044 | FZ7: =FX7-FY7 -> 110681.27 | GA7: 1864 | GB7: 427415.07 | GC7: 273927 | GD7: 14175 | GE7: 11968 | GF7: 7700878.3 | GG7: 6703863.2 | GH7: 997015.03 | GI7: 285630 | GJ7: 715176.18 | GK7: 269530.74 | GL7: 143035.24 | GM7: =(FO7*3200)*GF1 -> 179200 | GN7: =(FP7*1733)*GF1 -> 48524 | GO7: 41247.054 | GP7: 236.15227 | GQ7: 543.27184 | GR7: =FX7/(GK7+GL7+GI7+GM7) -> 2.0158803 | GS7: =GH7/(GK7+GL7+GI7+GM7+GN7) -> 1.0767832 | GV7: PH18 | GW7: 2 | GX7: 1 | GY7: 50 | GZ7: =(HB7/GY7)/HL1 -> 1.883871 | HA7: 7039 | HB7: 2920 | HC7: 444871 | HD7: 607365 | HE7: 419779 | HF7: 1616410.1 | HG7: 1511247 | HH7: =HF7-HG7 -> 105163.06 | HI7: 2448 | HJ7: 506301 | HK7: 360356 | HL7: 18094 | HM7: 15174 | HN7: 8551758.3 | HO7: 7699218 | HP7: 852540.26 | HQ7: 415560 | HR7: 531792.83 | HS7: 299311.54 | HT7: 69371.85 | HU7: =(GW7*3200)*31 -> 198400 | HV7: =(GX7*1733)*31 -> 53723 | HW7: -216872.13 | HX7: 208.00171 | HY7: 472.6295 | HZ7: =HF7/(HS7+HT7+HQ7+HU7) -> 1.644961 | IA7: =HP7/(HS7+HT7+HQ7+HU7+HV7) -> 0.82262438 | ID7: PH18 | IE7: 3 | IF7: 0 | IG7: 58 | IH7: =(IJ7/IG7)/IT1 -> 3.057842 | II7: 13675 | IJ7: 5498 | IK7: 816908 | IL7: 1173968.9 | IM7: 735381 | IN7: 3215200.5 | IO7: 2943729 | IP7: =IN7-IO7 -> 271471.5 | IQ7: 4565 | IR7: 993658.89 | IS7: 603710 | IT7: 26333 | IU7: 20835 | IV7: 11702604 | IW7: 9537748 | IX7: =IV7-IW7 -> 2164855.6 | IY7: 500700 | IZ7: 1697468.3 | JA7: =IV7*3.5% -> 409591.13 | JB7: =IZ7*20% -> 339493.67 | JC7: 221824 | JD7: 0 | JE7: =IX7-JA7-JB7-IY7-JC7 -> 693246.84 | JF7: =IL7/IJ7 -> 213.52654 | JG7: =IV7/IT7 -> 444.40829 | JH7: =IL7/(JA7+JB7+IY7+JC7) -> 0.79774523 | JI7: =IX7/(JA7+JB7+IY7+JC7) -> 1.4710809 | JL7: PH18 | JM7: 5 | JN7: 0 | JO7: 88 | JP7: =(JR7/JO7)/KB1 -> 1.5155303 | JQ7: 8925 | JR7: 4001 | JS7: 586063 | JT7: 833665 | JU7: 454778 | JV7: 2076869.8 | JW7: 1667987 | JX7: =JV7-JW7 -> 408882.82 | JY7: 3316 | JZ7: 687740 | KA7: 366665 | KB7: 22103 | KC7: 18102 | KD7: 10406089 | KE7: 8457605 | KF7: =KD7-KE7 -> 1948483.8 | KG7: 379360 | KH7: 1578733.6 | KI7: =KD7*3.5% -> 364213.11 | KJ7: =KH7*20% -> 315746.71 | KK7: 259950 | KL7: 0 | KM7: =KF7-KI7-KJ7-KG7-KK7 -> 629213.95 | KN7: =JT7/JR7 -> 208.36416 | KO7: =KD7/KB7 -> 470.79984 | KP7: =JT7/(KI7+KJ7+KG7+KK7) -> 0.63191395 | KQ7: =KF7/(KI7+KJ7+KG7+KK7) -> 1.4769411 | KT7: PH18 | KU7: 5 | KV7: 0 | KW7: 125 | KX7: =(KZ7/KW7)/LJ1 -> 1.4309677 | KY7: 13728 | KZ7: 5545 | LA7: 841950 | LB7: 1279811 | LC7: 811336 | LD7: 4175580.7 | LE7: 3529556 | LF7: =LE7 -> 3529556 | LG7: 4640 | LH7: 1038759 | LI7: 650982 | LJ7: 27158 | LK7: 21613 | LL7: 11362924 | LM7: 9899067 | LN7: 1463856.6 | LO7: 344550 | LP7: 1013835.5 | LQ7: 397702.33 | LR7: 202767.1 | LS7: 268615 | LT7: 0 | LU7: 250222.19 | LV7: 230.80451 | LW7: 418.4006 | LX7: 1.0545276 | LY7: 1.2061759 | MB7: PH18 | MC7: 5 | MD7: 0 | ME7: 142 | MF7: =(MH7/ME7)/MR1 -> 1.5600939 | MG7: 14928 | MH7: 6646 | MI7: 1089920.4 | MJ7: 1740947 | MK7: 1093491 | ML7: 4894921.1 | MM7: 4218503 | MN7: =ML7-MM7 -> 676418.1 | MO7: 5574 | MP7: 1474642.4 | MQ7: 729309 | MR7: 27821 | MS7: 21175 | MT7: 16118826 | MU7: 15815437 | MV7: =MT7-MU7 -> 303388.75 | MW7: 503340 | MX7: -258291.46 | MY7: =MT7*3.5% -> 564158.9 | MZ7: 0 | NA7: 259950 | NB7: =MV7-MY7-MZ7-MW7-NA7 -> -1024060.2 | NC7: 0 | ND7: =MJ7/MH7 -> 261.95411 | NE7: =MT7/MR7 -> 579.37622 | NF7: =MJ7/(MY7+MZ7+MW7+NA7) -> 1.3114983 | NG7: =MV7/(MY7+MZ7+MW7+NA7) -> 0.22855023 | NJ7: PH18 | NK7: 7 | NL7: 0 | NM7: 145 | NN7: =(NP7/NM7)/NZ1 -> 2.2157953 | NO7: 18131 | NP7: 9960 | NQ7: 1429557 | NR7: 1999654 | NS7: 1448096 | NT7: 5004447.7 | NU7: 4615209 | NV7: =NT7-NU7 -> 389238.66 | NW7: 8477 | NX7: 1678195 | NY7: 1211360 | NZ7: 30033 | OA7: =NZ7-NP7 -> 20073 | OB7: 10161098 | OC7: 9583644 | OD7: =OB7-OC7 -> 577454.14 | OE7: 936840 | OF7: 71129.53 | OG7: =OB7*3.5% -> 355638.43 | OH7: =OF7*20% -> 14225.906 | OI7: 344867 | OJ7: 0 | OK7: =OD7-OG7-OH7-OE7-OI7 -> -1074117.2 | OL7: =NR7/NP7 -> 200.76847 | OM7: =OB7/NZ7 -> 338.33111 | ON7: =NR7/(OG7+OH7+OE7+OI7) -> 1.2107585 | OO7: =OD7/(OG7+OH7+OE7+OI7) -> 0.34963923 | OS7: PH18 | OT7: 6 | OU7: 175 | OV7: 22136 | OW7: 11483 | OX7: 1676707 | OY7: 2217047 | OZ7: 1487147 | PA7: 5292446.8 | PB7: 4474229 | PC7: 29075 | PD7: 17592 | PE7: 8439571.8 | PF7: 6953178 | PG7: =PE7-PF7 -> 1486393.8 | PH7: 1153200 | PI7: 948017.1 | PJ7: =PE7*3.5% -> 295385.01 | PK7: =PI7*20% -> 189603.42 | PL7: =OT7*1733*PF1+1 -> 322339 | PM7: =PG7-PJ7-PK7-PH7-PL7 -> -474133.59 | PN7: =OY7/OW7 -> 193.07211 | PO7: =PE7/PC7 -> 290.26902 | PP7: =OY7/(PH7+PJ7+PK7+PL7) -> 1.1308421 | PQ7: =PG7/(PJ7+PK7+PH7+PL7) -> 0.75816018 | PU7: PH18 | PV7: 6 | PW7: 196 | PX7: 18694 | PY7: 8791 | PZ7: 1329954 | QA7: 1808204 | QB7: 1066383 | QC7: 22040 | QD7: 13249 | QE7: 7178463.8 | QF7: 6638412 | QG7: 540051.76 | QH7: 806690 | QI7: 167385.12 | QJ7: =QE7*3.5% -> 251246.23 | QK7: =QI7*20% -> 33477.024 | QL7: =PV7*3306*QG1+1 -> 595081 | QM7: =QG7-QJ7-QK7 -> 255328.5 | QN7: =PZ7/PY7 -> 151.28586 | QO7: =QE7/QC7 -> 325.70162 | QP7: =QA7/(QH7+QJ7+QK7+QL7) -> 1.0721673 | QQ7: =QG7/(QJ7+QK7) -> 1.8967603 | QR7: 披索 | QT7: 5-04玩家提款：40,637.04 / 5-08玩家提款：36,102.51/ 5-20玩家提款：30,655.35/ 5-26玩家提款：27,304.14/ 5-28玩家提款：18,587.40/ 5-29玩家提款：33,497.90/ 5-30玩家提款：60,132.61 总提款：246,916.95 | QU7: PH18 | QV7: 4 | QW7: 14715 | QX7: 7063 | QY7: 3205612.9 | QZ7: 8372 | RA7: 5662956.2 | RB7: 5146982 | RC7: =RB7-RE7 -> 4454182 | RD7: =RA7-RB7 -> 515974.24 | RE7: 692800 | RF7: 219056.76 | RG7: =RA7*3.5% -> 198203.47 | RH7: =RF7*10% -> 21905.676 | RI7: =QV7*3306*31 -> 409944 | RJ7: =RD7-RG7-RH7 -> 295865.1 | RK7: =RA7/QZ7 -> 676.41618 | RL7: =QY7/(RE7+RG7+RH7+RI7) -> 2.4232568 | RM7: =RD7/(RG7+RH7) -> 2.3441745 | RQ7: PH18 | RR7: 3 | RS7: 11178 | RT7: 5481 | RU7: 2359144.9 | RV7: 6333 | RW7: 3641576 | RX7: 3457365 | RY7: =RW7-RX7 -> 184211.01 | RZ7: 486240 | SA7: 0 | SB7: 37856.94 | SC7: =RW7*3.5% -> 127455.16 | SD7: =SB7*10% -> 3785.694 | SE7: =RR7*3306*30 -> 297540 | SF7: =RY7-SC7-SD7-SE7 -> -244569.84 | SG7: =RW7/RV7 -> 575.01595 | SH7: =RU7/(RZ7+SC7+SD7+SE7) -> 2.5782416 | SI7: =RY7/(SC7+SD7+SE7) -> 0.42961575 | SM7: PH18 | SN7: 3 | SO7: 8814 | SP7: 4190 | SQ7: 1657239.3 | SR7: 5421 | SS7: 3619162.3 | ST7: 3263071 | SU7: =SS7-ST7 -> 356091.27 | SV7: 482777 | SW7: 0 | SX7: 258937.49 | SY7: =SS7*3.5% -> 126670.68 | SZ7: =SX7*10% -> 25893.749 | TA7: =SN7*4000*31 -> 372000 | TB7: =SU7-SY7-SZ7-TA7 -> -168473.16 | TC7: =SS7/SR7 -> 667.61894 | TD7: =SQ7/(SV7+SY7+SZ7+TA7) -> 1.6451614 | TE7: =SU7/(SY7+SZ7+TA7) -> 0.67883229 | TH7: PH18 | TI7: 3 | TJ7: 17299 | TK7: 7593 | TL7: 2966813.4 | TM7: 8965 | TN7: 5070308.2 | TO7: 5226826 | TP7: =TN7-TO7 -> -156517.76 | TQ7: 1110570 | TR7: 0 | TS7: -248917.46 | TT7: =TN7*4% -> 202812.33 | TU7: 0 | TV7: =TI7*4000*28 -> 336000 | TW7: =TP7-TT7-TU7-TV7 -> -695330.09 | TX7: =TN7/TM7 -> 565.56701 | TY7: =TL7/(TQ7+TT7+TU7+TV7) -> 1.7987421 | TZ7: =TP7/(TT7+TU7+TV7) -> -0.2904866 | UD7: PH18 | UE7: 4 | UF7: 19200 | UG7: 9340 | UH7: 4190588 | UI7: 10028 | UJ7: 5715637 | UK7: 6556834 | UL7: =UJ7-UK7 -> -841197.01 | UM7: 906685 | UN7: 0 | UO7: -967693.71 | UP7: =UJ7*4% -> 228625.48 | UQ7: 0 | UR7: =UE7*4000*31 -> 496000 | US7: =UL7-UP7-UQ7-UR7 -> -1565822.5 | UT7: =UJ7/UI7 -> 569.96779 | UU7: =UH7/(UM7+UP7+UQ7+UR7) -> 2.5688476 | UV7: =UL7/(UP7+UQ7+UR7) -> -1.1608714 | UZ7: PH18 | VA7: 4 | VB7: 7796 | VC7: 4204 | VD7: 2123082 | VE7: 4204 | VF7: 2123082 | VG7: 2871507 | VH7: =VF7-VG7 -> -748425 | VI7: 259060 | VJ7: 0 | VK7: -822129.71 | VL7: =VF7*4% -> 84923.28 | VM7: 0 | VN7: =VA7*4000*20 -> 320000 | VO7: =VH7-VL7-VM7-VN7 -> -1153348.3 | VP7: =VF7/VE7 -> 505.01475 | VQ7: =VD7/(VI7+VL7+VM7+VN7) -> 3.1974932 | VR7: =VH7/(VL7+VM7+VN7) -> -1.8483131 | VS7: 12月12-31
C8: PH21 | AJ8: PH21 | BQ8: PH21 | BU8: #DIV/0! | CO8: =IF(CM8>0,CM8*20%,0) -> 0 | CR8: =CK8-CN8-CO8-CL8-CP8-CQ8 -> 0 | CU8: =CA8/(CN8+CO8+CL8+CP8) -> #DIV/0! | CV8: =CK8/(CN8+CO8+CL8+CP8+CQ8) -> #DIV/0! | CX8: PH21 | DB8: #DIV/0! | DV8: =IF(DT8>0,DT8*20%,0) -> 0 | DY8: =DR8-DU8-DV8-DS8-DW8-DX8 -> 0 | EB8: =DH8/(DU8+DV8+DS8+DW8) -> #DIV/0! | EC8: =DR8/(DU8+DV8+DS8+DW8+DX8) -> #DIV/0! | EE8: PH21 | EI8: #DIV/0! | FC8: 0 | FF8: 0 | FI8: #DIV/0! | FJ8: #DIV/0! | FN8: PH21 | GO8: =GH8-GK8-GL8-GI8-GM8-GN8 -> 0 | GR8: =FX8/(GK8+GL8+GI8+GM8) -> #DIV/0! | GS8: =GH8/(GK8+GL8+GI8+GM8+GN8) -> #DIV/0! | GV8: PH21 | HW8: =HP8-HS8-HT8-HQ8-HU8-HV8 -> 0 | HZ8: =HF8/(HS8+HT8+HQ8+HU8) -> #DIV/0! | IA8: =HP8/(HS8+HT8+HQ8+HU8+HV8) -> #DIV/0! | ID8: PH21 | JL8: PH21 | JX8: =JV8-JW8 -> 0 | KT8: PH21 | LF8: =LE8 -> 0 | LN8: 0 | LR8: 0 | LU8: 0 | LX8: #DIV/0! | LY8: #DIV/0! | MB8: PH21 | MZ8: =MX8*20% -> 0 | NB8: =MV8-MY8-MZ8-MW8-NA8 -> 0 | NF8: =MJ8/(MY8+MZ8+MW8+NA8) -> #DIV/0! | NG8: =MV8/(MY8+MZ8+MW8+NA8) -> #DIV/0! | NJ8: PH21 | OH8: =OF8*20% -> 0 | OK8: =OD8-OG8-OH8-OE8-OI8 -> 0 | OL8: =NR8/NP8 -> #DIV/0! | ON8: =NR8/(OG8+OH8+OE8+OI8) -> #DIV/0! | OO8: =OD8/(OG8+OH8+OE8+OI8) -> #DIV/0! | OS8: PH21 | OT8: 0 | PC8: 4824 | PD8: 4824 | PG8: =PE8-PF8 -> 0 | PJ8: =PE8*3.5% -> 0 | PK8: =PI8*20% -> 0 | PL8: =OT8*3306*PF5+1 -> 1 | PM8: =PG8-PJ8-PK8-PH8-PL8 -> -1 | PN8: =OY8/OW8 -> #DIV/0! | PO8: =PE8/PC8 -> 0 | PP8: =OY8/(PH8+PJ8+PK8+PL8) -> 0 | PQ8: =PG8/(PJ8+PK8+PH8+PL8) -> 0 | PU8: PH21 | PV8: 0 | QG8: 325038 | QJ8: =QE8*3.5% -> 0 | QK8: =QI8*20% -> 0 | QM8: 0 | QP8: =QA8/(QH8+QJ8+QK8+QL8) -> #DIV/0! | QQ8: =QG8/(QJ8+QK8) -> #DIV/0! | QR8: 披索 | QT8: 5月1停推 | QU8: PH21 | QV8: 0 | RC8: =RB8-RE8 -> 0 | RD8: =RA8-RB8 -> 0 | RG8: =RA8*3.5% -> 0 | RH8: =RF8*10% -> 0 | RI8: 0 | RJ8: =RD8-RG8-RH8 -> 0 | RK8: =RA8/QZ8 -> #DIV/0! | RL8: =QY8/(RE8+RG8+RH8+RI8) -> #DIV/0! | RM8: =RD8/(RG8+RH8) -> #DIV/0! | RQ8: PH21 | RR8: 2 | RV8: 1016 | RW8: 788675 | RX8: 671794 | RY8: =RW8-RX8 -> 116881 | SA8: 0 | SB8: 81723.25 | SC8: =RW8*3.5% -> 27603.625 | SD8: =SB8*10% -> 8172.325 | SE8: =RR8*3306*30 -> 198360 | SF8: =RY8-SC8-SD8-SE8 -> -117254.95 | SG8: =RW8/RV8 -> 776.25492 | SH8: =RU8/(RZ8+SC8+SD8+SE8) -> 0 | SI8: =RY8/(SC8+SD8+SE8) -> 0.49920143 | SM8: PH21 | SN8: 4 | SR8: 1637 | SS8: 1155526 | ST8: 1031709 | SU8: =SS8-ST8 -> 123817 | SW8: 0 | SX8: 88004.61 | SY8: =SS8*3.5% -> 40443.41 | SZ8: =SX8*10% -> 8800.461 | TA8: =SN8*4000*31 -> 496000 | TB8: =SU8-SY8-SZ8-TA8 -> -421426.87 | TC8: =SS8/SR8 -> 705.88027 | TD8: =SQ8/(SV8+SY8+SZ8+TA8) -> 0 | TE8: =SU8/(SY8+SZ8+TA8) -> 0.22708554 | TH8: PH21 | TI8: 2 | TM8: 2689 | TN8: 1913275.2 | TO8: 1704237 | TP8: =TN8-TO8 -> 209038.25 | TQ8: 218380 | TR8: 0 | TS8: 152983.27 | TT8: =TN8*4% -> 76531.01 | TU8: =TS8*10% -> 15298.327 | TV8: =TI8*4000*28 -> 224000 | TW8: =TP8-TT8-TU8-TV8 -> -106791.09 | TX8: =TN8/TM8 -> 711.51925 | TY8: =TL8/(TQ8+TT8+TU8+TV8) -> 0 | TZ8: =TP8/(TT8+TU8+TV8) -> 0.66187091 | UD8: PH21 | UE8: 2 | UI8: 752 | UJ8: 320945 | UK8: 347206 | UL8: =UJ8-UK8 -> -26261 | UM8: 44410 | UN8: 0 | UO8: -62640.53 | UP8: =UJ8*4% -> 12837.8 | UQ8: 0 | UR8: =UE8*4000*24 -> 192000 | US8: =UL8-UP8-UQ8-UR8 -> -231098.8 | UT8: =UJ8/UI8 -> 426.78856 | UU8: =UH8/(UM8+UP8+UQ8+UR8) -> 0 | UV8: =UL8/(UP8+UQ8+UR8) -> -0.12820388 | UW8: 1月08-31 | UZ8: PH21 | VA8: 0 | VF8: 0 | VG8: 0 | VH8: =VF8-VG8 -> 0 | VI8: 0 | VJ8: 0 | VK8: 0 | VL8: =VF8*4% -> 0 | VM8: =VK8*10% -> 0 | VN8: =VA8*4000*0 -> 0 | VO8: =VH8-VL8-VM8-VN8 -> 0 | VP8: =VF8/VE8 -> #DIV/0! | VQ8: =VD8/(VI8+VL8+VM8+VN8) -> #DIV/0! | VR8: =VH8/(VL8+VM8+VN8) -> #DIV/0! | VS8: 未开始
C9: PH22 | AJ9: PH22 | BQ9: PH22 | BU9: #DIV/0! | CO9: =IF(CM9>0,CM9*20%,0) -> 0 | CR9: =CK9-CN9-CO9-CL9-CP9-CQ9 -> 0 | CU9: =CA9/(CN9+CO9+CL9+CP9) -> #DIV/0! | CV9: =CK9/(CN9+CO9+CL9+CP9+CQ9) -> #DIV/0! | CX9: PH22 | DB9: #DIV/0! | DV9: =IF(DT9>0,DT9*20%,0) -> 0 | DY9: =DR9-DU9-DV9-DS9-DW9-DX9 -> 0 | EB9: =DH9/(DU9+DV9+DS9+DW9) -> #DIV/0! | EC9: =DR9/(DU9+DV9+DS9+DW9+DX9) -> #DIV/0! | EE9: PH22 | EI9: #DIV/0! | FC9: 0 | FF9: 0 | FI9: #DIV/0! | FJ9: #DIV/0! | FN9: PH22 | GO9: =GH9-GK9-GL9-GI9-GM9-GN9 -> 0 | GR9: =FX9/(GK9+GL9+GI9+GM9) -> #DIV/0! | GS9: =GH9/(GK9+GL9+GI9+GM9+GN9) -> #DIV/0! | GV9: PH22 | HW9: =HP9-HS9-HT9-HQ9-HU9-HV9 -> 0 | HZ9: =HF9/(HS9+HT9+HQ9+HU9) -> #DIV/0! | IA9: =HP9/(HS9+HT9+HQ9+HU9+HV9) -> #DIV/0! | ID9: PH22 | JL9: PH22 | JX9: =JV9-JW9 -> 0 | KT9: PH22 | LF9: =LE9 -> 0 | LN9: 0 | LR9: 0 | LU9: 0 | LX9: #DIV/0! | LY9: #DIV/0! | MB9: PH22 | MZ9: =MX9*20% -> 0 | NB9: =MV9-MY9-MZ9-MW9-NA9 -> 0 | NF9: =MJ9/(MY9+MZ9+MW9+NA9) -> #DIV/0! | NG9: =MV9/(MY9+MZ9+MW9+NA9) -> #DIV/0! | NJ9: PH22 | OH9: =OF9*20% -> 0 | OK9: =OD9-OG9-OH9-OE9-OI9 -> 0 | OL9: =NR9/NP9 -> #DIV/0! | ON9: =NR9/(OG9+OH9+OE9+OI9) -> #DIV/0! | OO9: =OD9/(OG9+OH9+OE9+OI9) -> #DIV/0! | OS9: PH22 | OT9: 0 | PC9: 4733 | PD9: 4733 | PG9: =PE9-PF9 -> 0 | PJ9: =PE9*3.5% -> 0 | PK9: =PI9*20% -> 0 | PL9: =OT9*3306*PF6+1 -> 1 | PM9: =PG9-PJ9-PK9-PH9-PL9 -> -1 | PN9: =OY9/OW9 -> #DIV/0! | PO9: =PE9/PC9 -> 0 | PP9: =OY9/(PH9+PJ9+PK9+PL9) -> 0 | PQ9: =PG9/(PJ9+PK9+PH9+PL9) -> 0 | PU9: PH22 | PV9: 0 | QG9: 230158 | QJ9: =QE9*3.5% -> 0 | QK9: =QI9*20% -> 0 | QM9: 0 | QP9: =QA9/(QH9+QJ9+QK9+QL9) -> #DIV/0! | QQ9: =QG9/(QJ9+QK9) -> #DIV/0! | QR9: 披索 | QS9: 6月23停推 | QT9: 5-16玩家提款：37,491.90/ 5-19玩家提款：500,007.78/ 5-21玩家提款：190,108.14/ 5-22玩家提款：34,891.94/ 5-26玩家提款：33,699.77/ 5-30玩家提款：99,080.73/ 5-31玩家提款：822,814.42 总提款：1,718,094.68 | QU9: PH22 | QV9: 2 | QW9: 4185 | QX9: 2134 | QY9: 875675 | QZ9: 2444 | RA9: 2902626 | RB9: 3032409 | RC9: =RB9-RE9 -> 2842619 | RD9: =RA9-RB9 -> -129783 | RE9: 189790 | RF9: -311182.95 | RG9: =RA9*3.5% -> 101591.91 | RH9: 0 | RI9: =QV9*3306*31 -> 204972 | RJ9: =RD9-RG9-RH9 -> -231374.91 | RK9: =RA9/QZ9 -> 1187.6538 | RL9: =QY9/(RE9+RG9+RH9+RI9) -> 1.764215 | RM9: =RD9/(RG9+RH9) -> -1.2774935 | RQ9: PH22 | RR9: 2 | RS9: 2759 | RT9: 1741 | RU9: 570801 | RV9: 1978 | RW9: 1548050 | RX9: 1292799 | RY9: =RW9-RX9 -> 255251 | RZ9: 163830 | SA9: 0 | SB9: 210240.76 | SC9: =RW9*3.5% -> 54181.75 | SD9: =SB9*10% -> 21024.076 | SE9: =RR9*3306*30 -> 198360 | SF9: =RY9-SC9-SD9-SE9 -> -18314.826 | SG9: =RW9/RV9 -> 782.63397 | SH9: =RU9/(RZ9+SC9+SD9+SE9) -> 1.3049987 | SI9: =RY9/(SC9+SD9+SE9) -> 0.93305148 | SM9: PH22 | SN9: 3 | SO9: 2086 | SP9: 1054 | SQ9: 771552 | SR9: 1270 | SS9: 1225448 | ST9: 836408 | SU9: =SS9-ST9 -> 389040 | SV9: 102940 | SW9: 0 | SX9: 367090.49 | SY9: =SS9*3.5% -> 42890.68 | SZ9: =SX9*10% -> 36709.049 | TA9: =SN9*4000*31 -> 372000 | TB9: =SU9-SY9-SZ9-TA9 -> -62559.729 | TC9: =SS9/SR9 -> 964.91969 | TD9: =SQ9/(SV9+SY9+SZ9+TA9) -> 1.3913376 | TE9: =SU9/(SY9+SZ9+TA9) -> 0.86147084 | TH9: PH22 | TI9: 2 | TJ9: 2814 | TK9: 1394 | TL9: 756837.1 | TM9: 1410 | TN9: 773269.1 | TO9: 1029114 | TP9: =TN9-TO9 -> -255844.9 | TQ9: 16910 | TR9: 0 | TS9: -318352.75 | TT9: =TN9*4% -> 30930.764 | TU9: 0 | TV9: =TI9*4000*28 -> 224000 | TW9: =TP9-TT9-TU9-TV9 -> -510775.66 | TX9: =TN9/TM9 -> 548.4178 | TY9: =TL9/(TQ9+TT9+TU9+TV9) -> 2.7841192 | TZ9: =TP9/(TT9+TU9+TV9) -> -1.0035858 | UD9: PH22 | UE9: 2 | UF9: 124 | UG9: 60 | UH9: 19191 | UI9: 60 | UJ9: 19191 | UK9: 24593 | UL9: =UJ9-UK9 -> -5402 | UM9: 0 | UN9: 0 | UO9: -7087.62 | UP9: =UJ9*4% -> 767.64 | UQ9: 0 | UR9: =UE9*4000*14 -> 112000 | US9: =UL9-UP9-UQ9-UR9 -> -118169.64 | UT9: =UJ9/UI9 -> 319.85 | UU9: =UH9/(UM9+UP9+UQ9+UR9) -> 0.1701818 | UV9: =UL9/(UP9+UQ9+UR9) -> -0.047903814 | UW9: 1月18-31 | UZ9: PH22 | VH9: =VF9-VG9 -> 0 | VL9: =VF9*4% -> 0 | VM9: 0 | VN9: =VA9*4000*0 -> 0 | VO9: =VH9-VL9-VM9-VN9 -> 0 | VP9: =VF9/VE9 -> #DIV/0! | VQ9: =VD9/(VI9+VL9+VM9+VN9) -> #DIV/0! | VR9: =VH9/(VL9+VM9+VN9) -> #DIV/0! | VS9: 未开始
C10: PH30 | D10: 3 | E10: 1 | F10: ='PH30'!AJ4 -> 36 | G10: =(I10/F10)/S1 -> 3.9113248 | H10: ='PH30'!G4 -> 7790 | I10: ='PH30'!H4 -> 3661 | J10: ='PH30'!T4 -> 626598 | K10: ='PH30'!U4 -> 853882 | L10: ='PH30'!V4 -> 586999 | M10: =57125+1894504 -> 1951629 | N10: =63359+1812286.22 -> 1875645.2 | O10: =M10-N10 -> 75983.78 | P10: ='PH30'!J4 -> 2996 | Q10: ='PH30'!R4 -> 706540 | R10: ='PH30'!S4 -> 462970 | S10: ='PH30'!K4 -> 16663 | T10: =S10-I10 -> 13002 | U10: ='PH30'!W4 -> 8133619.7 | V10: ='PH30'!X4 -> 7280993.2 | W10: =U10-V10 -> 852626.52 | X10: ='PH30'!D4 -> 510845 | Y10: =73206.11+745655.46 -> 818861.57 | Z10: =U10*3.5% -> 284676.69 | AA10: =IF(Y10>0,Y10*20%,0) -> 163772.31 | AB10: =(D10*3200)*S1 -> 249600 | AC10: =(E10*1733)*S1 -> 45058 | AD10: =W10-Z10-AA10-X10-AB10-AC10 -> -401325.48 | AE10: =K10/I10 -> 233.23737 | AF10: =U10/S10 -> 488.12457 | AG10: =M10/(Z10+AA10+X10+AB10+AC10) -> 1.5563825 | AH10: =W10/(Z10+AA10+X10+AB10+AC10) -> 0.67995148 | AJ10: PH30 | AK10: 3 | AL10: 2 | AM10: 40 | AN10: =(AP10/AM10)/AZ1 -> 3.4325 | AO10: 8876 | AP10: 4119 | AQ10: 681374 | AR10: 938494 | AS10: 642351.26 | AT10: 2312685 | AU10: 2014547.3 | AV10: =AT10-AU10 -> 298137.74 | AW10: 810518 | AX10: 810518 | AY10: 558090.26 | AZ10: 18420 | BA10: 14301 | BB10: 9885972.9 | BC10: 8800405.2 | BD10: =BB10-BC10 -> 1085567.8 | BE10: 531451 | BF10: 1007818.8 | BG10: =BB10*3.5% -> 346009.05 | BH10: =IF(BF10>0,BF10*20%,0) -> 201563.76 | BI10: =(AK10*3200)*AZ1 -> 288000 | BJ10: =(AL10*1733)*AZ1 -> 103980 | BK10: =BD10-BG10-BH10-BE10-BI10-BJ10 -> -385436.02 | BL10: =AR10/AP10 -> 227.84511 | BM10: =BB10/AZ10 -> 536.69777 | BN10: =AT10/(BG10+BH10+BE10+BI10) -> 1.6917664 | BO10: =BD10/(BG10+BH10+BE10+BI10+BJ10) -> 0.73797755 | BQ10: PH30 | BR10: 3 | BS10: 2 | BT10: 78 | BU10: 1.0467328 | BV10: 5465 | BW10: 2531 | BX10: 401310 | BY10: 593602.7 | BZ10: 381596.96 | CA10: 1361488.7 | CB10: 1008691.3 | CC10: 352797.38 | CD10: 2224 | CE10: 524058.7 | CF10: 334301 | CG10: 16107 | CH10: 13576 | CI10: 8080404.9 | CJ10: 6633218 | CK10: =CI10-CJ10-CW10 -> 1178286.3 | CL10: 281610 | CM10: 1078460.7 | CN10: =CI10*3.5% -> 282814.17 | CO10: =IF(CM10>0,CM10*20%,0) -> 215692.13 | CP10: =(BR10*3200)*CI1 -> 297600 | CQ10: =(BS10*1733)*CI1 -> 107446 | CR10: =CK10-CN10-CO10-CL10-CP10-CQ10 -> -6876.0248 | CS10: =BY10/BW10 -> 234.53287 | CT10: =CI10/CG10 -> 501.67038 | CU10: =CA10/(CN10+CO10+CL10+CP10) -> 1.263309 | CV10: =CK10/(CN10+CO10+CL10+CP10+CQ10) -> 0.99419824 | CW10: 268900.6 | CX10: PH30 | CY10: 4 | CZ10: 1 | DA10: 51 | DB10: 1.8261438 | DC10: 5627 | DD10: 2794 | DE10: 427287 | DF10: 607568 | DG10: 423570.41 | DH10: 1684146.5 | DI10: 1472108.1 | DJ10: =DH10-DI10 -> 212038.43 | DK10: 2420 | DL10: 518968 | DM10: 334667.41 | DN10: 19329 | DO10: 16535 | DP10: 8396539 | DQ10: 7051388 | DR10: =DP10-DQ10 -> 1345151 | DS10: 379020 | DT10: 1260389.9 | DU10: =DP10*3.5% -> 293878.86 | DV10: =IF(DT10>0,DT10*20%,0) -> 252077.98 | DW10: =(CY10*3200)*DP1 -> 384000 | DX10: =(CZ10*1733)*DP1 -> 51990 | DY10: =DR10-DU10-DV10-DS10-DW10-DX10 -> -15815.857 | DZ10: =DF10/DD10 -> 217.45455 | EA10: =DP10/DN10 -> 434.40111 | EB10: =DH10/(DU10+DV10+DS10+DW10) -> 1.2866129 | EC10: =DR10/(DU10+DV10+DS10+DW10+DX10) -> 0.98837896 | EE10: PH30 | EF10: 4 | EG10: 1 | EH10: 58 | EI10: 1.9933259 | EJ10: 7507 | EK10: 3584 | EL10: 588067.1 | EM10: 833381.1 | EN10: 521183.3 | EO10: 2434155.4 | EP10: 2118634.3 | EQ10: 315521.12 | ER10: 2933 | ES10: 702005 | ET10: 402276.3 | EU10: 22821 | EV10: 19237 | EW10: 12766005 | EX10: 10754994 | EY10: 2011010.6 | EZ10: 450060 | FA10: 1993351.6 | FB10: 446810.16 | FC10: 398670.31 | FD10: =(EF10*3200)*EW1 -> 396800 | FE10: =(EG10*1733)*EW1 -> 53723 | FF10: 198955.17 | FG10: 232.52821 | FH10: 559.39725 | FI10: 1.3843545 | FJ10: 1.1097953 | FN10: PH30 | FO10: 4 | FP10: 1 | FQ10: 82 | FR10: =(FT10/FQ10)/GF1 -> 1.5840592 | FS10: 8457 | FT10: 3637 | FU10: 570979.14 | FV10: 948007.14 | FW10: 796441 | FX10: 3363036.4 | FY10: 3340355 | FZ10: =FX10-FY10 -> 22681.39 | GA10: 2951 | GB10: 781980.14 | GC10: 639972 | GD10: 23070 | GE10: 19433 | GF10: 12049663 | GG10: 11371019 | GH10: 678643.51 | GI10: 513080 | GJ10: 577798.43 | GK10: 421738.19 | GL10: 115559.69 | GM10: =(FO10*3200)*GF1 -> 358400 | GN10: =(FP10*1733)*GF1 -> 48524 | GO10: -838354.36 | GP10: 260.65635 | GQ10: 522.30873 | GR10: =FX10/(GK10+GL10+GI10+GM10) -> 2.3872013 | GS10: =GH10/(GK10+GL10+GI10+GM10+GN10) -> 0.46568492 | GV10: PH30 | GW10: 4 | GX10: 1 | GY10: 80 | GZ10: =(HB10/GY10)/HL1 -> 1.5645161 | HA10: 9261 | HB10: 3880 | HC10: 615384.89 | HD10: 950093.89 | HE10: 703586 | HF10: 3023373.8 | HG10: 2729088 | HH10: =HF10-HG10 -> 294285.79 | HI10: 3156 | HJ10: 791112 | HK10: 537074 | HL10: 28068 | HM10: 24188 | HN10: 13342194 | HO10: 12075497 | HP10: 1266697.1 | HQ10: 635210 | HR10: 1194336.5 | HS10: 466976.79 | HT10: 134134.68 | HU10: =(GW10*3200)*31 -> 396800 | HV10: =(GX10*1733)*31 -> 53723 | HW10: -486239.37 | HX10: 244.86956 | HY10: 475.3525 | HZ10: =HF10/(HS10+HT10+HQ10+HU10) -> 1.8512853 | IA10: =HP10/(HS10+HT10+HQ10+HU10+HV10) -> 0.75092702 | ID10: PH30 | IE10: 5 | IF10: 0 | IG10: 84 | IH10: =(IJ10/IG10)/IT1 -> 3.0011521 | II10: 20107 | IJ10: 7815 | IK10: 1227907.9 | IL10: 1819238 | IM10: 1230077 | IN10: 5632529.3 | IO10: 5077153 | IP10: =IN10-IO10 -> 555376.29 | IQ10: 6441 | IR10: 1500944.9 | IS10: 1037357 | IT10: 39873 | IU10: 32058 | IV10: 16969141 | IW10: 14824188 | IX10: =IV10-IW10 -> 2144953 | IY10: 822850 | IZ10: 1975858.6 | JA10: =IV10*3.5% -> 593919.94 | JB10: =IZ10*20% -> 395171.72 | JC10: 301542 | JD10: 0 | JE10: =IX10-JA10-JB10-IY10-JC10 -> 31469.376 | JF10: =IL10/IJ10 -> 232.78797 | JG10: =IV10/IT10 -> 425.57974 | JH10: =IL10/(JA10+JB10+IY10+JC10) -> 0.86077694 | JI10: =IX10/(JA10+JB10+IY10+JC10) -> 1.0148898 | JL10: PH30 | JM10: 6 | JN10: 0 | JO10: 122 | JP10: =(JR10/JO10)/KB1 -> 1.6199454 | JQ10: 15521 | JR10: 5929 | JS10: 905154 | JT10: 1374700 | JU10: 1000285 | JV10: 2969422.9 | JW10: 2509196 | JX10: =JV10-JW10 -> 460226.94 | JY10: 1111327 | JZ10: 1111327 | KA10: 709832 | KB10: 33119 | KC10: 27190 | KD10: 14900973 | KE10: 12431301 | KF10: =KD10-KE10 -> 2469671.5 | KG10: 682470 | KH10: 2387484.2 | KI10: =KD10*3.5% -> 521534.04 | KJ10: =KH10*20% -> 477496.84 | KK10: 311940 | KL10: 0 | KM10: =KF10-KI10-KJ10-KG10-KK10 -> 476230.67 | KN10: =JT10/JR10 -> 231.86035 | KO10: =KD10/KB10 -> 449.92218 | KP10: =JT10/(KI10+KJ10+KG10+KK10) -> 0.68961162 | KQ10: =KF10/(KI10+KJ10+KG10+KK10) -> 1.2388988 | KT10: PH30 | KU10: 6 | KV10: 0 | KW10: 206 | KX10: =(KZ10/KW10)/LJ1 -> 1.621829 | KY10: 22403 | KZ10: 10357 | LA10: 1527739 | LB10: 2283614 | LC10: 1538293 | LD10: 6233905.7 | LE10: 4912812 | LF10: =LE10 -> 4912812 | LG10: 8259 | LH10: 1794733 | LI10: 1154375 | LJ10: 53370 | LK10: 43013 | LL10: 20300181 | LM10: 16772664 | LN10: 3527516.6 | LO10: 1024160 | LP10: 3340830.2 | LQ10: 710506.32 | LR10: 668166.03 | LS10: 322338 | LT10: 0 | LU10: 802346.21 | LV10: 220.48991 | LW10: 380.36688 | LX10: 0.8379711 | LY10: 1.2944206 | MB10: PH30 | MC10: 6 | MD10: 0 | ME10: 247 | MF10: =(MH10/ME10)/MR1 -> 2.2207827 | MG10: 42661 | MH10: 16456 | MI10: 2405187 | MJ10: 3660286 | MK10: 2398859 | ML10: 10150096 | MM10: 8441415 | MN10: =ML10-MM10 -> 1708681.5 | MO10: 13199 | MP10: 2916487 | MQ10: 1778349 | MR10: 64104 | MS10: 47648 | MT10: 23882188 | MU10: 19980973 | MV10: =MT10-MU10 -> 3901215.3 | MW10: 1165940 | MX10: 3711201.9 | MY10: =MT10*3.5% -> 835876.59 | MZ10: =MX10*20% -> 742240.37 | NA10: 311940 | NB10: =MV10-MY10-MZ10-MW10-NA10 -> 845218.32 | NC10: 0 | ND10: =MJ10/MH10 -> 222.42866 | NE10: =MT10/MR10 -> 372.55379 | NF10: =MJ10/(MY10+MZ10+MW10+NA10) -> 1.1977388 | NG10: =MV10/(MY10+MZ10+MW10+NA10) -> 1.2765769 | NJ10: PH30 | NK10: 6 | NL10: 0 | NM10: 149 | NN10: =(NP10/NM10)/NZ1 -> 3.7731111 | NO10: 40653 | NP10: 17428 | NQ10: 2569058 | NR10: 3950690.2 | NS10: 2589014 | NT10: 11312360 | NU10: 9631857 | NV10: =NT10-NU10 -> 1680502.7 | NW10: 13877 | NX10: 3176118.2 | NY10: 2096731 | NZ10: 60257 | OA10: =NZ10-NP10 -> 42829 | OB10: 19846576 | OC10: 16867478 | OD10: =OB10-OC10 -> 2979098.1 | OE10: 1115330 | OF10: 2526640.8 | OG10: =OB10*3.5% -> 694630.16 | OH10: =OF10*20% -> 505328.15 | OI10: 291144 | OJ10: 0 | OK10: =OD10-OG10-OH10-OE10-OI10 -> 372665.77 | OL10: =NR10/NP10 -> 226.68638 | OM10: =OB10/NZ10 -> 329.36549 | ON10: =NR10/(OG10+OH10+OE10+OI10) -> 1.5157463 | OO10: =OD10/(OG10+OH10+OE10+OI10) -> 1.1429793 | OS10: PH30 | OT10: 5 | OU10: 201 | OV10: 34917 | OW10: 15365 | OX10: 2279914.9 | OY10: 3229963 | OZ10: 2099225 | PA10: 7907492.5 | PB10: 6713307 | PC10: 48234 | PD10: 32869 | PE10: 14632641 | PF10: 12250879 | PG10: =PE10-PF10 -> 2381762.4 | PH10: 1077500 | PI10: 2028264.6 | PJ10: =PE10*3.5% -> 512142.45 | PK10: =PI10*20% -> 405652.91 | PL10: =OT10*1733*PF1+1 -> 268616 | PM10: =PG10-PJ10-PK10-PH10-PL10 -> 117851.07 | PN10: =OY10/OW10 -> 210.21562 | PO10: =PE10/PC10 -> 303.36778 | PP10: =OY10/(PH10+PJ10+PK10+PL10) -> 1.426718 | PQ10: =PG10/(PJ10+PK10+PH10+PL10) -> 1.0520564 | PU10: PH30 | PV10: 4 | PW10: 157 | PX10: 28328 | PY10: 11647 | PZ10: 1985281.5 | QA10: 1808737 | QB10: 1066392 | QC10: 38118 | QD10: 26471 | QE10: 12802413 | QF10: 11111237 | QG10: 1691176.4 | QH10: 892350 | QI10: 1361841.2 | QJ10: =QE10*3.5% -> 448084.47 | QK10: =QI10*20% -> 272368.25 | QL10: =PV10*3306*QG1+1 -> 396721 | QM10: =QG10-QJ10-QK10 -> 970723.67 | QN10: =PZ10/PY10 -> 170.45432 | QO10: =QE10/QC10 -> 335.86267 | QP10: =QA10/(QH10+QJ10+QK10+QL10) -> 0.90008244 | QQ10: =QG10/(QJ10+QK10) -> 2.3473801 | QR10: 披索 | QT10: 5-01玩家提款：28,635.82/ 5-17玩家异常提款取消：73,167.23/ 5-21玩家提款：39,171.99/ 5-25玩家提款：13,839.36 + 10,261.20 + 14,073.59/ 5-27玩家提款：24,501.68 + 10,755.22 + 17,500.16/ 5-28玩家提款：60,148.75/ 5-31玩家提款：15,767.88 + 9,385.48 总提款：317,208.36（包含5/17玩家异常提款取消 73,167.23） | QU10: PH30 | QV10: 5 | QW10: 42147 | QX10: 15727 | QY10: 9399053 | QZ10: 18624 | RA10: 14592544 | RB10: =13399554.99-RN10 -> 13326388 | RC10: =RB10-RE10 -> 12102918 | RD10: =RA10-RB10 -> 1266156.5 | RE10: 1223470 | RF10: 780333.6 | RG10: =RA10*3.5% -> 510739.05 | RH10: =RF10*10% -> 78033.36 | RI10: =QV10*3306*31 -> 512430 | RJ10: =RD10-RG10-RH10 -> 677384.1 | RK10: =RA10/QZ10 -> 783.53438 | RL10: =QY10/(RE10+RG10+RH10+RI10) -> 4.0431731 | RM10: =RD10/(RG10+RH10) -> 2.1505025 | RN10: 73167.23 | RQ10: PH30 | RR10: 6 | RS10: 26815 | RT10: 10489 | RU10: 5280337.7 | RV10: 11634 | RW10: 7082110.7 | RX10: 6742302 | RY10: =RW10-RX10 -> 339808.73 | RZ10: 1000848 | SA10: 0 | SB10: 88155.77 | SC10: =RW10*3.5% -> 247873.88 | SD10: =SB10*10% -> 8815.577 | SE10: =RR10*3306*30 -> 595080 | SF10: =RY10-SC10-SD10-SE10 -> -511960.72 | SG10: =RW10/RV10 -> 608.74254 | SH10: =RU10/(RZ10+SC10+SD10+SE10) -> 2.850204 | SI10: =RY10/(SC10+SD10+SE10) -> 0.39894449 | SM10: PH30 | SN10: 6 | SO10: 17588 | SP10: 5262 | SQ10: 2770136.4 | SR10: 5858 | SS10: 3522384.4 | ST10: 3492475.2 | SU10: =SS10-ST10 -> 29909.26 | SV10: 321550 | SW10: 0 | SX10: -144468.37 | SY10: =SS10*3.5% -> 123283.46 | SZ10: 0 | TA10: =SN10*4000*31 -> 744000 | TB10: =SU10-SY10-SZ10-TA10 -> -837374.2 | TC10: =SS10/SR10 -> 601.29471 | TD10: =SQ10/(SV10+SY10+SZ10+TA10) -> 2.3301299 | TE10: =SU10/(SY10+SZ10+TA10) -> 0.034486142 | TH10: PH30 | TI10: 7 | TJ10: 7315 | TK10: 2842 | TL10: 1204471.5 | TM10: 2842 | TN10: 1204471.5 | TO10: 1301912 | TP10: =TN10-TO10 -> -97440.47 | TQ10: 174200 | TR10: 0 | TS10: -156569.96 | TT10: =TN10*4% -> 48178.861 | TU10: 0 | TV10: =TI10*4000*28 -> 784000 | TW10: =TP10-TT10-TU10-TV10 -> -929619.33 | TX10: =TN10/TM10 -> 423.81124 | TY10: =TL10/(TQ10+TT10+TU10+TV10) -> 1.1968371 | TZ10: =TP10/(TT10+TU10+TV10) -> -0.11709078 | UA10: 2月11-28 | UD10: PH30 | UL10: =UJ10-UK10 -> 0 | UP10: =UJ10*4% -> 0 | UQ10: =UO10*10% -> 0 | UR10: 0 | US10: =UL10-UP10-UQ10-UR10 -> 0 | UT10: =UJ10/UI10 -> #DIV/0! | UU10: =UH10/(UM10+UP10+UQ10+UR10) -> #DIV/0! | UV10: =UL10/(UP10+UQ10+UR10) -> #DIV/0! | UZ10: PH30 | VH10: =VF10-VG10 -> 0 | VL10: =VF10*4% -> 0 | VM10: 0 | VN10: =VA10*4000*0 -> 0 | VO10: =VH10-VL10-VM10-VN10 -> 0 | VP10: =VF10/VE10 -> #DIV/0! | VQ10: =VD10/(VI10+VL10+VM10+VN10) -> #DIV/0! | VR10: =VH10/(VL10+VM10+VN10) -> #DIV/0! | VS10: 未开始
C11: PH05 | AJ11: PH05 | BQ11: PH05 | BR11: 0 | BS11: 0 | BT11: 0 | BU11: #DIV/0! | BV11: 1830 | BW11: 1036 | BX11: 153506 | BY11: 215789 | BZ11: 161636 | CA11: 544130 | CB11: 431607 | CC11: 112523 | CD11: 876 | CE11: 175018 | CF11: 139720 | CG11: 11016 | CH11: 9633 | CI11: 9092797 | CJ11: 7970174 | CK11: =CI11-CJ11 -> 1122623 | CL11: 258220 | CM11: 882241.31 | CN11: =CI11*3.5% -> 318247.9 | CO11: =IF(CM11>0,CM11*20%,0) -> 176448.26 | CP11: =(BR11*3200)*CI1 -> 0 | CQ11: =(BS11*1733)*CI1 -> 0 | CR11: =CK11-CN11-CO11-CL11-CP11-CQ11 -> 369706.84 | CS11: =BY11/BW11 -> 208.29054 | CT11: =CI11/CG11 -> 825.4173 | CU11: =CA11/(CN11+CO11+CL11+CP11) -> 0.72269667 | CV11: =CK11/(CN11+CO11+CL11+CP11+CQ11) -> 1.4910332 | CW11: 5月10停 | CX11: PH05 | CY11: 1 | CZ11: 1 | DA11: 77 | DB11: 0.89220779 | DC11: 3585 | DD11: 2061 | DE11: 287293 | DF11: 426962 | DG11: 318943.18 | DH11: 1265170 | DI11: 1143021.2 | DJ11: =DH11-DI11 -> 122148.82 | DK11: 1788 | DL11: 349893 | DM11: 257589.18 | DN11: 14137 | DO11: 11665 | DP11: 9402976 | DQ11: 8579421 | DR11: =DP11-DQ11 -> 823555 | DS11: 317190 | DT11: 580898.86 | DU11: =DP11*3.5% -> 329104.16 | DV11: =IF(DT11>0,DT11*20%,0) -> 116179.77 | DW11: =(CY11*3200)*DP1 -> 96000 | DX11: =(CZ11*1733)*DP1 -> 51990 | DY11: =DR11-DU11-DV11-DS11-DW11-DX11 -> -86908.932 | DZ11: =DF11/DD11 -> 207.16254 | EA11: =DP11/DN11 -> 665.13235 | EB11: =DH11/(DU11+DV11+DS11+DW11) -> 1.4737431 | EC11: =DR11/(DU11+DV11+DS11+DW11+DX11) -> 0.90454434 | EE11: PH05 | EF11: 1 | EG11: 1 | EH11: 92 | EI11: 0.89270687 | EJ11: 5085 | EK11: 2546 | EL11: 411337 | EM11: 586658 | EN11: 377740 | EO11: 1801010 | EP11: 1797382 | EQ11: 3628 | ER11: 2190 | ES11: 487594 | ET11: 321381 | EU11: 14957 | EV11: 12031 | EW11: 9846289 | EX11: 8813876 | EY11: 1032413 | EZ11: 265470 | FA11: 832060.72 | FB11: 344620.11 | FC11: 166412.14 | FD11: =(EF11*3200)*EW1 -> 99200 | FE11: =(EG11*1733)*EW1 -> 53723 | FF11: 86464.741 | FG11: 230.42341 | FH11: 658.30641 | FI11: 2.0185598 | FJ11: 1.0914054 | FN11: PH05 | FO11: 1 | FP11: 1 | FQ11: 66 | FR11: =(FT11/FQ11)/GF1 -> 1.0551948 | FS11: 3812 | FT11: 1950 | FU11: 284359 | FV11: 405955 | FW11: 193969 | FX11: 1068283 | FY11: 855905 | FZ11: =FX11-FY11 -> 212378 | GA11: 1659 | GB11: 341004 | GC11: 157770 | GD11: 13449 | GE11: 11499 | GF11: 8820770 | GG11: 7792812 | GH11: 1027958 | GI11: 223010 | GJ11: 881940.64 | GK11: 308726.95 | GL11: 176388.13 | GM11: =(FO11*3200)*GF1 -> 89600 | GN11: =(FP11*1733)*GF1 -> 48524 | GO11: 166784.92 | GP11: 208.18205 | GQ11: 655.86809 | GR11: =FX11/(GK11+GL11+GI11+GM11) -> 1.3391619 | GS11: =GH11/(GK11+GL11+GI11+GM11+GN11) -> 1.2147227 | GV11: PH05 | GW11: 1 | GX11: 1 | GY11: 62 | GZ11: =(HB11/GY11)/HL1 -> 0.79396462 | HA11: 2836 | HB11: 1526 | HC11: 238604 | HD11: 341712 | HE11: 249618 | HF11: 1231252 | HG11: 1158676 | HH11: =HF11-HG11 -> 72576 | HI11: 1250 | HJ11: 276048 | HK11: 179856 | HL11: 14132 | HM11: 12606 | HN11: 8434349 | HO11: 7612774 | HP11: 821575 | HQ11: 177660 | HR11: 552691.81 | HS11: 295202.22 | HT11: 66731.06 | HU11: =(GW11*3200)*31 -> 99200 | HV11: =(GX11*1733)*31 -> 53723 | HW11: 112535.73 | HX11: 223.92661 | HY11: 596.82628 | HZ11: =HF11/(HS11+HT11+HQ11+HU11) -> 1.9274655 | IA11: =HP11/(HS11+HT11+HQ11+HU11+HV11) -> 1.186362 | ID11: PH05 | IE11: 2 | IF11: 0 | IG11: 44 | IH11: =(IJ11/IG11)/IT1 -> 1.7543988 | II11: 4492 | IJ11: 2393 | IK11: 361538 | IL11: 512935 | IM11: 306657 | IN11: 1609815 | IO11: 1560944 | IP11: =IN11-IO11 -> 48871 | IQ11: 2038 | IR11: 438621 | IS11: 250295 | IT11: 17203 | IU11: 14810 | IV11: 9433861 | IW11: 8264830 | IX11: =IV11-IW11 -> 1169031 | IY11: 222840 | IZ11: 869686.61 | JA11: =IV11*3.5% -> 330185.14 | JB11: =IZ11*20% -> 173937.32 | JC11: 135174 | JD11: 0 | JE11: =IX11-JA11-JB11-IY11-JC11 -> 306894.54 | JF11: =IL11/IJ11 -> 214.3481 | JG11: =IV11/IT11 -> 548.38464 | JH11: =IL11/(JA11+JB11+IY11+JC11) -> 0.59495802 | JI11: =IX11/(JA11+JB11+IY11+JC11) -> 1.3559698 | JL11: PH05 | JM11: 3 | JN11: 44 | JQ11: 4301 | JR11: 2317 | JS11: 388495 | JT11: 606875 | JU11: 336456 | JV11: 1361274 | JW11: 968815 | JX11: =JV11-JW11 -> 392459 | JY11: 1950 | JZ11: 533241 | KA11: 295595 | KB11: 16511 | KC11: 14194 | KD11: 9215049 | KE11: 7422406 | KF11: =KD11-KE11 -> 1792643 | KG11: 345220 | KH11: 1549504 | KI11: =KD11*3.5% -> 322526.72 | KJ11: =KH11*20% -> 309900.8 | KK11: 155970 | KM11: =KF11-KI11-KJ11-KG11-KK11 -> 659025.48 | KN11: =JT11/JR11 -> 261.92274 | KO11: =KD11/KB11 -> 558.11574 | KP11: =JT11/(KI11+KJ11+KG11+KK11) -> 0.5353437 | KQ11: =KF11/(KI11+KJ11+KG11+KK11) -> 1.5813473 | KT11: PH05 | KU11: 3 | KW11: 92 | KY11: 10138 | KZ11: 5312 | LA11: 846736 | LB11: 1284876 | LC11: 726381 | LD11: 4062778 | LE11: 3547033 | LG11: 4273 | LH11: 1008982 | LI11: 764534 | LJ11: 27016 | LK11: 21704 | LL11: 12756382 | LM11: 10905781 | LN11: 1850601 | LO11: 477200 | LP11: 437141.55 | LQ11: 446473.37 | LR11: 87428.31 | LS11: 161169 | LU11: 678330.32 | LV11: 241.88178 | LW11: 472.17878 | LX11: 1.0960574 | LY11: 1.5786465 | MB11: PH05 | MC11: 3 | ME11: 102 | MG11: 13731 | MH11: 6336 | MI11: 939556 | MJ11: 1465643 | MK11: 1076080 | ML11: 4036806 | MM11: 3321493 | MO11: 5179 | MP11: 1230311 | MQ11: 831644 | MR11: 30122 | MS11: 23786 | MT11: 12326644 | MU11: 10295980 | MV11: =MT11-MU11 -> 2030664 | MW11: 439130 | MX11: 1515380.2 | MY11: =MT11*3.5% -> 431432.54 | MZ11: =MX11*20% -> 303076.04 | NA11: 155970 | NB11: =MV11-MY11-MZ11-MW11-NA11 -> 701055.42 | ND11: =MJ11/MH11 -> 231.31992 | NE11: =MT11/MR11 -> 409.22396 | NF11: =MJ11/(MY11+MZ11+MW11+NA11) -> 1.1023116 | NG11: =MV11/(MY11+MZ11+MW11+NA11) -> 1.5272645 | NJ11: PH05 | NK11: 3 | NM11: 90 | NO11: 15280 | NP11: 7798 | NQ11: 1361848 | NR11: 1704619 | NS11: 1166683 | NT11: 4843598 | NU11: 4137731 | NW11: 6512 | NX11: 1461463 | NY11: 1009595 | NZ11: 29501 | OA11: =NZ11-NP11 -> 21703 | OB11: 11845791 | OC11: 9817439 | OD11: =OB11-OC11 -> 2028352 | OE11: 560370 | OF11: 1486784.9 | OG11: =OB11*3.5% -> 414602.68 | OH11: =OF11*20% -> 297356.98 | OI11: 161169 | OK11: =OD11-OG11-OH11-OE11-OI11 -> 594853.33 | OL11: =NR11/NP11 -> 218.59695 | OM11: =OB11/NZ11 -> 401.53863 | ON11: =NR11/(OG11+OH11+OE11+OI11) -> 1.1891319 | OO11: =OD11/(OG11+OH11+OE11+OI11) -> 1.4149661 | OS11: PH05 | OT11: 3 | OU11: 103 | OV11: 19290 | OW11: 10454 | OX11: 1411461 | OY11: 1994026 | OZ11: 1210322 | PA11: 4979775 | PB11: 3978497 | PC11: 30472 | PD11: 20018 | PE11: 11909751 | PF11: 10070402 | PG11: =PE11-PF11 -> 1839349 | PH11: 982940 | PI11: 1196342.6 | PJ11: =PE11*3.5% -> 416841.28 | PK11: =PI11*20% -> 239268.52 | PL11: =OT11*1733*PF1+1 -> 161170 | PM11: =PG11-PJ11-PK11-PH11-PL11 -> 39129.197 | PN11: =OY11/OW11 -> 190.74287 | PO11: =PE11/PC11 -> 390.84245 | PP11: =OY11/(PH11+PJ11+PK11+PL11) -> 1.107657 | PQ11: =PG11/(PJ11+PK11+PH11+PL11) -> 1.0217358 | PU11: PH05 | PV11: 3 | PW11: 160 | PX11: 22627 | PY11: 10387 | PZ11: 1499005 | QA11: 2100241 | QB11: 1435241 | QC11: 27476 | QD11: 17089 | QE11: 11712488 | QF11: 11187395 | QG11: 525093 | QH11: 925330 | QI11: -79992.36 | QJ11: =QE11*3.5% -> 409937.08 | QK11: 0 | QL11: =PV11*3306*QG1+1 -> 297541 | QM11: =QG11-QJ11-QK11 -> 115155.92 | QN11: =PZ11/PY11 -> 144.31549 | QO11: =QE11/QC11 -> 426.28068 | QP11: =QA11/(QH11+QJ11+QK11+QL11) -> 1.2862755 | QQ11: =QG11/(QJ11+QK11) -> 1.2809112 | QR11: 披索 | QT11: 5-01玩家提款：82,928.97 / 5-03玩家提款：31,280.07 /5-04玩家提款：49,559.63 / 5-05玩家提款：55,009.54 / 5-11玩家提款：54,836.15 / 5-14玩家提款：49,219 / 5-19玩家提款：43,151.31/ 5-21玩家提款：67,556.89 + 30,727.83/ 5-30玩家提款：13,792.44 + 28,239.11/ 5-31玩家提款：32,084.01 + 23,036.23 + 17,894.50 + 49,546.24 总提款：628,861.92 | QU11: PH05 | QV11: 3 | QW11: 16584 | QX11: 7625 | QY11: 3669150 | QZ11: 8562 | RA11: 10985613 | RB11: 9782073 | RC11: =RB11-RE11 -> 9091873 | RD11: =RA11-RB11 -> 1203540 | RE11: 690200 | RF11: 759868.56 | RG11: =RA11*3.5% -> 384496.46 | RH11: =RF11*10% -> 75986.856 | RI11: =QV11*3306*31 -> 307458 | RJ11: =RD11-RG11-RH11 -> 743056.69 | RK11: =RA11/QZ11 -> 1283.0662 | RL11: =QY11/(RE11+RG11+RH11+RI11) -> 2.5163199 | RM11: =RD11/(RG11+RH11) -> 2.6136452 | RQ11: PH05 | RR11: 2 | RS11: 6429 | RT11: 2648 | RU11: 1611948 | RV11: 3223 | RW11: 9693213 | RX11: 8292377 | RY11: =RW11-RX11 -> 1400836 | RZ11: 403680 | SA11: 0 | SB11: 1265813.9 | SC11: =RW11*3.5% -> 339262.46 | SD11: =SB11*10% -> 126581.39 | SE11: =RR11*3306*30 -> 198360 | SF11: =RY11-SC11-SD11-SE11 -> 736632.16 | SG11: =RW11/RV11 -> 3007.5126 | SH11: =RU11/(RZ11+SC11+SD11+SE11) -> 1.5094788 | SI11: =RY11/(SC11+SD11+SE11) -> 2.1090453 | SJ11: 4月9开始 | SM11: PH05 | SN11: 3 | SO11: 4417 | SP11: 1529 | SQ11: 1172788 | SR11: 2011 | SS11: 8452896 | ST11: 7957166 | SU11: =SS11-ST11 -> 495730 | SV11: 72200 | SW11: 0 | SX11: 438651.86 | SY11: =SS11*3.5% -> 295851.36 | SZ11: =SX11*10% -> 43865.186 | TA11: =SN11*4000*31 -> 372000 | TB11: =SU11-SY11-SZ11-TA11 -> -215986.55 | TC11: =SS11/SR11 -> 4203.3297 | TD11: =SQ11/(SV11+SY11+SZ11+TA11) -> 1.4960623 | TE11: =SU11/(SY11+SZ11+TA11) -> 0.69652729 | TH11: PH05 | TI11: 5 | TJ11: 6241 | TK11: 1650 | TL11: 2702009 | TM11: 2020 | TN11: 8954093 | TO11: 8350972 | TP11: =TN11-TO11 -> 603121 | TQ11: 6350 | TR11: 0 | TS11: 616011.92 | TT11: =TN11*4% -> 358163.72 | TU11: =TS11*10% -> 61601.192 | TV11: =TI11*4000*28 -> 560000 | TW11: =TP11-TT11-TU11-TV11 -> -376643.91 | TX11: =TN11/TM11 -> 4432.7193 | TY11: =TL11/(TQ11+TT11+TU11+TV11) -> 2.7400549 | TZ11: =TP11/(TT11+TU11+TV11) -> 0.61557726 | UD11: PH05 | UE11: 3 | UF11: 5537 | UG11: 1745 | UH11: 3379772 | UI11: 2035 | UJ11: 8162950 | UK11: 7087639 | UL11: =UJ11-UK11 -> 1075311 | UM11: 142000 | UN11: 0 | UO11: 994856.96 | UP11: =UJ11*4% -> 326518 | UQ11: =UO11*10% -> 99485.696 | UR11: =UE11*4000*31 -> 372000 | US11: =UL11-UP11-UQ11-UR11 -> 277307.3 | UT11: =UJ11/UI11 -> 4011.2776 | UU11: =UH11/(UM11+UP11+UQ11+UR11) -> 3.595488 | UV11: =UL11/(UP11+UQ11+UR11) -> 1.3475013 | UZ11: PH05 | VA11: 3 | VB11: 3327 | VC11: 1504 | VD11: 1739071 | VE11: 1649 | VF11: 4063633 | VG11: 4177704 | VH11: =VF11-VG11 -> -114071 | VI11: 239400 | VJ11: 0 | VK11: -142626.37 | VL11: =VF11*4% -> 162545.32 | VM11: 0 | VN11: =VA11*4000*31 -> 372000 | VO11: =VH11-VL11-VM11-VN11 -> -648616.32 | VP11: =VF11/VE11 -> 2464.3014 | VQ11: =VD11/(VI11+VL11+VM11+VN11) -> 2.2470205 | VR11: =VH11/(VL11+VM11+VN11) -> -0.21339818
C12: PH05-2 | AJ12: PH05-2 | BQ12: PH05-2 | CO12: =IF(CM12>0,CM12*20%,0) -> 0 | CR12: =CK12-CN12-CO12-CL12-CP12-CQ12 -> 0 | CU12: =CA12/(CN12+CO12+CL12+CP12) -> #DIV/0! | CV12: =CK12/(CN12+CO12+CL12+CP12+CQ12) -> #DIV/0! | CX12: PH05-2 | DV12: =IF(DT12>0,DT12*20%,0) -> 0 | DY12: =DR12-DU12-DV12-DS12-DW12-DX12 -> 0 | EB12: =DH12/(DU12+DV12+DS12+DW12) -> #DIV/0! | EC12: =DR12/(DU12+DV12+DS12+DW12+DX12) -> #DIV/0! | EE12: PH05-2 | FC12: 0 | FF12: 0 | FI12: #DIV/0! | FJ12: #DIV/0! | FN12: PH05-2 | GO12: =GH12-GK12-GL12-GI12-GM12-GN12 -> 0 | GR12: =FX12/(GK12+GL12+GI12+GM12) -> #DIV/0! | GS12: =GH12/(GK12+GL12+GI12+GM12+GN12) -> #DIV/0! | GV12: PH05-2 | HW12: =HP12-HS12-HT12-HQ12-HU12-HV12 -> 0 | HZ12: =HF12/(HS12+HT12+HQ12+HU12) -> #DIV/0! | IA12: =HP12/(HS12+HT12+HQ12+HU12+HV12) -> #DIV/0! | ID12: PH05-2 | JL12: PH05-2 | JX12: =JV12-JW12 -> 0 | KT12: PH05-2 | LN12: 0 | LR12: 0 | LU12: 0 | LX12: #DIV/0! | LY12: #DIV/0! | MB12: PH05-2 | MZ12: =MX12*20% -> 0 | NB12: =MV12-MY12-MZ12-MW12-NA12 -> 0 | NF12: =MJ12/(MY12+MZ12+MW12+NA12) -> #DIV/0! | NG12: =MV12/(MY12+MZ12+MW12+NA12) -> #DIV/0! | NJ12: PH05-2 | OH12: =OF12*20% -> 0 | OK12: =OD12-OG12-OH12-OE12-OI12 -> 0 | OL12: =NR12/NP12 -> #DIV/0! | ON12: =NR12/(OG12+OH12+OE12+OI12) -> #DIV/0! | OO12: =OD12/(OG12+OH12+OE12+OI12) -> #DIV/0! | OS12: PH05-2 | OT12: 0 | PC12: 4605 | PD12: 4605 | PG12: =PE12-PF12 -> 0 | PJ12: =PE12*3.5% -> 0 | PK12: =PI12*20% -> 0 | PL12: =OT12*3306*PF9+1 -> 1 | PM12: =PG12-PJ12-PK12-PH12-PL12 -> -1 | PN12: =OY12/OW12 -> #DIV/0! | PO12: =PE12/PC12 -> 0 | PP12: =OY12/(PH12+PJ12+PK12+PL12) -> 0 | PQ12: =PG12/(PJ12+PK12+PH12+PL12) -> 0 | PU12: PH05-2 | PV12: 0 | QG12: 706272 | QJ12: =QE12*3.5% -> 0 | QK12: =QI12*10% -> 0 | QM12: 0 | QP12: =QA12/(QH12+QJ12+QK12+QL12) -> #DIV/0! | QQ12: =QG12/(QJ12+QK12) -> #DIV/0! | QR12: 披索 | QT12: 5月10停推 | QU12: PH05-2 | QV12: 0 | QZ12: 2875 | RA12: 1584523 | RB12: 1354073 | RC12: =RB12-RE12 -> 1354073 | RD12: =RA12-RB12 -> 230450 | RF12: 172858.96 | RG12: =RA12*3.5% -> 55458.305 | RH12: =RF12*10% -> 17285.896 | RI12: 0 | RJ12: =RD12-RG12-RH12 -> 157705.8 | RK12: =RA12/QZ12 -> 551.13843 | RL12: =QY12/(RE12+RG12+RH12+RI12) -> 0 | RM12: =RD12/(RG12+RH12) -> 3.1679501 | RQ12: PH05-2 | RR12: 1 | RV12: 1720 | RW12: 1374863 | RX12: 1354990 | RY12: =RW12-RX12 -> 19873 | SA12: 0 | SB12: -68784.4 | SC12: =RW12*3.5% -> 48120.205 | SD12: 0 | SE12: =RR12*3306*30 -> 99180 | SF12: =RY12-SC12-SD12-SE12 -> -127427.21 | SG12: =RW12/RV12 -> 799.33895 | SH12: =RU12/(RZ12+SC12+SD12+SE12) -> 0 | SI12: =RY12/(SC12+SD12+SE12) -> 0.13491495 | SJ12: 4月9开始 | SM12: PH05-2 | SN12: 2 | SR12: 641 | SS12: 1078373 | ST12: 971201 | SU12: =SS12-ST12 -> 107172 | SW12: 0 | SX12: 94235.36 | SY12: =SS12*3.5% -> 37743.055 | SZ12: =SX12*10% -> 9423.536 | TA12: =SN12*4000*31 -> 248000 | TB12: =SU12-SY12-SZ12-TA12 -> -187994.59 | TC12: =SS12/SR12 -> 1682.3292 | TD12: =SQ12/(SV12+SY12+SZ12+TA12) -> 0 | TE12: =SU12/(SY12+SZ12+TA12) -> 0.36308987 | TH12: PH05-2 | TI12: 3 | TM12: 508 | TN12: 1376668 | TO12: 1136772 | TP12: =TN12-TO12 -> 239896 | TQ12: 8360 | TR12: 0 | TS12: 230776.3 | TT12: =TN12*4% -> 55066.72 | TU12: =TS12*10% -> 23077.63 | TV12: =TI12*4000*28 -> 336000 | TW12: =TP12-TT12-TU12-TV12 -> -174248.35 | TX12: =TN12/TM12 -> 2709.9764 | TY12: =TL12/(TQ12+TT12+TU12+TV12) -> 0 | TZ12: =TP12/(TT12+TU12+TV12) -> 0.57925697 | UD12: PH05-2 | UE12: 2 | UI12: 725 | UJ12: 1044329 | UK12: 940938 | UL12: =UJ12-UK12 -> 103391 | UM12: 94000 | UN12: 0 | UO12: 83226.97 | UP12: =UJ12*4% -> 41773.16 | UQ12: =UO12*10% -> 8322.697 | UR12: =UE12*4000*31 -> 248000 | US12: =UL12-UP12-UQ12-UR12 -> -194704.86 | UT12: =UJ12/UI12 -> 1440.4538 | UU12: =UH12/(UM12+UP12+UQ12+UR12) -> 0 | UV12: =UL12/(UP12+UQ12+UR12) -> 0.3468381 | UZ12: PH05-2 | VA12: 2 | VE12: 529 | VF12: 682164 | VG12: 1249836 | VH12: =VF12-VG12 -> -567672 | VI12: 0 | VJ12: 0 | VK12: -569631.23 | VL12: =VF12*4% -> 27286.56 | VM12: 0 | VN12: =VA12*4000*12 -> 96000 | VO12: =VH12-VL12-VM12-VN12 -> -690958.56 | VP12: =VF12/VE12 -> 1289.535 | VQ12: =VD12/(VI12+VL12+VM12+VN12) -> 0 | VR12: =VH12/(VL12+VM12+VN12) -> -4.6044922 | VS12: 12月20-31
C13: PH16 | AJ13: PH16 | BQ13: PH16 | BR13: 1 | BS13: 2 | BT13: 18 | BU13: 3.2867384 | BV13: 3167 | BW13: 1834 | BX13: 270293 | BY13: 369409 | BZ13: 259756.76 | CA13: 746154 | CB13: 620747.11 | CC13: 125406.89 | CD13: 1677 | CE13: 338819 | CF13: 234061.11 | CG13: 6193 | CH13: 4359 | CI13: 3622124 | CJ13: 2424360 | CK13: =CI13-CJ13 -> 1197764 | CL13: 247660 | CM13: 1018054.6 | CN13: =CI13*3.5% -> 126774.34 | CO13: =IF(CM13>0,CM13*20%,0) -> 203610.91 | CP13: =(BR13*3200)*CI1 -> 99200 | CQ13: =(BS13*1733)*CI1 -> 107446 | CR13: =CK13-CN13-CO13-CL13-CP13-CQ13 -> 413072.75 | CS13: =BY13/BW13 -> 201.42257 | CT13: =CI13/CG13 -> 584.87389 | CU13: =CA13/(CN13+CO13+CL13+CP13) -> 1.1017486 | CV13: =CK13/(CN13+CO13+CL13+CP13+CQ13) -> 1.5264144 | CX13: PH16 | CY13: 1 | CZ13: 2 | DA13: 28 | DB13: 2.3083333 | DC13: 3638 | DD13: 1939 | DE13: 292996 | DF13: 415328 | DG13: 332388.61 | DH13: 944364 | DI13: 925862.61 | DJ13: =DH13-DI13 -> 18501.39 | DK13: 1764 | DL13: 331474 | DM13: 280047.61 | DN13: 6568 | DO13: 4629 | DP13: 3822160 | DQ13: 2889454 | DR13: =DP13-DQ13 -> 932706 | DS13: 273440 | DT13: 773289.53 | DU13: =DP13*3.5% -> 133775.6 | DV13: =IF(DT13>0,DT13*20%,0) -> 154657.91 | DW13: =(CY13*3200)*DP1 -> 96000 | DX13: =(CZ13*1733)*DP1 -> 103980 | DY13: =DR13-DU13-DV13-DS13-DW13-DX13 -> 170852.49 | DZ13: =DF13/DD13 -> 214.19701 | EA13: =DP13/DN13 -> 581.93666 | EB13: =DH13/(DU13+DV13+DS13+DW13) -> 1.4354796 | EC13: =DR13/(DU13+DV13+DS13+DW13+DX13) -> 1.224259 | EE13: PH16 | EF13: 1 | EG13: 2 | EH13: 25 | EI13: 2.9264516 | EJ13: 3829 | EK13: 2268 | EL13: 353322 | EM13: 473242 | EN13: 373187 | EO13: 1070414 | EP13: 1053760 | EQ13: 16654 | ER13: 2048 | ES13: 427625 | ET13: 323138 | EU13: 8873 | EV13: 6605 | EW13: 5556155 | EX13: 3819076 | EY13: 1737079 | EZ13: 249610 | FA13: 1648344.8 | FB13: 194465.42 | FC13: 329668.97 | FD13: =(EF13*3200)*EW1 -> 99200 | FE13: =(EG13*1733)*EW1 -> 107446 | FF13: 740165.61 | FG13: 208.66049 | FH13: 626.18675 | FI13: 1.2034325 | FJ13: 1.7424573 | FN13: PH16 | FO13: 1 | FP13: 2 | FQ13: 32 | FR13: =(FT13/FQ13)/GF1 -> 2.2265625 | FS13: 3858 | FT13: 1995 | FU13: 296431 | FV13: 426263 | FW13: 258756 | FX13: 1092752 | FY13: 1042840 | FZ13: =FX13-FY13 -> 49912 | GA13: 1764 | GB13: 369957 | GC13: 218093 | GD13: 8562 | GE13: 6567 | GF13: 4134364 | GG13: 3970593 | GH13: 163771 | GI13: 240130 | GJ13: 61881.27 | GK13: 144702.74 | GL13: 12376.254 | GM13: =(FO13*3200)*GF1 -> 89600 | GN13: =(FP13*1733)*GF1 -> 97048 | GO13: -435009.99 | GP13: 213.66566 | GQ13: 482.87363 | GR13: =FX13/(GK13+GL13+GI13+GM13) -> 2.2447243 | GS13: =GH13/(GK13+GL13+GI13+GM13+GN13) -> 0.28049848 | GV13: PH16 | GW13: 1 | GX13: 2 | GY13: 21 | GZ13: =(HB13/GY13)/HL1 -> 2.3732719 | HA13: 3143 | HB13: 1545 | HC13: 240576 | HD13: 320363 | HE13: 175420 | HF13: 715225 | HG13: 573858 | HH13: =HF13-HG13 -> 141367 | HI13: 1325 | HJ13: 283798 | HK13: 151269 | HL13: 8844 | HM13: 7299 | HN13: 4729862 | HO13: 5267151 | HP13: -537289 | HQ13: 195530 | HR13: -720760.05 | HS13: 165545.17 | HT13: 0 | HU13: =(GW13*3200)*31 -> 99200 | HV13: =(GX13*1733)*31 -> 107446 | HW13: -1121533.2 | HX13: 207.35469 | HY13: 534.81027 | HZ13: =HF13/(HS13+HT13+HQ13+HU13) -> 1.5539074 | IA13: =HP13/(HS13+HT13+HQ13+HU13+HV13) -> -0.94639592 | ID13: PH16 | IE13: 3 | IF13: 0 | IG13: 28 | IH13: =(IJ13/IG13)/IT1 -> 2.4354839 | II13: 4114 | IJ13: 2114 | IK13: 349028 | IL13: 518471 | IM13: 348394 | IN13: 1296240 | IO13: 1174121 | IP13: =IN13-IO13 -> 122119 | IQ13: 1821 | IR13: 451728 | IS13: 276913 | IT13: 10829 | IU13: 8715 | IV13: 4851950 | IW13: 4199439 | IX13: =IV13-IW13 -> 652511 | IY13: 313480 | IZ13: 475370.08 | JA13: =IV13*3.5% -> 169818.25 | JB13: =IZ13*20% -> 95074.016 | JC13: 161169 | JD13: 0 | JE13: =IX13-JA13-JB13-IY13-JC13 -> -87030.266 | JF13: =IL13/IJ13 -> 245.25591 | JG13: =IV13/IT13 -> 448.05153 | JH13: =IL13/(JA13+JB13+IY13+JC13) -> 0.70107109 | JI13: =IX13/(JA13+JB13+IY13+JC13) -> 0.88231858 | JL13: PH16 | JM13: 3 | JN13: 45 | JQ13: 4282 | JR13: 2436 | JS13: 387373 | JT13: 526544 | JU13: 351190 | JV13: 1371177 | JW13: 1195133 | JX13: =JV13-JW13 -> 176044 | JY13: 2084 | JZ13: 464203 | KA13: 289440 | KB13: 11873 | KC13: 9437 | KD13: 10236710 | KE13: 9339816 | KF13: =KD13-KE13 -> 896894 | KG13: 352780 | KH13: 830083.43 | KI13: =KD13*3.5% -> 358284.85 | KJ13: =KH13*20% -> 166016.69 | KK13: 155970 | KM13: =KF13-KI13-KJ13-KG13-KK13 -> -136157.54 | KN13: =JT13/JR13 -> 216.15107 | KO13: =KD13/KB13 -> 862.18395 | KP13: =JT13/(KI13+KJ13+KG13+KK13) -> 0.50969771 | KQ13: =KF13/(KI13+KJ13+KG13+KK13) -> 0.8681987 | KT13: PH16 | KU13: 3 | KW13: 72 | KY13: 9095 | KZ13: 4776 | LA13: 798263 | LB13: 1132247 | LC13: 1094100 | LD13: 4891824 | LE13: 4170434 | LG13: 4052 | LH13: 972876 | LI13: 983291 | LJ13: 19907 | LK13: 15131 | LL13: 9160445 | LM13: 8103609 | LN13: 1056836 | LO13: 447110 | LP13: 948618.73 | LQ13: 320615.58 | LR13: 189723.75 | LS13: 161169 | LU13: -61782.321 | LV13: 237.07014 | LW13: 460.162 | LX13: 1.0121835 | LY13: 0.94476908 | MB13: PH16 | MC13: 3 | ME13: 118 | MG13: 11659 | MH13: 6763 | MI13: 1047122 | MJ13: 1514896 | MK13: 1164478 | ML13: 4093359 | MM13: 3715062 | MO13: 5832 | MP13: 1302490 | MQ13: 954601 | MR13: 20754 | MS13: 13991 | MT13: 6380530 | MU13: 5842079 | MV13: =MT13-MU13 -> 538451 | MW13: 549130 | MX13: 373278.12 | MY13: =MT13*3.5% -> 223318.55 | MZ13: =MX13*20% -> 74655.624 | NA13: 155970 | NB13: =MV13-MY13-MZ13-MW13-NA13 -> -464623.17 | ND13: =MJ13/MH13 -> 223.99763 | NE13: =MT13/MR13 -> 307.43616 | NF13: =MJ13/(MY13+MZ13+MW13+NA13) -> 1.5102532 | NG13: =MV13/(MY13+MZ13+MW13+NA13) -> 0.53680078 | NJ13: PH16 | NK13: 3 | NM13: 56 | NO13: 7253 | NP13: 4437 | NQ13: 629791 | NR13: 949999 | NS13: 643401 | NT13: 2317866 | NU13: 1999992 | NW13: 3850 | NX13: 795466 | NY13: 524850 | NZ13: 12453 | OA13: =NZ13-NP13 -> 8016 | OB13: 3641164 | OC13: 3089299 | OD13: =OB13-OC13 -> 551865 | OE13: 388890 | OF13: 340109.22 | OG13: =OB13*3.5% -> 127440.74 | OH13: =OF13*20% -> 68021.844 | OI13: 161169 | OK13: =OD13-OG13-OH13-OE13-OI13 -> -193656.58 | OL13: =NR13/NP13 -> 214.10841 | OM13: =OB13/NZ13 -> 292.39252 | ON13: =NR13/(OG13+OH13+OE13+OI13) -> 1.2742743 | OO13: =OD13/(OG13+OH13+OE13+OI13) -> 0.74024014 | OS13: PH16 | OT13: 3 | OU13: 35 | OV13: 7316 | OW13: 4311 | OX13: 645357 | OY13: 847657 | OZ13: 593968 | PA13: 1987956 | PB13: 1692123 | PC13: 11993 | PD13: 7682 | PE13: 3190162 | PF13: 2711417 | PG13: =PE13-PF13 -> 478745 | PH13: 376880 | PI13: 287083.66 | PJ13: =PE13*3.5% -> 111655.67 | PK13: =PI13*20% -> 57416.732 | PL13: =OT13*1733*PF1+1 -> 161170 | PM13: =PG13-PJ13-PK13-PH13-PL13 -> -228377.4 | PN13: =OY13/OW13 -> 196.62654 | PO13: =PE13/PC13 -> 266.002 | PP13: =OY13/(PH13+PJ13+PK13+PL13) -> 1.1987415 | PQ13: =PG13/(PJ13+PK13+PH13+PL13) -> 0.67703272 | PU13: PH16 | PV13: 3 | PW13: 60 | PX13: 10184 | PY13: 4852 | PZ13: 684067 | QA13: 926087 | QB13: 687098 | QC13: 10535 | QD13: 5683 | QE13: 2937505 | QF13: 2856819 | QG13: 80686 | QH13: 353910 | QI13: -144426.89 | QJ13: =QE13*4% -> 117500.2 | QK13: 0 | QL13: =PV13*3306*QG1+1 -> 297541 | QM13: =QG13-QJ13-QK13 -> -36814.2 | QN13: =PZ13/PY13 -> 140.9866 | QO13: =QE13/QC13 -> 278.83294 | QP13: =QA13/(QH13+QJ13+QK13+QL13) -> 1.2043508 | QQ13: =QG13/(QJ13+QK13) -> 0.68668819 | QT13: 5-19玩家提款：25,750.01 总提款：25,750.01 | QU13: PH16 | QV13: 2 | QW13: 4745 | QX13: 1998 | QY13: 869757 | QZ13: 2100 | RA13: 1034573 | RB13: 844994 | RC13: =RB13-RE13 -> 704834 | RD13: =RA13-RB13 -> 189579 | RE13: 140160 | RF13: 102634.16 | RG13: =RA13*4% -> 41382.92 | RH13: =RF13*10% -> 10263.416 | RI13: =QV13*3306*31 -> 204972 | RJ13: =RD13-RG13-RH13 -> 137932.66 | RK13: =RA13/QZ13 -> 492.65381 | RL13: =QY13/(RE13+RG13+RH13+RI13) -> 2.1920476 | RM13: =RD13/(RG13+RH13) -> 3.6707154 | RQ13: PH16 | RR13: 1 | RS13: 588 | RT13: 227 | RU13: 93771 | RV13: 227 | RW13: 91771 | RX13: 65722 | RY13: =RW13-RX13 -> 26049 | RZ13: 0 | SA13: 0 | SB13: 17242.33 | SC13: =RW13*4% -> 3670.84 | SD13: =SB13*10% -> 1724.233 | SE13: =RR13*3306*30 -> 99180 | SF13: =RY13-SC13-SD13-SE13 -> -78526.073 | SG13: =RW13/RV13 -> 404.27753 | SH13: =RU13/(RZ13+SC13+SD13+SE13) -> 0.89668596 | SI13: =RY13/(SC13+SD13+SE13) -> 0.24909378 | SJ13: 4月12开始 | SU13: =SS13-ST13 -> 0 | SY13: =SS13*3.5% -> 0 | SZ13: =SX13*10% -> 0 | TA13: =SN13*4000*31 -> 0 | TB13: =SU13-SY13-SZ13-TA13 -> 0 | TC13: =SS13/SR13 -> #DIV/0! | TD13: =SQ13/(SV13+SY13+SZ13+TA13) -> #DIV/0! | TE13: =SU13/(SY13+SZ13+TA13) -> #DIV/0! | TP13: =TN13-TO13 -> 0 | TT13: =TN13*4% -> 0 | TU13: =TS13*10% -> 0 | TV13: =TI13*4000*28 -> 0 | TW13: =TP13-TT13-TU13-TV13 -> 0 | TX13: =TN13/TM13 -> #DIV/0! | TY13: =TL13/(TQ13+TT13+TU13+TV13) -> #DIV/0! | TZ13: =TP13/(TT13+TU13+TV13) -> #DIV/0! | UL13: =UJ13-UK13 -> 0 | UM13: 94000 | UP13: =UJ13*4% -> 0 | UQ13: =UO13*10% -> 0 | UR13: =UE13*4000*31 -> 0 | US13: =UL13-UP13-UQ13-UR13 -> 0 | UT13: =UJ13/UI13 -> #DIV/0! | UU13: =UH13/(UM13+UP13+UQ13+UR13) -> 0 | UV13: =UL13/(UP13+UQ13+UR13) -> #DIV/0! | VH13: =VF13-VG13 -> 0 | VI13: 0 | VL13: =VF13*4% -> 0 | VM13: 0 | VN13: =VA13*4000*12 -> 0 | VO13: =VH13-VL13-VM13-VN13 -> 0 | VP13: =VF13/VE13 -> #DIV/0! | VQ13: =VD13/(VI13+VL13+VM13+VN13) -> #DIV/0! | VR13: =VH13/(VL13+VM13+VN13) -> #DIV/0!
C14: PH35 | D14: 1 | E14: 0 | F14: ='PH35'!AJ4 -> 17 | G14: =(I14/F14)/S1 -> 2.5723982 | H14: ='PH35'!G4 -> 1712 | I14: ='PH35'!H4 -> 1137 | J14: ='PH35'!T4 -> 292884 | K14: ='PH35'!U4 -> 380552 | L14: ='PH35'!V4 -> 324686 | M14: 741672 | N14: 648435 | O14: =M14-N14 -> 93237 | P14: ='PH35'!J4 -> 1047 | Q14: ='PH35'!R4 -> 360303 | R14: ='PH35'!S4 -> 295322 | S14: ='PH35'!K4 -> 2128 | T14: =S14-I14 -> 991 | U14: ='PH35'!W4 -> 960128 | V14: ='PH35'!X4 -> 830473 | W14: =U14-V14 -> 129655 | X14: ='PH35'!D4 -> 150719 | Y14: 119746.35 | Z14: =U14*3.5% -> 33604.48 | AA14: =IF(Y14>0,Y14*20%,0) -> 23949.27 | AB14: =(D14*3200)*S1 -> 83200 | AC14: =(E14*1733)*S1 -> 0 | AD14: =W14-Z14-AA14-X14-AB14-AC14 -> -161817.75 | AE14: =K14/I14 -> 334.69833 | AF14: =U14/S14 -> 451.18797 | AG14: =M14/(Z14+AA14+X14+AB14+AC14) -> 2.5445672 | AH14: =W14/(Z14+AA14+X14+AB14+AC14) -> 0.44482718 | AJ14: PH35 | AK14: 1 | AL14: 0 | AM14: 14 | AN14: =(AP14/AM14)/AZ1 -> 1.552381 | AO14: 1179 | AP14: 652 | AQ14: 200178 | AR14: 286106 | AS14: 146067.5 | AT14: 571926 | AU14: 453472.21 | AV14: =AT14-AU14 -> 118453.79 | AW14: 275175 | AX14: 275175 | AY14: 138522.5 | AZ14: 1130 | BA14: 478 | BB14: 571962 | BC14: 453472.21 | BD14: =BB14-BC14 -> 118489.79 | BE14: 45415 | BF14: 104021.16 | BG14: =BB14*3.5% -> 20018.67 | BH14: =IF(BF14>0,BF14*20%,0) -> 20804.232 | BI14: =(AK14*3200)*AZ1 -> 96000 | BJ14: =(AL14*1733)*AZ1 -> 0 | BK14: =BD14-BG14-BH14-BE14-BI14-BJ14 -> -63748.112 | BL14: =AR14/AP14 -> 438.81288 | BM14: =BB14/AZ14 -> 506.16106 | BN14: =AT14/(BG14+BH14+BE14+BI14) -> 3.1383482 | BO14: =BD14/(BG14+BH14+BE14+BI14+BJ14) -> 0.6501929 | JX14: =JV14-JW14 -> 0 | LN14: 0 | LQ14: 0 | LR14: 0 | LS14: 53723 | LU14: 0 | LV14: #DIV/0! | LW14: #DIV/0! | LX14: #DIV/0! | LY14: 0 | MB14: PH11 | MC14: 1 | ME14: ='[1]PH11'!AB4 -> 3 | MG14: ='[1]PH11'!G4 -> 0 | MH14: ='[1]PH11'!H4 -> 0 | MI14: ='[1]PH11'!Q4 -> 0 | MJ14: ='[1]PH11'!R4 -> 0 | MK14: ='[1]PH11'!S4 -> 0 | MR14: ='[1]PH11'!J4 -> 0 | MS14: =MR14-MH14 -> 0 | MT14: ='[1]PH11'!T4 -> 0 | MU14: ='[1]PH11'!U4 -> 0 | MV14: =MT14-MU14 -> 0 | MW14: 5940 | MX14: 14424.05 | MY14: =MT14*3.5% -> 0 | MZ14: =MX14*10% -> 1442.405 | NA14: ='[1]PH11'!B4 -> 0 | NB14: =MV14-MY14-MZ14 -> -1442.405 | ND14: =MI14/MH14 -> #DIV/0! | NE14: =MT14/MR14 -> #DIV/0! | NF14: =MJ14/(MY14+MZ14) -> 0 | NG14: =MV14/(MY14+MZ14) -> 0 | NJ14: PH11 | NK14: 1 | NM14: 10 | NO14: 432 | NP14: 206 | NQ14: 36686 | NR14: 1773 | NS14: 0 | NZ14: 302 | OA14: =NZ14-NP14 -> 96 | OB14: 76447 | OC14: 41913 | OD14: =OB14-OC14 -> 34534 | OE14: 7970 | OF14: 47929.4 | OG14: =OB14*3.5% -> 2675.645 | OH14: =OF14*10% -> 4792.94 | OI14: 102487 | OK14: =OD14-OG14-OH14 -> 27065.415 | OL14: =NQ14/NP14 -> 178.08738 | OM14: =OB14/NZ14 -> 253.13576 | ON14: =NR14/(OG14+OH14) -> 0.23739437 | OO14: =OD14/(OG14+OH14) -> 4.6239013 | OP14: 8月6号开始
JX15: =JV15-JW15 -> 0
C16: 总 | D16: =SUM(D4:D13) -> 11 | E16: =SUM(E4:E13) -> 9 | F16: =SUM(F4:F13) -> 155 | G16: =(I16/F16)/S1 -> 3.7394541 | H16: =SUM(H4:H14) -> 28468 | I16: =SUM(I4:I14) -> 15070 | J16: =SUM(J4:J14) -> 2496829 | K16: =SUM(K4:K14) -> 3446491 | L16: =SUM(L4:L14) -> 2351061.1 | M16: =SUM(M4:M14) -> 7939679 | N16: =SUM(N4:N14) -> 7241578.9 | O16: =SUM(O4:O14) -> 698100.11 | ... Y16: =SUM(Y4:Y14) -> 5601834.5 | Z16: =U16*3.5% -> 1524696.9 | AA16: =IF(Y16>0,Y16*20%,0) -> 1120366.9 | AB16: =SUM(AB4:AB14) -> 998400 | AC16: =SUM(AC4:AC14) -> 405522 | AD16: =W16-X16-Z16-AA16-AB16-AC16 -> -242658.5 | AE16: =K16/I16 -> 228.69881 | AF16: =U16/S16 -> 579.88591 | AG16: =K16/(Z16+AA16+X16+AB16+AC16) -> 0.53187165 | AH16: =W16/(Z16+AA16+X16+AB16+AC16) -> 0.9625523 | AJ16: 总 | AK16: =SUM(AK4:AK13) -> 8 | AL16: =SUM(AL4:AL13) -> 10 | AM16: =SUM(AM4:AM14) -> 196 | AN16: =(AP16/AM16)/AZ1 -> 2.755102 | AO16: =SUM(AO4:AO14) -> 31862 | AP16: =SUM(AP4:AP14) -> 16200 | AQ16: =SUM(AQ4:AQ14) -> 2609832 | AR16: =SUM(AR4:AR14) -> 4179788 | AS16: =SUM(AS4:AS14) -> 2349772 | AT16: =SUM(AT4:AT14) -> 9488069.5 | AU16: =SUM(AU4:AU14) -> 7651603.3 | AV16: =SUM(AV4:AV14) -> 1836466.1 | ... BF16: =SUM(BF4:BF14) -> 8061950.4 | BG16: =BB16*3.5% -> 1710601.5 | BH16: =IF(BF16>0,BF16*20%,0) -> 1612390.1 | BI16: =SUM(BI4:BI14) -> 864000 | BJ16: =SUM(BJ4:BJ14) -> 519900 | BK16: =BD16-BE16-BG16-BH16-BI16-BJ16 -> 1326817.3 | BL16: =AR16/AP16 -> 258.0116 | BM16: =BB16/AZ16 -> 590.36235 | BN16: =AR16/(BG16+BH16+BE16+BI16) -> 0.637644 | BO16: =BD16/(BG16+BH16+BE16+BI16+BJ16) -> 1.1875374 | BQ16: 总 | BR16: =SUM(BR4:BR13) -> 9 | BS16: =SUM(BS4:BS13) -> 13 | BT16: =SUM(BT4:BT13) -> 332 | BU16: =(BW16/BT16)/CI1 -> 1.3792266 | BV16: =SUM(BV4:BV13) -> 28602 | BW16: =SUM(BW4:BW13) -> 14195 | BX16: =SUM(BX4:BX13) -> 2194904.4 | BY16: =SUM(BY4:BY13) -> 3783165.7 | BZ16: =SUM(BZ4:BZ13) -> 2045647.7 | CA16: =SUM(CA4:CA13) -> 8647785.1 | CB16: =SUM(CB4:CB13) -> 7521787.6 | CC16: =CA16-CB16 -> 1125997.5 | CD16: =SUM(CD4:CD13) -> 12299 | CE16: =SUM(CE4:CE13) -> 2667207.7 | CF16: =SUM(CF4:CF13) -> 1741392.2 | CG16: =SUM(CG4:CG13) -> 97484 | CH16: =SUM(CH4:CH13) -> 84275 | CI16: =SUM(CI4:CI13) -> 64157972 | CJ16: =SUM(CJ4:CJ13) -> 52520716 | CK16: =SUM(CK4:CK13) -> 11368355 | ... CM16: =SUM(CM4:CM13) -> 9874981.8 | CN16: =CI16*3.5% -> 2245529 | CO16: =IF(CM16>0,CM16*20%,0) -> 1974996.4 | CP16: =SUM(CP4:CP13) -> 892800 | CQ16: =SUM(CQ4:CQ13) -> 698399 | CR16: =CK16-CL16-CN16-CO16-CP16-CQ16 -> 3617450.9 | CS16: =BY16/BW16 -> 266.51396 | CT16: =CI16/CG16 -> 658.13848 | CU16: =BY16/(CN16+CO16+CL16+CP16) -> 0.53642862 | CV16: =CK16/(CN16+CO16+CL16+CP16+CQ16) -> 1.4667134 | CX16: 总 | CY16: =SUM(CY4:CY13) -> 10 | CZ16: =SUM(CZ4:CZ13) -> 11 | DA16: =SUM(DA4:DA13) -> 309 | DB16: =(DD16/DA16)/DP1 -> 1.6477886 | DC16: =SUM(DC4:DC13) -> 28850 | DD16: =SUM(DD4:DD13) -> 15275 | DE16: =SUM(DE4:DE13) -> 2276296 | DF16: =SUM(DF4:DF13) -> 3650994 | DG16: =SUM(DG4:DG13) -> 2070114.1 | DH16: =SUM(DH4:DH13) -> 8663242.3 | DI16: =SUM(DI4:DI13) -> 7693770.2 | DJ16: =DH16-DI16 -> 969472.16 | DK16: =SUM(DK4:DK13) -> 13257 | DL16: =SUM(DL4:DL13) -> 2633217 | DM16: =SUM(DM4:DM13) -> 1711116.9 | DN16: =SUM(DN4:DN13) -> 109171 | DO16: =SUM(DO4:DO13) -> 93485 | DP16: =SUM(DP4:DP13) -> 63938220 | DQ16: =SUM(DQ4:DQ13) -> 56488886 | DR16: =SUM(DR4:DR13) -> 7449334.3 | ... DT16: =SUM(DT4:DT13) -> 6141914.3 | DU16: =DP16*3.5% -> 2237837.7 | DV16: =IF(DT16>0,DT16*20%,0) -> 1228382.9 | DW16: =SUM(DW4:DW13) -> 960000 | DX16: =SUM(DX4:DX13) -> 571890 | DY16: =DR16-DS16-DU16-DV16-DW16-DX16 -> 84093.695 | DZ16: =DF16/DD16 -> 239.01761 | EA16: =DP16/DN16 -> 585.67037 | EB16: =DF16/(DU16+DV16+DS16+DW16) -> 0.53743642 | EC16: =DR16/(DU16+DV16+DS16+DW16+DX16) -> 1.0114176 | EE16: 总 | EF16: =SUM(EF4:EF13) -> 12 | EG16: =SUM(EG4:EG13) -> 11 | EH16: =SUM(EH4:EH13) -> 417 | EI16: =(EK16/EH16)/EW1 -> 1.8198345 | EJ16: =SUM(EJ4:EJ13) -> 44903 | EK16: =SUM(EK4:EK13) -> 23525 | EL16: =SUM(EL4:EL13) -> 3654209.5 | EM16: =SUM(EM4:EM13) -> 5594475.5 | EN16: =SUM(EN4:EN13) -> 3153773.5 | EO16: =SUM(EO4:EO13) -> 13140116 | EP16: =SUM(EP4:EP13) -> 11736890 | EQ16: =EO16-EP16 -> 1403225.4 | ER16: =SUM(ER4:ER13) -> 20042 | ES16: =SUM(ES4:ES13) -> 4326534.4 | ET16: =SUM(ET4:ET13) -> 2619784.4 | EU16: =SUM(EU4:EU13) -> 139415 | EV16: =SUM(EV4:EV13) -> 115510 | EW16: =SUM(EW4:EW13) -> 75688300 | EX16: =SUM(EX4:EX13) -> 65206205 | EY16: =SUM(EY4:EY13) -> 10482095 | ... FA16: =SUM(FA4:FA13) -> 9176988 | FB16: =EW16*3.5% -> 2649090.5 | FC16: =IF(FA16>0,FA16*20%,0) -> 1835397.6 | FD16: =SUM(FD4:FD13) -> 1190400 | FE16: =SUM(FE4:FE13) -> 590953 | FF16: =EY16-EZ16-FB16-FC16-FD16-FE16 -> 1024314.3 | FG16: =EM16/EK16 -> 237.8098 | FH16: =EW16/EU16 -> 542.89926 | FI16: =EM16/(FB16+FC16+EZ16+FD16) -> 0.6309444 | FJ16: =EY16/(FB16+FC16+EZ16+FD16+FE16) -> 1.1083039 | FN16: 总 | FO16: =SUM(FO4:FO13) -> 12 | FP16: =SUM(FP4:FP13) -> 14 | FQ16: =SUM(FQ4:FQ13) -> 550 | FR16: =(FT16/FQ16)/$GF$1 -> 1.6298701 | FS16: =SUM(FS4:FS13) -> 51985 | FT16: =SUM(FT4:FT13) -> 25100 | FU16: =SUM(FU4:FU13) -> 3923093.2 | FV16: =SUM(FV4:FV13) -> 6290027.2 | FW16: =SUM(FW4:FW13) -> 3846324.2 | FX16: =SUM(FX4:FX13) -> 18475422 | FY16: =SUM(FY4:FY13) -> 17651447 | FZ16: =FX16-FY16 -> 823974.46 | GA16: =SUM(GA4:GA13) -> 21130 | GB16: =SUM(GB4:GB13) -> 4880368.2 | GC16: =SUM(GC4:GC13) -> 3181011.2 | GD16: =SUM(GD4:GD13) -> 144394 | GE16: =SUM(GE4:GE13) -> 119294 | GF16: =SUM(GF4:GF13) -> 75361987 | GG16: =SUM(GG4:GG13) -> 69002517 | GH16: =SUM(GH4:GH13) -> 6359469.5 | ... GJ16: =SUM(GJ4:GJ13) -> 5083802.5 | GK16: =GF16*3.5% -> 2637669.5 | GL16: =GJ16*20% -> 1016760.5 | GM16: =SUM(GM4:GM13) -> 1075200 | GN16: =SUM(GN4:GN13) -> 679336 | GO16: =GH16-GI16-GK16-GL16-GM16-GN16 -> -2169426.5 | GP16: =FV16/FT16 -> 250.59869 | GQ16: =GF16/GD16 -> 521.9191 | GR16: =FV16/(GK16+GL16+GI16+GM16) -> 0.80132226 | GS16: =GH16/(GK16+GL16+GI16+GM16+GN16) -> 0.74563807 | GV16: 总 | GW16: =SUM(GW4:GW13) -> 13 | GX16: =SUM(GX4:GX13) -> 13 | GY16: =SUM(GY4:GY13) -> 417 | GZ16: =(HB16/GY16)/HL1 -> 1.7236018 | HA16: =SUM(HA4:HA13) -> 48563 | HB16: =SUM(HB4:HB13) -> 22281 | HC16: =SUM(HC4:HC13) -> 3494216.1 | HD16: =SUM(HD4:HD13) -> 5017472.9 | HE16: =SUM(HE4:HE13) -> 3430372 | HF16: =SUM(HF4:HF13) -> 14389132 | HG16: =SUM(HG4:HG13) -> 13093924 | HH16: =HF16-HG16 -> 1295207.9 | HI16: =SUM(HI4:HI13) -> 18396 | HJ16: =SUM(HJ4:HJ13) -> 4164740 | HK16: =SUM(HK4:HK13) -> 2761254 | HL16: =SUM(HL4:HL13) -> 158038 | HM16: =SUM(HM4:HM13) -> 135757 | HN16: =SUM(HN4:HN13) -> 78901314 | HO16: =SUM(HO4:HO13) -> 72114921 | HP16: =SUM(HP4:HP13) -> 6786393.4 | ... HR16: =SUM(HR4:HR13) -> 5414129.1 | HS16: =HN16*3.5% -> 2761546 | HT16: =HR16*20% -> 1082825.8 | HU16: =SUM(HU4:HU13) -> 1289600 | HV16: =SUM(HV4:HV13) -> 698399 | HW16: =HP16-HQ16-HS16-HT16-HU16-HV16 -> -2156067.5 | HX16: =HD16/HB16 -> 225.19065 | HY16: =HN16/HL16 -> 499.25533 | HZ16: =HD16/(HS16+HT16+HQ16+HU16) -> 0.6086166 | IA16: =HP16/(HS16+HT16+HQ16+HU16+HV16) -> 0.75889551 | IB16: =(IJ16/IG16)/30 -> 2.6209476 | ID16: 总 | IE16: =SUM(IE4:IE13) -> 26 | IF16: =SUM(IF4:IF13) -> 0 | IG16: =SUM(IG4:IG13) -> 401 | IH16: =(IJ16/IG16)/IT1 -> 2.5364009 | II16: =SUM(II4:II13) -> 72851 | IJ16: =SUM(IJ4:IJ13) -> 31530 | IK16: =SUM(IK4:IK13) -> 4894721.8 | IL16: =SUM(IL4:IL13) -> 7169762.8 | IM16: =SUM(IM4:IM13) -> 4592105.6 | IN16: =SUM(IN4:IN13) -> 21408809 | IO16: =SUM(IO4:IO13) -> 19127529 | IP16: =IN16-IO16 -> 2281280 | IQ16: =SUM(IQ4:IQ13) -> 26126 | IR16: =SUM(IR4:IR13) -> 5987356.8 | IS16: =SUM(IS4:IS13) -> 3722045 | IT16: =SUM(IT4:IT13) -> 195779 | IU16: =SUM(IU4:IU13) -> 164249 | IV16: =SUM(IV4:IV13) -> 94022374 | IW16: =SUM(IW4:IW13) -> 80567959 | IX16: =SUM(IX4:IX13) -> 13454415 | ... IZ16: =SUM(IZ4:IZ13) -> 11307553 | JA16: =IV16*3.5% -> 3290783.1 | JB16: =IZ16*20% -> 2261510.7 | JC16: =SUM(JC4:JC13) -> 1497312 | JD16: =SUM(JD4:JD13) -> 0 | JE16: =IX16-IY16-JA16-JB16-JC16 -> 2923278.8 | JF16: =IL16/IJ16 -> 227.39495 | JG16: =IV16/IT16 -> 480.24749 | JH16: =IL16/(JA16+JB16+IY16+JC16) -> 0.68081573 | JI16: =IX16/(JA16+JB16+IY16+JC16) -> 1.2775844 | JL16: 总 | JM16: =SUM(JM4:JM13) -> 31 | JN16: 0 | JO16: =SUM(JO4:JO13) -> 453 | JP16: =(JR16/JO16)/KB1 -> 1.841869 | JQ16: =SUM(JQ4:JQ13) -> 60717 | JR16: =SUM(JR4:JR13) -> 25031 | JS16: =SUM(JS4:JS13) -> 3843437 | JT16: =SUM(JT4:JT13) -> 5553326 | JU16: =SUM(JU4:JU13) -> 3570139 | JV16: =SUM(JV4:JV13) -> 12894310 | JW16: =SUM(JW4:JW13) -> 10358110 | JX16: =JV16-JW16 -> 2536199.8 | JY16: =SUM(JY4:JY13) -> 1127343 | JZ16: =SUM(JZ4:JZ13) -> 4613195 | KA16: =SUM(KA4:KA13) -> 2736435 | KB16: =SUM(KB4:KB13) -> 162176 | KC16: =SUM(KC4:KC13) -> 137145 | KD16: =SUM(KD4:KD13) -> 85829092 | KE16: =SUM(KE4:KE13) -> 72384619 | KF16: =SUM(KF4:KF13) -> 13444473 | ... KH16: =SUM(KH4:KH13) -> 12112133 | KI16: =KD16*3.5% -> 3004018.2 | KJ16: =KH16*10% -> 1211213.3 | KK16: =SUM(KK4:KK13) -> 1597826 | KL16: =SUM(KL4:KL13) -> 0 | KM16: =KF16-KG16-KI16-KJ16-KK16 -> 4532945.8 | KN16: =JT16/JR16 -> 221.85794 | KO16: =KD16/KB16 -> 529.23424 | KP16: =JT16/(KI16+KJ16+KG16+KK16) -> 0.62316208 | KQ16: =KF16/(KI16+KJ16+KG16+KK16) -> 1.5086609 | KT16: 总 | KU16: 31 | KV16: 0 | KW16: 952 | KX16: =(KZ16/KW16)/LJ1 -> 1.4968826 | KY16: 102868 | KZ16: 44176 | LA16: 6768998 | LB16: 10069307 | LC16: 6846573.5 | LD16: 30778401 | LE16: 26019469 | LF16: =LD16-LE16 -> 4758931.9 | LG16: 35989 | LH16: 8237886 | LI16: 5707732.5 | LJ16: 246617 | LK16: 202441 | LL16: 1.1031058e+08 | LM16: 95191420 | LN16: 15119164 | LO16: 4180250 | LP16: 12056689 | LQ16: 3860870.4 | LR16: 1205668.9 | LS16: 1651549 | LT16: 0 | LU16: 4220825.8 | LV16: 227.93614 | LW16: 447.29513 | LX16: 0.92393048 | LY16: 1.3872908 | MB16: 总 | MC16: =SUM(MC4:MC13) -> 32 | MD16: =SUM(MD4:MD13) -> 0 | ME16: =SUM(ME4:ME13) -> 1113 | MF16: =(MH16/ME16)/MR1 -> 2.0363881 | MG16: =SUM(MG4:MG13) -> 170708 | MH16: =SUM(MH4:MH13) -> 67995 | MI16: =SUM(MI4:MI13) -> 10169622 | MJ16: =SUM(MJ4:MJ13) -> 15511479 | MK16: =SUM(MK4:MK13) -> 10531421 | ML16: =SUM(ML4:ML13) -> 43278928 | MM16: =SUM(MM4:MM13) -> 36040585 | MN16: =ML16-MM16 -> 7238343 | MO16: =SUM(MO4:MO13) -> 55657 | MP16: =SUM(MP4:MP13) -> 12766540 | MQ16: =SUM(MQ4:MQ13) -> 7977589 | MR16: =SUM(MR4:MR13) -> 285017 | MS16: =SUM(MS4:MS13) -> 217022 | MT16: =SUM(MT4:MT13) -> 1.1983316e+08 | MU16: =SUM(MU4:MU13) -> 102245800 | MV16: =SUM(MV4:MV13) -> 17587364 | ... MX16: =SUM(MX4:MX13) -> 15284565 | MY16: =MT16*3.5% -> 4194160.7 | MZ16: =MX16*20% -> 3056912.9 | NA16: =SUM(NA4:NA13) -> 1677544 | NB16: =MV16-MW16-MY16-MZ16-NA16 -> 3377836.4 | NC16: =MW16-MX16-MZ16-NA16-NB16 -> -18115948 | ND16: =MJ16/MH16 -> 228.12676 | NE16: =MT16/MR16 -> 420.44216 | NF16: =MJ16/(MY16+MZ16+MW16+NA16) -> 1.0916252 | NG16: =MV16/(MY16+MZ16+MW16+NA16) -> 1.2377163 | NJ16: 总 | NK16: =SUM(NK4:NK13) -> 35 | NL16: =SUM(NL4:NL13) -> 0 | NM16: =SUM(NM4:NM13) -> 851 | NN16: =(NP16/NM16)/NZ1 -> 2.7728668 | NO16: =SUM(NO4:NO13) -> 156722 | NP16: =SUM(NP4:NP13) -> 73151 | NQ16: =SUM(NQ4:NQ13) -> 10766364 | NR16: =SUM(NR4:NR13) -> 15669759 | NS16: =SUM(NS4:NS13) -> 10329120 | NT16: =SUM(NT4:NT13) -> 43072363 | NU16: =SUM(NU4:NU13) -> 36142180 | NV16: =NT16-NU16 -> 6930183.4 | NW16: =SUM(NW4:NW13) -> 59696 | NX16: =SUM(NX4:NX13) -> 12830713 | NY16: =SUM(NY4:NY13) -> 8378548 | NZ16: =SUM(NZ4:NZ13) -> 282504 | OA16: =SUM(OA4:OA13) -> 209353 | OB16: =SUM(OB4:OB13) -> 1.0672712e+08 | OC16: =SUM(OC4:OC13) -> 90361044 | OD16: =SUM(OD4:OD13) -> 16366078 | ... OF16: =SUM(OF4:OF13) -> 13247482 | OG16: =OB16*3.5% -> 3735449.3 | OH16: =OF16*20% -> 2649496.3 | OI16: =SUM(OI4:OI13) -> 1734733 | OJ16: =SUM(OJ4:OJ13) -> 0 | OK16: =OD16-OG16-OH16-OE16-OI16 -> 2151839.6 | OL16: =NR16/NP16 -> 214.21114 | OM16: =OB16/NZ16 -> 377.78977 | ON16: =NR16/(OG16+OH16+OE16+OI16) -> 1.1023988 | OO16: =OD16/(OG16+OH16+OE16+OI16) -> 1.1513862 | OS16: 总 | OT16: =SUM(OT4:OT13) -> 31 | OU16: =SUM(OU4:OU13) -> 1029 | OV16: =SUM(OV4:OV13) -> 193185 | OW16: =SUM(OW4:OW13) -> 90387 | OX16: =SUM(OX4:OX13) -> 12853450 | OY16: =SUM(OY4:OY13) -> 17788355 | OZ16: =SUM(OZ4:OZ13) -> 11166247 | PA16: =SUM(PA4:PA13) -> 44279026 | ... PF16: =SUM(PF4:PF13) -> 83307543 | PG16: =PE16-PF16 -> 16807817 | PH16: =SUM(PH4:PH13) -> 8013840 | PI16: =SUM(PI4:PI13) -> 13221817 | PJ16: =PE16*3.5% -> 3504037.6 | PK16: =PI16*20% -> 2644363.5 | PL16: =SUM(PL4:PL13) -> 1665423 | PM16: =PG16-PJ16-PK16-PH16-PL16 -> 980153.19 | PN16: =OY16/OW16 -> 196.80214 | PO16: =PE16/PC16 -> 328.41937 | PP16: =OY16/(PH16+PJ16+PK16+PL16) -> 1.1238775 | PQ16: =PG16/(PJ16+PK16+PH16+PL16) -> 1.0619266 | PU16: 总 | PV16: =SUM(PV4:PV13) -> 30 | PW16: =SUM(PW4:PW13) -> 1223 | PX16: =SUM(PX4:PX13) -> 181492 | PY16: =SUM(PY4:PY13) -> 76919 | PZ16: =SUM(PZ4:PZ13) -> 11470292 | QA16: =SUM(QA4:QA13) -> 14823512 | QB16: =SUM(QB4:QB13) -> 9017672 | QC16: =SUM(QC4:QC13) -> 245522 | ... QJ16: =SUM(QJ4:QJ13) -> 3084724.8 | QK16: =QI16*20% -> 1236906.8 | QL16: =SUM(QL4:QL13) -> 2975407 | QM16: =SUM(QM4:QM13) -> 5320077.7 | QN16: =SUM(QN4:QN13) -> 1052.8712 | QO16: =QE16/QC16 -> 357.26065 | QP16: =QA16/(QH16+QJ16+QK16+QL16) -> 1.0374698 | QQ16: =QG16/(QJ16+QK16) -> 2.5333166 | QU16: 总 | QV16: =SUM(QV4:QV13) -> 27 | QW16: =SUM(QW4:QW13) -> 195196 | QX16: =SUM(QX4:QX13) -> 76125 | QY16: =SUM(QY4:QY13) -> 38184989 | QZ16: =SUM(QZ4:QZ13) -> 104463 | RA16: =SUM(RA4:RA13) -> 95609552 | RB16: =SUM(RB4:RB13) -> 84755569 | RC16: =RB16-RE16 -> 78333909 | RD16: =SUM(RD4:RD13) -> 14009924 | RE16: =SUM(RE4:RE13) -> 6421660 | RF16: =SUM(RF4:RF13) -> 7570843.8 | RG16: =SUM(RG4:RG13) -> 3351507.2 | RH16: =SUM(RH4:RH13) -> 788202.67 | RI16: =SUM(RI4:RI13) -> 2767122 | RJ16: =RD16-RG16-RH16 -> 9870213.8 | RK16: =RA16/QZ16 -> 915.24801 | RL16: =QY16/(RE16+RG16+RH16+RI16) -> 2.8649144 | RM16: =RD16/(RG16+RH16) -> 3.3842767 | RQ16: 总 | RR16: =SUM(RR4:RR13) -> 28 | RS16: =SUM(RS4:RS13) -> 166013 | RT16: =SUM(RT4:RT13) -> 57435 | RU16: =SUM(RU4:RU13) -> 30128332 | RV16: =SUM(RV4:RV13) -> 85913 | RW16: =SUM(RW4:RW13) -> 75915440 | RX16: =SUM(RX4:RX13) -> 68088871 | RY16: =SUM(RY4:RY13) -> 7826568.7 | ... SF16: =SUM(SF4:SF13) -> 1810808.9 | SG16: =RW16/RV16 -> 883.63158 | SH16: =RU16/(RZ16+SC16+SD16+SE16) -> 2.6630714 | SI16: =RY16/(SC16+SD16+SE16) -> 1.3010108 | SM16: 总 | SN16: =SUM(SN4:SN13) -> 36 | SO16: =SUM(SO4:SO13) -> 154057 | SP16: =SUM(SP4:SP13) -> 51910 | SQ16: =SUM(SQ4:SQ13) -> 25554460 | SR16: =SUM(SR4:SR13) -> 72756 | SS16: =SUM(SS4:SS13) -> 70302124 | ST16: =SUM(ST4:ST13) -> 64016126 | SU16: =SUM(SU4:SU13) -> 6285997.4 | ... TB16: =SUM(TB4:TB13) -> -1128791.2 | TC16: =SS16/SR16 -> 966.27252 | TD16: =SQ16/(SV16+SY16+SZ16+TA16) -> 2.1097357 | TE16: =SU16/(SY16+SZ16+TA16) -> 0.84776488 | TH16: 总 | TI16: =SUM(TI4:TI13) -> 39 | TJ16: =SUM(TJ4:TJ13) -> 154976 | TK16: =SUM(TK4:TK13) -> 55888 | TL16: =SUM(TL4:TL13) -> 27507759 | TM16: =SUM(TM4:TM13) -> 74928 | TN16: =SUM(TN4:TN13) -> 64527054 | TO16: =SUM(TO4:TO13) -> 61662572 | TP16: =SUM(TP4:TP13) -> 2864482 | ... TW16: =SUM(TW4:TW13) -> -4434764.4 | TX16: =TN16/TM16 -> 861.18746 | TY16: =TL16/(TQ16+TT16+TU16+TV16) -> 2.0378493 | TZ16: =TP16/(TT16+TU16+TV16) -> 0.39243531 | UD16: 总 | UE16: =SUM(UE4:UE13) -> 28 | UF16: =SUM(UF4:UF13) -> 146046 | UG16: =SUM(UG4:UG13) -> 51468 | UH16: =SUM(UH4:UH13) -> 29823407 | UI16: =SUM(UI4:UI13) -> 66396 | UJ16: =SUM(UJ4:UJ13) -> 62117850 | UK16: =SUM(UK4:UK13) -> 58857443 | UL16: =SUM(UL4:UL13) -> 3260406.9 | ... US16: =SUM(US4:US13) -> -2684007.9 | UT16: =UJ16/UI16 -> 935.56615 | UU16: =UH16/UM16 -> 5.9336012 | UV16: =UL16/(UP16+UQ16+UR16) -> 0.5484824 | UZ16: 总 | VA16: =SUM(VA4:VA13) -> 20 | VB16: =SUM(VB4:VB13) -> 105880 | VC16: =SUM(VC4:VC13) -> 37094 | VD16: =SUM(VD4:VD13) -> 22695885 | VE16: =SUM(VE4:VE13) -> 48239 | VF16: =SUM(VF4:VF13) -> 49300264 | VG16: =SUM(VG4:VG13) -> 51237237 | VH16: =SUM(VH4:VH13) -> -1936973 | ... VO16: =SUM(VO4:VO13) -> -5676983.6 | VP16: =VF16/VE16 -> 1022.0001 | VQ16: =VD16/VI16 -> 6.7460441 | VR16: =VH16/(VL16+VM16+VN16) -> -0.51790576
C18: 平台 | D18: 现场人数 | E18: 转线上人数 | F18: 线上人数 | G18: 人均开发 | H18: 总注册 | I18: 总开发人数 | J18: 首存金额 | K18: 首存总金额 | L18: 首提总金额 | M18: 新客总存 | N18: 新客总提 | O18: 新客存提差 | P18: 一级首存 | Q18: 一级存款 | R18: 一级提款 | S18: 充值人数 | T18: 复存人数 | U18: 存款 | V18: 提款 | W18: 存提差 | X18: 线上员工资 | Y18: 平台盈亏 | Z18: 充值 手续费3.5% | AA18: 平台 服务费20% | AB18: 现场员工资 | AC18: 转线上员工资 | AD18: 净利润 | AE18: 新客单价 | AF18: 客单价 | AG18: 支出回报率 | AH18: 投产比 | AJ18: 平台 | AK18: 现场人数 | AL18: 现场转线上 | AM18: 线上人数 | AN18: 人均开发 | AO18: 总注册 | AP18: 总开发人数 | AQ18: 首存金额 | AR18: 首存总金额 | AS18: 首提总金额 | AT18: 新客总存 | AU18: 新客总提 | AV18: 新客存提差 | AW18: 一级首存 | AX18: 一级存款 | AY18: 一级提款 | AZ18: 充值人数 | BA18: 复存人数 | BB18: 存款 | BC18: 提款 | BD18: 存提差 | BE18: 线上人员工资 | BF18: 平台盈亏 | BG18: 充值手续费5.5% | BH18: 平台服务费20% | BI18: 现场人员工资 | BJ18: 现场转线上 | BK18: 净利润 | BL18: 新客客单价 | BM18: 人均客单价 | BN18: 投资回报率 | BO18: 投产比 | BQ18: 平台 | BR18: 现场人数 | BS18: 现场转线上 | BT18: 线上人数 | BU18: 人均开发 | BV18: 总注册 | BW18: 总开发人数 | BX18: 首存金额 | BY18: 首存总金额 | BZ18: 首提总金额 | CA18: 新客总存 | CB18: 新客总提 | CC18: 新客存提差 | CD18: 一级首存 | CE18: 一级存款 | CF18: 一级提款 | CG18: 充值人数 | CH18: 复存人数 | CI18: 存款 | CJ18: 提款 | CK18: 存提差 | CL18: 线上人员工资 | CM18: 平台盈亏 | CN18: 充值手续费5.5% | CO18: 平台服务费20% | CP18: 现场人员工资 | CQ18: 现场转线上 | CR18: 净利润 | CS18: 新客客单价 | CT18: 人均客单价 | CU18: 投资回报率 | CV18: 投产比 | CX18: 平台 | CY18: 现场人数 | CZ18: 转线上人数 | DA18: 线上人数 | DB18: 人均开发 | DC18: 总注册 | DD18: 总开发人数 | DE18: 首存金额 | DF18: 首存总金额 | DG18: 首提总金额 | DH18: 新客总存 | DI18: 新客总提 | DJ18: 新客存提差 | DK18: 一级首存 | DL18: 一级存款 | DM18: 一级提款 | DN18: 充值人数 | DO18: 复存人数 | DP18: 存款 | DQ18: 提款 | DR18: 存提差 | DS18: 线上员工资 | DT18: 平台盈亏 | DU18: 充值 手续费3.5% | DV18: 平台 服务费20% | DW18: 现场员工资 | DX18: 转线上员工资 | DY18: 净利润 | DZ18: 新客单价 | EA18: 客单价 | EB18: 支出回报率 | EC18: 投产比 | EE18: 平台 | EF18: 现场人数 | EG18: 转线上人数 | EH18: 线上人数 | EI18: 人均开发 | EJ18: 总注册 | EK18: 总开发人数 | EL18: 首存金额 | EM18: 首存总金额 | EN18: 首提总金额 | EO18: 新客总存 | EP18: 新客总提 | EQ18: 新客存提差 | ER18: 一级首存 | ES18: 一级存款 | ET18: 一级提款 | EU18: 充值人数 | EV18: 复存人数 | EW18: 存款 | EX18: 提款 | EY18: 存提差 | EZ18: 线上员工资 | FA18: 平台盈亏 | FB18: 充值 手续费3.5% | FC18: 平台 服务费20% | FD18: 现场员工资 | FE18: 转线上员工资 | FF18: 净利润 | FG18: 新客单价 | FH18: 客单价 | FI18: 支出回报率 | FJ18: 投产比 | FN18: 平台 | FO18: 现场人数 | FP18: 转线上人数 | FQ18: 线上人数 | FR18: 人均开发 | FS18: 总注册 | FT18: 总开发人数 | FU18: 首存金额 | FV18: 首存总金额 | FW18: 首提总金额 | FX18: 新客总存 | FY18: 新客总提 | FZ18: 新客存提差 | GA18: 一级首存 | GB18: 一级存款 | GC18: 一级提款 | GD18: 充值人数 | GE18: 复存人数 | GF18: 存款 | GG18: 提款 | GH18: 存提差 | GI18: 线上员工资 | GJ18: 平台盈亏 | GK18: 充值 手续费3.5% | GL18: 平台 服务费20% | GM18: 现场员工资 | GN18: 转线上员工资 | GO18: 净利润 | GP18: 新客单价 | GQ18: 客单价 | GR18: 支出回报率 | GS18: 投产比 | GV18: 平台 | GW18: 现场人数 | GX18: 转线上人数 | GY18: 线上人数 | GZ18: 人均开发 | HA18: 总注册 | HB18: 总开发人数 | HC18: 首存金额 | HD18: 首存总金额 | HE18: 首提总金额 | HF18: 新客总存 | HG18: 新客总提 | HH18: 新客存提差 | HI18: 一级首存 | HJ18: 一级存款 | HK18: 一级提款 | HL18: 充值人数 | HM18: 复存人数 | HN18: 存款 | HO18: 提款 | HP18: 存提差 | HQ18: 线上员工资 | HR18: 平台盈亏 | HS18: 充值 手续费3.5% | HT18: 平台 服务费20% | HU18: 现场员工资 | HV18: 转线上员工资 | HW18: 净利润 | HX18: 新客单价 | HY18: 客单价 | HZ18: 支出回报率 | IA18: 投产比 | ID18: 平台 | IE18: 现场人数 | IF18: 转线上人数 | IG18: 线上人数 | IH18: 人均开发 | II18: 总注册 | IJ18: 总开发人数 | IK18: 首存金额 | IL18: 首存总金额 | IM18: 首提总金额 | IN18: 新客总存 | IO18: 新客总提 | IP18: 新客存提差 | IQ18: 一级首存 | IR18: 一级存款 | IS18: 一级提款 | IT18: 充值人数 | IU18: 复存人数 | IV18: 存款 | IW18: 提款 | IX18: 存提差 | IY18: 线上员工资 | IZ18: 平台盈亏 | JA18: 充值 手续费3.5% | JB18: 平台 服务费20% | JC18: 现场员工资 | JD18: 转线上员工资 | JE18: 净利润 | JF18: 新客单价 | JG18: 客单价 | JH18: 支出回报率 | JI18: 投产比 | JL18: 平台 | JM18: 现场人数 | JN18: 转线上人数 | JO18: 线上人数 | JP18: 人均开发 | JQ18: 总注册 | JR18: 总开发人数 | JS18: 首存金额 | JT18: 首存总金额 | JU18: 首提总金额 | JV18: 新客总存 | JW18: 新客总提 | JX18: 新客存提差 | JY18: 一级首存 | JZ18: 一级存款 | KA18: 一级提款 | KB18: 充值人数 | KC18: 复存人数 | KD18: 存款 | KE18: 提款 | KF18: 存提差 | KG18: 线上员工资 | KH18: 平台盈亏 | KI18: 充值 手续费3.5% | KJ18: 平台 服务费20% | KK18: 现场员工资 | KL18: 转线上员工资 | KM18: 净利润 | KN18: 新客单价 | KO18: 客单价 | KP18: 支出回报率 | KQ18: 投产比 | KT18: 平台 | KU18: 现场人数 | KW18: 线上人数 | KY18: 注册 | KZ18: 首存 | LA18: 首存金额 | LB18: 首存总存金额 | LC18: 首提总金额 | LD18: 新客总存 | LE18: 新客总提 | LG18: 一级首存 | LH18: 一级存款 | LI18: 一级提款 | LJ18: 充值人数 | LK18: 复存人数 | LL18: 存款 | LM18: 提款 | LN18: 存提差 | LO18: 线上人员工资 | LP18: 平台盈亏 | LQ18: 充值手续费5.5% | LR18: 平台服务费20% | LS18: 现场人员工资 | LU18: 净利润 | LV18: 新客客单价 | LW18: 人均客单价 | LX18: 投资回报率 | LY18: 投产比 | MB18: 平台 | MC18: 现场人数 | ME18: 线上人数 | MG18: 注册 | MH18: 首存 | MI18: 首存金额 | MJ18: 首存总存金额 | MK18: 首提总金额 | ML18: 新客总存 | MM18: 新客总提 | MO18: 一级首存 | MP18: 一级存款 | MQ18: 一级提款 | MR18: 充值人数 | MS18: 复存人数 | MT18: 存款 | MU18: 提款 | MV18: 存提差 | MW18: 线上人员工资 | MX18: 平台盈亏 | MY18: 充值手续费5.5% | MZ18: 平台服务费20% | NA18: 现场人员工资 | NB18: 净利润 | ND18: 新客客单价 | NE18: 人均客单价 | NF18: 投资回报率 | NG18: 投产比 | NJ18: 平台 | NK18: 现场人数 | NM18: 线上人数 | NO18: 注册 | NP18: 首存 | NQ18: 首存金额 | NR18: 首存总存金额 | NS18: 首提总金额 | NT18: 新客总存 | NU18: 新客总提 | NW18: 一级首存 | NX18: 一级存款 | NY18: 一级提款 | NZ18: 充值人数 | OA18: 复存人数 | OB18: 存款 | OC18: 提款 | OD18: 存提差 | OE18: 外部人员工资 | OF18: 平台盈亏 | OG18: 充值手续费5.5% | OH18: 平台服务费20% | OI18: 现场人员工资 | OK18: 净利润 | OL18: 新客客单价 | OM18: 人均客单价 | ON18: 投资回报率 | OO18: 投产比 | OS18: 平台 | OT18: 现场人数 | OU18: 线上人数 | OV18: 注册 | OW18: 首存 | OX18: 首存金额 | OY18: 首存总存金额 | OZ18: 首提总金额 | PA18: 新客总存 | PB18: 新客总提 | PC18: 充值人数 | PD18: 复存人数 | PE18: 存款 | PF18: 提款 | PG18: 存提差 | PH18: 外部人员工资 | PI18: 平台盈亏 | PJ18: 充值手续费5.5% | PK18: 平台服务费20% | PL18: 现场人员工资 | PM18: 净利润 | PN18: 新客客单价 | PO18: 人均客单价 | PP18: 投资回报率 | PQ18: 投产比 | PU18: 平台 | PV18: 现场人数 | PW18: 线上人数 | PX18: 注册 | PY18: 首存 | PZ18: 首存金额 | QA18: 新客首存总金额 | QB18: 新客首提总金额 | QC18: 充值人数 | QD18: 复存人数 | QE18: 存款 | QF18: 提款 | QG18: 存提差 | QH18: 外部人员工资 | QI18: 平台盈亏 | QJ18: 充值手续费5.5% | QK18: 平台服务费20% | QL18: 现场人员工资 | QM18: 净利润 | QN18: 新款客单价 | QO18: 人均客单价 | QP18: 投资回报率 | QQ18: 投产比 | QU18: 平台 | QV18: 人数 | QW18: 注册 | QX18: 首存 | QY18: 首存/总存金额 | QZ18: 充值人数 | RA18: 存款 | RB18: 提款 | RC18: 提款 | RD18: 存提差 | RE18: 外部人员工资 | RF18: 平台盈亏 | RG18: 充值手续费5.5% | RH18: 平台服务费10% | RI18: 现场人员工资 | RJ18: 净利润 | RK18: 人均客单价 | RL18: 投资回报率 | RM18: 投产比 | RQ18: 平台 | RR18: 人数 | RS18: 注册 | RT18: 首存 | RU18: 首存/总存金额 | RV18: 充值人数 | RW18: 存款 | RX18: 提款 | RY18: 存提差 | RZ18: 外部人员工资 | SA18: - | SB18: 平台盈亏 | SC18: 充值手续费5.5% | SD18: 平台服务费10% | SE18: 现场人员工资 | SF18: 净利润 | SG18: 人均客单价 | SH18: 投资回报率 | SI18: 投产比 | SM18: 平台 | SN18: 人数 | SO18: 注册 | SP18: 首存 | SQ18: 首存/总存金额 | SR18: 充值人数 | SS18: 存款 | ST18: 提款 | SU18: 存提差 | SV18: 外部人员工资 | SW18: - | SX18: 平台盈亏 | SY18: 充值手续费5.5% | SZ18: 平台服务费10% | TA18: 现场人员工资 | TB18: 净利润 | TC18: 人均客单价 | TD18: 投资回报率 | TE18: 投产比 | TH18: 平台 | TI18: 人数 | TJ18: 注册 | TK18: 首存 | TL18: 首存/总存金额 | TM18: 充值人数 | TN18: 存款 | TO18: 提款 | TP18: 存提差 | TQ18: 外部人员工资 | TR18: 总赠金 | TS18: 平台盈亏 | TT18: 充值手续费5.5% | TU18: 平台服务费10% | TV18: 现场人员工资 | TW18: 净利润 | TX18: 人均客单价 | TY18: 投资回报率 | TZ18: 投产比 | UD18: 平台 | UE18: 人数 | UF18: 注册 | UG18: 首存 | UH18: 首存/总存金额 | UI18: 充值人数 | UJ18: 存款 | UK18: 提款 | UL18: 存提差 | UM18: 外部人员工资 | UN18: 总赠金 | UO18: 平台盈亏 | UP18: 充值手续费5.5% | UQ18: 平台服务费10% | UR18: 现场人员工资 | US18: 净利润 | UT18: 人均客单价 | UU18: 投资回报率 | UV18: 投产比 | UZ18: 平台 | VA18: 人数 | VB18: 注册 | VC18: 首存 | VD18: 首存/总存金额 | VE18: 充值人数 | VF18: 存款 | VG18: 提款 | VH18: 存提差 | VI18: 外部人员工资 | VJ18: 总赠金 | VK18: 平台盈亏 | VL18: 充值手续费5.5% | VM18: 平台服务费10% | VN18: 现场人员工资 | VO18: 净利润 | VP18: 人均客单价 | VQ18: 投资回报率 | VR18: 投产比
C19: BD09 | AJ19: BD09 | BQ19: BD09 | CX19: BD09 | EE19: BD09 | FN19: BD09 | GV19: BD09 | ID19: BD09 | JL19: BD09 | KT19: BD09 | MB19: BD09 | NH19: 停推9月2 | NJ19: BD09 | NK19: 2 | NM19: 23 | NO19: 549 | NP19: 228 | NQ19: 61952 | NR19: 88711 | NS19: 48859.71 | NT19: 227258 | NU19: 170518.71 | NW19: 167 | NX19: 67139 | NY19: 38159.71 | NZ19: 2080 | OA19: 1852 | OB19: 1321060 | OC19: 979896 | OD19: =OB19-OC19 -> 341164 | OE19: 4300 | OF19: 313133.77 | OG19: =OB19*5.5% -> 72658.3 | OH19: =OF19*10% -> 31313.377 | OI19: 228346 | OK19: =OD19-OG19-OH19-OE19-OI19 -> 4546.323 | OL19: =NR19/NP19 -> 389.08333 | OM19: =OB19/NZ19 -> 635.125 | ON19: =NR19/(OG19+OH19+OE19+OI19) -> 0.26353637 | OO19: =OD19/(OG19+OH19+OE19+OI19) -> 1.0135059 | OP19: 停推8月31 | OS19: BD09 | OT19: 2 | OU19: 19 | OV19: 959 | OW19: 461 | OX19: 147169 | OY19: 194942 | OZ19: 87926 | PA19: 404755 | PB19: 303319 | PC19: 2607 | PD19: 2146 | PE19: 1563074 | PF19: 1268391 | PG19: =PE19-PF19 -> 294683 | PH19: 40650 | PI19: 254537.77 | PJ19: =PE19*5.5% -> 85969.07 | PK19: =PI19*10% -> 25453.777 | PL19: 228346 | PM19: =PG19-PJ19-PK19-PH19-PL19 -> -85735.847 | PN19: =OY19/OW19 -> 422.86768 | PO19: =PE19/PC19 -> 599.56809 | PP19: =OY19/(PH19+PJ19+PK19+PL19) -> 0.51244044 | PQ19: =PG19/(PJ19+PK19+PH19+PL19) -> 0.77462776 | PU19: BD09 | PV19: 2 | PW19: 22 | PX19: 1242 | PY19: 707 | PZ19: 361465 | QA19: 498824 | QB19: 359198 | QC19: 3110 | QD19: 2403 | QE19: 2190829 | QF19: 1857009 | QG19: 333820 | QH19: 14530 | QI19: 286288.59 | QJ19: =QE19*5.5% -> 120495.6 | QK19: =QI19*10% -> 28628.859 | QL19: =PV19*6613*QG1+1 -> 396781 | QM19: =QG19-QJ19-QK19 -> 184695.55 | QN19: =PZ19/PY19 -> 511.26591 | QO19: =QE19/QC19 -> 704.44662 | QP19: =QA19/(QH19+QJ19+QK19+QL19) -> 0.89006503 | QQ19: =QG19/(QJ19+QK19) -> 2.2385329 | QT19: 5-12玩家提款：30,408.71 + 34,015.90/ 5-13玩家提款：30,998.20 + 16,136.42/ 5-21玩家提款：25,895.98/ 5-23玩家提款：50,894.72 总提款：188,349.9 | QU19: BD09 | QV19: 5 | QW19: 2959 | QX19: 1143 | QY19: 1348964 | QZ19: 1570 | RA19: 3198327 | RB19: 2957231 | RC19: =RB19-RE19 -> 2930091 | RD19: =RA19-RB19 -> 241096 | RE19: 27140 | RF19: 131117.88 | RG19: =RA19*5.5% -> 175907.98 | RH19: =RF19*10% -> 13111.788 | RI19: =QV19*6613*31 -> 1025015 | RJ19: =RD19-RG19-RH19 -> 52076.227 | RK19: =RA19/QZ19 -> 2037.151 | RL19: =QY19/(RE19+RG19+RH19+RI19) -> 1.0868445 | RM19: =RD19/(RG19+RH19) -> 1.2755068 | RQ19: BD09 | RR19: 5 | RS19: 2802 | RT19: 900 | RU19: 1275118 | RV19: 1185 | RW19: 2293386 | RX19: 1823734 | RY19: =RW19-RX19 -> 469652 | RZ19: 60640 | SA19: 0 | SB19: 323980.5 | SC19: =RW19*5.5% -> 126136.23 | SD19: =SB19*10% -> 32398.05 | SE19: =RR19*6613*30 -> 991950 | SF19: =RY19-SC19-SD19-SE19 -> -680832.28 | SG19: =RW19/RV19 -> 1935.3468 | SH19: =RU19/(RZ19+SC19+SD19+SE19) -> 1.0528383 | SI19: =RY19/(SC19+SD19+SE19) -> 0.40822114 | SM19: BD09 | SN19: 6 | SO19: 1554 | SP19: 609 | SQ19: 656920 | SR19: 919 | SS19: 1823278 | ST19: 1518106.2 | SU19: =SS19-ST19 -> 305171.83 | SV19: 90500 | SW19: 0 | SX19: 224567.12 | SY19: =SS19*5.5% -> 100280.29 | SZ19: =SX19*10% -> 22456.712 | TA19: =SN19*8500*31 -> 1581000 | TB19: =SU19-SY19-SZ19-TA19 -> -1398565.2 | TC19: =SS19/SR19 -> 1983.9804 | TD19: =SQ19/(SV19+SY19+SZ19+TA19) -> 0.36612777 | TE19: =SU19/(SY19+SZ19+TA19) -> 0.1791191 | TH19: BD09 | TI19: 6 | TJ19: 2710 | TK19: 1637 | TL19: 789967 | TM19: 1978 | TN19: 2491328 | TO19: 2138690 | TP19: =TN19-TO19 -> 352638 | TQ19: 414730 | TR19: 0 | TS19: 352383.48 | TT19: =TN19*4% -> 99653.12 | TU19: =TS19*10% -> 35238.348 | TV19: =TI19*8500*28 -> 1428000 | TW19: =TP19-TT19-TU19-TV19 -> -1210253.5 | TX19: =TN19/TM19 -> 1259.5187 | TY19: =TL19/(TQ19+TT19+TU19+TV19) -> 0.39945309 | TZ19: =TP19/(TT19+TU19+TV19) -> 0.22563179 | UD19: BD09 | UE19: 6 | UF19: 5312 | UG19: 3519 | UH19: 1997383 | UI19: 3830 | UJ19: 4094857 | UK19: 4457483 | UL19: =UJ19-UK19 -> -362626 | UM19: 1022433.6 | UN19: 0 | UO19: -325411.07 | UP19: =UJ19*4% -> 163794.28 | UQ19: 0 | UR19: =UE19*8500*31 -> 1581000 | US19: =UL19-UP19-UQ19-UR19 -> -2107420.3 | UT19: =UJ19/UI19 -> 1069.1533 | UU19: =UH19/(UM19+UP19+UQ19+UR19) -> 0.72179925 | UV19: =UL19/(UP19+UQ19+UR19) -> -0.2078331 | UZ19: BD09 | VA19: 6 | VB19: 3115 | VC19: 1733 | VD19: 2020800 | VE19: 1921 | VF19: 3317168 | VG19: 3760492 | VH19: =VF19-VG19 -> -443324 | VI19: 462959.6 | VJ19: 0 | VK19: -558669.74 | VL19: =VF19*5.5% -> 182444.24 | VM19: 0 | VN19: =VA19*8500*31 -> 1581000 | VO19: =VH19-VL19-VM19-VN19 -> -2206768.2 | VP19: =VF19/VE19 -> 1726.7923 | VQ19: =VD19/(VI19+VL19+VM19+VN19) -> 0.90765205 | VR19: =VH19/(VL19+VM19+VN19) -> -0.25139666
C20: BD02 | AJ20: BD02 | BQ20: BD02 | BR20: 2 | BS20: 0 | BT20: 14 | BU20: 0.62672811 | BV20: 661 | BW20: 272 | BX20: 56863 | BY20: 93142 | BZ20: 99190 | CA20: 255396 | CB20: 255278 | CC20: 118 | CD20: 209 | CE20: 73979 | CF20: 72388 | CG20: 1897 | CH20: 1573 | CI20: 2453310 | CJ20: 2315848 | CK20: =CI20-CJ20 -> 137462 | CL20: 4832 | CM20: 65093.59 | CN20: =CI20*5.5% -> 134932.05 | CO20: =IF(CM20>0,CM20*20%,0) -> 13018.718 | CP20: ='[1]BD02'!$B$4 -> 0 | CQ20: ='[1]BD02'!$C$4 -> 0 | CR20: =CK20-CN20-CO20-CL20-CP20-CQ20 -> -15320.768 | CS20: =BY20/BW20 -> 342.43382 | CT20: =CI20/CG20 -> 1293.2578 | CU20: =BY20/(CN20+CO20+CL20+CP20) -> 0.60963681 | CV20: =CK20/(CN20+CO20+CL20+CP20+CQ20) -> 0.89972188 | CX20: BD02 | CY20: 2 | CZ20: 0 | DA20: 19 | DB20: 0.33157895 | DC20: 628 | DD20: 189 | DE20: 51236 | DF20: 74405 | DG20: 56153 | DH20: 410068 | DI20: 392722 | DJ20: =DH20-DI20 -> 17346 | DK20: 140 | DL20: 57560 | DM20: 44510 | DN20: 1559 | DO20: 1370 | DP20: 2001366 | DQ20: 1831760 | DR20: =DP20-DQ20 -> 169606 | DS20: 3166 | DT20: 180516.44 | DU20: =DP20*5.5% -> 110075.13 | DV20: =IF(DT20>0,DT20*20%,0) -> 36103.288 | DW20: ='[1]BD02'!$B$4 -> 0 | DX20: ='[1]BD02'!$C$4 -> 0 | DY20: =DR20-DU20-DV20-DS20-DW20-DX20 -> 20261.582 | DZ20: =DF20/DD20 -> 393.67725 | EA20: =DP20/DN20 -> 1283.7498 | EB20: =DF20/(DU20+DV20+DS20+DW20) -> 0.49821079 | EC20: =DR20/(DU20+DV20+DS20+DW20+DX20) -> 1.1356702 | EE20: BD02 | EF20: 1 | EG20: 0 | EH20: 12 | EI20: 0.75806452 | EJ20: 636 | EK20: 282 | EL20: 61792 | EM20: 106272 | EN20: 68891 | EO20: 2327989 | EP20: 2592306 | EQ20: -264317.01 | ER20: 205 | ES20: 82535 | ET20: 53791 | EU20: 1879 | EV20: 1597 | EW20: 3805631 | EX20: 4027921 | EY20: -222290 | EZ20: 9998 | FA20: -326364.22 | FB20: 209309.7 | FC20: 0 | FD20: 245923 | FE20: 0 | FF20: -687520.7 | FG20: 376.85106 | FH20: 2025.3491 | FI20: 0.2284286 | FJ20: -0.47780595 | FN20: BD02 | FO20: 1 | FP20: 0 | FQ20: 13 | FR20: =(FT20/FQ20)/GF1 -> 0.63186813 | FS20: 557 | FT20: 230 | FU20: 51822 | FV20: 83771 | FW20: 63036 | FX20: 2265663 | FY20: 2414291.1 | FZ20: =FX20-FY20 -> -148628.07 | GA20: 166 | GB20: 58625 | GC20: 47703 | GD20: 1549 | GE20: 1319 | GF20: 3398087 | GG20: 3286127.1 | GH20: 111959.93 | GI20: 4167 | GJ20: 118991.84 | GK20: 186894.79 | GL20: 23798.368 | GM20: 222124 | GN20: 0 | GO20: -325024.22 | GP20: 364.22174 | GQ20: 2193.7295 | GR20: =FV20/(GK20+GL20+GI20+GM20) -> 0.1917026 | GS20: =GH20/(GK20+GL20+GI20+GM20+GN20) -> 0.2562105 | GV20: BD02 | GW20: 1 | GX20: 0 | GY20: 4 | GZ20: =(HB20/GY20)/HL1 -> 1.2258065 | HA20: 411 | HB20: 152 | HC20: 64100.77 | HD20: 123671.47 | HE20: 37900 | HF20: 294360.47 | HG20: 204923 | HH20: =HF20-HG20 -> 89437.47 | HI20: 113 | HJ20: 51710 | HK20: 18254 | HL20: 1536 | HM20: 1384 | HN20: 1572806.5 | HO20: 1432266.5 | HP20: 140539.99 | HQ20: 0 | HR20: -116705.72 | HS20: 86504.356 | HT20: 0 | HU20: =(GW20*6800)*31 -> 210800 | HV20: 0 | HW20: -183954.37 | HX20: 813.62809 | HY20: 1023.9625 | HZ20: =HD20/(HS20+HT20+HQ20+HU20) -> 0.41597598 | IA20: =HP20/(HS20+HT20+HQ20+HU20+HV20) -> 0.47271418 | IB20: 1月9开导盈亏有问题 | ID20: BD02 | IE20: 1 | IF20: 0 | IG20: 16 | IH20: =(IJ20/IG20)/IT1 -> 0.24193548 | II20: 472 | IJ20: 120 | IK20: 28736 | IL20: 38631 | IM20: 32808 | IN20: 103580 | IO20: 90575.35 | IP20: =IN20-IO20 -> 13004.65 | IQ20: 81 | IR20: 26986 | IS20: 18926 | IT20: 1505 | IU20: 1385 | IV20: 2182090 | IW20: 1509471 | IX20: =IV20-IW20 -> 672619 | IY20: 10999.8 | IZ20: 662002.99 | JA20: =IV20*5.5% -> 120014.95 | JB20: =IZ20*20% -> 132400.6 | JC20: 114173 | JD20: 0 | JE20: =IX20-JA20-JB20-IY20-JC20 -> 295030.65 | JF20: =IL20/IJ20 -> 321.925 | JG20: =IV20/IT20 -> 1449.8937 | JH20: =IL20/(JA20+JB20+IY20+JC20) -> 0.10230983 | JI20: =IX20/(JA20+JB20+IY20+JC20) -> 1.7813553 | JL20: BD02 | JM20: 1 | JN20: 23 | JQ20: 2487 | JR20: 1494 | JS20: 439548 | JT20: 486035 | JU20: 317203 | JV20: 749545 | JW20: 990491.83 | JY20: 1463 | JZ20: 469543 | KA20: 305307 | KB20: 2851 | KC20: 1357 | KD20: 2020468 | KE20: 2210004 | KF20: =KD20-KE20 -> -189536 | KG20: 29000 | KH20: -367085.26 | KI20: =KD20*5.5% -> 111125.74 | KJ20: 0 | KK20: 110490 | KM20: =KF20-KI20-KJ20-KG20-KK20 -> -440151.74 | KN20: =JT20/JR20 -> 325.32463 | KO20: =KD20/KB20 -> 708.68748 | KP20: =JT20/(KI20+KJ20+KG20+KK20) -> 1.9393634 | KQ20: =KF20/(KI20+KJ20+KG20+KK20) -> -0.75628131 | KT20: BD02 | KU20: 2 | KW20: 94 | KY20: 1539 | KZ20: 559 | LA20: 153183 | LB20: 212598 | LC20: 188384 | LD20: 459883 | LE20: 524263.33 | LG20: 439 | LH20: 170824 | LI20: 163869 | LJ20: 2256 | LK20: 1697 | LL20: 1644615 | LM20: 1617246 | LN20: 27369 | LO20: 0 | LP20: -58430.12 | LQ20: 90453.825 | LR20: 0 | LS20: 228346 | LU20: -291430.83 | LV20: 380.31843 | LW20: 728.99601 | LX20: 0.66686988 | LY20: 0.08585011 | MB20: BD02 | MC20: 2 | ME20: 47 | MG20: 1016 | MH20: 225 | MI20: 69640 | MJ20: 96229 | MK20: 53019 | ML20: 222650 | MM20: 204556 | MO20: 189 | MP20: 81275 | MQ20: 40987 | MR20: 1639 | MS20: 1414 | MT20: 1278151 | MU20: 1061232 | MV20: =MT20-MU20 -> 216919 | MW20: 0 | MX20: 188153.84 | MY20: =MT20*5.5% -> 70298.305 | MZ20: =MX20*20% -> 37630.768 | NA20: 511937 | NB20: =MV20-MY20-MZ20-MW20-NA20 -> -402947.07 | ND20: =MJ20/MH20 -> 427.68444 | NE20: =MT20/MR20 -> 779.83588 | NF20: =MJ20/(MY20+MZ20+MW20+NA20) -> 0.1552416 | NG20: =MV20/(MY20+MZ20+MW20+NA20) -> 0.34994495 | NJ20: BD02 | NK20: 2 | NM20: 16 | NO20: 350 | NP20: 114 | NQ20: 34620 | NR20: 59310 | NS20: 21335 | NT20: 173046 | NU20: 134872 | NW20: 0 | NX20: 0 | NY20: 0 | NZ20: 1575 | OA20: 1459 | OB20: 2004540 | OC20: 1550897 | OD20: =OB20-OC20 -> 453643 | OE20: 0 | OF20: 441253.54 | OG20: =OB20*5.5% -> 110249.7 | OH20: =OF20*20% -> 88250.708 | OI20: 202565 | OK20: =OD20-OG20-OH20-OE20-OI20 -> 52577.592 | OL20: =NR20/NP20 -> 520.26316 | OM20: =OB20/NZ20 -> 1272.7238 | ON20: =NR20/(OG20+OH20+OE20+OI20) -> 0.14788112 | OO20: =OD20/(OG20+OH20+OE20+OI20) -> 1.1310948 | OS20: BD02 | OT20: 1 | OU20: 24 | OV20: 671 | OW20: 212 | OX20: 53690 | OY20: 88912 | OZ20: 55936 | PA20: 310961 | PB20: 215550 | PC20: 1491 | PD20: 1279 | PE20: 1400742 | PF20: 1114194 | PG20: =PE20-PF20 -> 286548 | PH20: 0 | PI20: 243493.06 | PJ20: =PE20*5.5% -> 77040.81 | PK20: =PI20*20% -> 48698.612 | PL20: 202565 | PM20: =PG20-PJ20-PK20-PH20-PL20 -> -41756.422 | PN20: =OY20/OW20 -> 419.39623 | PO20: =PE20/PC20 -> 939.46479 | PP20: =OY20/(PH20+PJ20+PK20+PL20) -> 0.27082182 | PQ20: =PG20/(PJ20+PK20+PH20+PL20) -> 0.87281188 | PU20: BD02 | PV20: 1 | PW20: 9 | PX20: 621 | PY20: 191 | PZ20: 57187 | QA20: 87534 | QB20: 65786 | QC20: 1281 | QD20: 1090 | QE20: 1156910 | QF20: 944437 | QG20: 212473 | QH20: 0 | QI20: 192889.13 | QJ20: =QE20*5.5% -> 63630.05 | QK20: =QI20*20% -> 38577.826 | QL20: =PV20*6613*QG1+1 -> 198391 | QM20: =QG20-QJ20-QK20 -> 110265.12 | QN20: =PZ20/PY20 -> 299.40838 | QO20: =QE20/QC20 -> 903.13037 | QP20: =QA20/(QH20+QJ20+QK20+QL20) -> 0.29119869 | QQ20: =QG20/(QJ20+QK20) -> 2.078832 | QT20: 5-06玩家提款：19,227.16/ 5-09玩家提款：19,517.40/ 5-11玩家提款：18,399.31/ 5-22玩家提款：34,310.49/ 5-24玩家提款：45,921.57 总提款：137,375.93 | QU20: BD02 | QV20: 2 | QW20: 1029 | QX20: 277 | QY20: 517980 | QZ20: 396 | RA20: 1122410 | RB20: 891765 | RC20: =RB20-RE20 -> 883595 | RD20: =RA20-RB20 -> 230645 | RE20: 8170 | RF20: 191329.68 | RG20: =RA20*5.5% -> 61732.55 | RH20: =RF20*10% -> 19132.968 | RI20: =QV20*6613*31 -> 410006 | RJ20: =RD20-RG20-RH20 -> 149779.48 | RK20: =RA20/QZ20 -> 2834.3687 | RL20: =QY20/(RE20+RG20+RH20+RI20) -> 1.0379497 | RM20: =RD20/(RG20+RH20) -> 2.8522046 | RQ20: BD02 | RR20: 2 | RS20: 620 | RT20: 170 | RU20: 270816 | RV20: 283 | RW20: 811444 | RX20: 686054 | RY20: =RW20-RX20 -> 125390 | RZ20: 8170 | SA20: 0 | SB20: 106040.64 | SC20: =RW20*5.5% -> 44629.42 | SD20: =SB20*10% -> 10604.064 | SE20: =RR20*6613*30 -> 396780 | SF20: =RY20-SC20-SD20-SE20 -> -326623.48 | SG20: =RW20/RV20 -> 2867.2933 | SH20: =RU20/(RZ20+SC20+SD20+SE20) -> 0.5884957 | SI20: =RY20/(SC20+SD20+SE20) -> 0.27740323 | SM20: BD02 | SN20: 4 | SO20: 554 | SP20: 229 | SQ20: 471969 | SR20: 291 | SS20: 688733 | ST20: 550196 | SU20: =SS20-ST20 -> 138537 | SV20: 8540 | SW20: 0 | SX20: 125942.37 | SY20: =SS20*5.5% -> 37880.315 | SZ20: =SX20*10% -> 12594.237 | TA20: =SN20*8500*31 -> 1054000 | TB20: =SU20-SY20-SZ20-TA20 -> -965937.55 | TC20: =SS20/SR20 -> 2366.7801 | TD20: =SQ20/(SV20+SY20+SZ20+TA20) -> 0.42404567 | TE20: =SU20/(SY20+SZ20+TA20) -> 0.1254325 | TH20: BD02 | TI20: 4 | TJ20: 698 | TK20: 315 | TL20: 349760 | TM20: 351 | TN20: 423823 | TO20: 456647 | TP20: =TN20-TO20 -> -32824 | TQ20: 0 | TR20: 0 | TS20: -10803.15 | TT20: =TN20*4% -> 16952.92 | TU20: 0 | TV20: =TI20*8500*28 -> 952000 | TW20: =TP20-TT20-TU20-TV20 -> -1001776.9 | TX20: =TN20/TM20 -> 1207.4729 | TY20: =TL20/(TQ20+TT20+TU20+TV20) -> 0.36096697 | TZ20: =TP20/(TT20+TU20+TV20) -> -0.033875743 | UD20: BD02 | UE20: 4 | UF20: 1732 | UG20: 1215 | UH20: 562856 | UI20: 1222 | UJ20: 562736 | UK20: 833295 | UL20: =UJ20-UK20 -> -270559 | UM20: 184465 | UN20: 0 | UO20: 145350.66 | UP20: =UJ20*4% -> 22509.44 | UQ20: =UO20*10% -> 14535.066 | UR20: =UE20*8500*31 -> 1054000 | US20: =UL20-UP20-UQ20-UR20 -> -1361603.5 | UT20: =UJ20/UI20 -> 460.50409 | UU20: =UH20/(UM20+UP20+UQ20+UR20) -> 0.44127935 | UV20: =UL20/(UP20+UQ20+UR20) -> -0.24798163 | UZ20: BD02 | VA20: 4 | VB20: 166 | VC20: 84 | VD20: 61340 | VE20: 84 | VF20: 61340 | VG20: 41222 | VH20: =VF20-VG20 -> 20118 | VI20: 0 | VJ20: 0 | VK20: 13327.13 | VL20: =VF20*5.5% -> 3373.7 | VM20: =VK20*10% -> 1332.713 | VN20: =VA20*8500*8 -> 272000 | VO20: =VH20-VL20-VM20-VN20 -> -256588.41 | VP20: =VF20/VE20 -> 730.2381 | VQ20: =VD20/(VI20+VL20+VM20+VN20) -> 0.221679 | VR20: =VH20/(VL20+VM20+VN20) -> 0.072705218 | VS20: 12月24-31
C21: BD18 | AJ21: BD18 | BQ21: BD18 | CR21: =CK21-CN21-CO21-CL21-CP21-CQ21 -> 0 | CV21: =CK21/(CN21+CO21+CL21+CP21+CQ21) -> #DIV/0! | CX21: BD18 | DY21: =DR21-DU21-DV21-DS21-DW21-DX21 -> 0 | EC21: =DR21/(DU21+DV21+DS21+DW21+DX21) -> #DIV/0! | EE21: BD18 | FF21: 0 | FJ21: #DIV/0! | FN21: BD18 | GS21: =GH21/(GK21+GL21+GI21+GM21+GN21) -> #DIV/0! | GV21: BD18 | HQ21: 0 | HU21: 3733 | HW21: =HP21-HS21-HT21-HQ21-HU21-HV21 -> -3733 | IA21: =HP21/(HS21+HT21+HQ21+HU21+HV21) -> 0 | ID21: BD18 | JL21: BD18 | KT21: BD18 | LR21: 0 | LU21: 0 | LX21: #DIV/0! | LY21: #DIV/0! | MB21: BD18 | MZ21: =MX21*20% -> 0 | NB21: =MV21-MY21-MZ21-MW21-NA21 -> 0 | NF21: =MJ21/(MY21+MZ21+MW21+NA21) -> #DIV/0! | NG21: =MV21/(MY21+MZ21+MW21+NA21) -> #DIV/0! | NH21: 停推9月2 | NJ21: BD18 | NK21: 2 | NM21: 28 | NO21: 990 | NP21: 451 | NQ21: 113358 | NR21: 153455 | NS21: 91168 | NT21: 387712 | NU21: 314541 | NW21: 362 | NX21: 129415 | NY21: 72904 | NZ21: 1865 | OA21: 1414 | OB21: 1386713 | OC21: 1333968 | OD21: =OB21-OC21 -> 52745 | OE21: 22880 | OF21: -28469.9 | OG21: =OB21*5.5% -> 76269.215 | OH21: =OF21*20% -> -5693.98 | OI21: 228346 | OK21: =OD21-OG21-OH21-OE21-OI21 -> -269056.23 | OL21: =NR21/NP21 -> 340.25499 | OM21: =OB21/NZ21 -> 743.54584 | ON21: =NR21/(OG21+OH21+OE21+OI21) -> 0.47686268 | OO21: =OD21/(OG21+OH21+OE21+OI21) -> 0.16390552 | OP21: 停推8月31 | OS21: BD18 | OT21: 2 | OU21: 35 | OV21: 1202 | OW21: 592 | OX21: 159471 | OY21: 276566 | OZ21: 153941 | PA21: 649015 | PB21: 551743 | PC21: 2101 | PD21: 1509 | PE21: 1389285 | PF21: 1106180 | PG21: =PE21-PF21 -> 283105 | PH21: 17780 | PI21: 205555.87 | PJ21: =PE21*5.5% -> 76410.675 | PK21: =PI21*20% -> 41111.174 | PL21: 228346 | PM21: =PG21-PJ21-PK21-PH21-PL21 -> -80542.849 | PN21: =OY21/OW21 -> 467.1723 | PO21: =PE21/PC21 -> 661.24941 | PP21: =OY21/(PH21+PJ21+PK21+PL21) -> 0.76053248 | PQ21: =PG21/(PJ21+PK21+PH21+PL21) -> 0.77851416 | PU21: BD18 | PV21: 2 | PW21: 43 | PX21: 1235 | PY21: 486 | PZ21: 140102 | QA21: 188082 | QB21: 115235 | QC21: 1858 | QD21: 1372 | QE21: 1142662 | QF21: 921204 | QG21: 221458 | QH21: 0 | QI21: 167607.57 | QJ21: =QE21*5.5% -> 62846.41 | QK21: =QI21*20% -> 33521.514 | QL21: =PV21*6613*QG1+1 -> 396781 | QM21: =QG21-QJ21-QK21 -> 125090.08 | QN21: =PZ21/PY21 -> 288.27572 | QO21: =QE21/QC21 -> 614.99569 | QP21: =QA21/(QH21+QJ21+QK21+QL21) -> 0.38138986 | QQ21: =QG21/(QJ21+QK21) -> 2.2980468 | QT21: 5-11玩家提款：24,699.68/ 5-31玩家提款：15,945.21 总提款：40,644.89 | QU21: BD18 | QV21: 3 | QW21: 1903 | QX21: 629 | QY21: 1184126 | QZ21: 790 | RA21: 1184126 | RB21: 941678 | RC21: =RB21-RE21 -> 933308 | RD21: =RA21-RB21 -> 242448 | RE21: 8370 | RF21: 169102.23 | RG21: =RA21*5.5% -> 65126.93 | RH21: =RF21*10% -> 16910.223 | RI21: =QV21*6613*31 -> 615009 | RJ21: =RD21-RG21-RH21 -> 160410.85 | RK21: =RA21/QZ21 -> 1498.8937 | RL21: =QY21/(RE21+RG21+RH21+RI21) -> 1.6786205 | RM21: =RD21/(RG21+RH21) -> 2.9553439 | RQ21: BD18 | RR21: 3 | RS21: 1167 | RT21: 400 | RU21: 788044 | RV21: 526 | RW21: 788044 | RX21: 659467 | RY21: =RW21-RX21 -> 128577 | RZ21: 22810 | SA21: 0 | SB21: 92752.45 | SC21: =RW21*5.5% -> 43342.42 | SD21: =SB21*10% -> 9275.245 | SE21: =RR21*6613*30 -> 595170 | SF21: =RY21-SC21-SD21-SE21 -> -519210.66 | SG21: =RW21/RV21 -> 1498.1825 | SH21: =RU21/(RZ21+SC21+SD21+SE21) -> 1.1751368 | SI21: =RY21/(SC21+SD21+SE21) -> 0.19848634 | SM21: BD18 | SN21: 3 | SO21: 1065 | SP21: 519 | SQ21: 1057925 | SR21: 695 | SS21: 1057925 | ST21: 902210 | SU21: =SS21-ST21 -> 155715 | SV21: 8540 | SW21: 0 | SX21: 115889.14 | SY21: =SS21*5.5% -> 58185.875 | SZ21: =SX21*10% -> 11588.914 | TA21: =SN21*8500*31 -> 790500 | TB21: =SU21-SY21-SZ21-TA21 -> -704559.79 | TC21: =SS21/SR21 -> 1522.1942 | TD21: =SQ21/(SV21+SY21+SZ21+TA21) -> 1.2176646 | TE21: =SU21/(SY21+SZ21+TA21) -> 0.18100612 | TH21: BD18 | TI21: 3 | TJ21: 2222 | TK21: 1409 | TL21: 1815705.9 | TM21: 1597 | TN21: 2008600.8 | TO21: 1825747 | TP21: =TN21-TO21 -> 182853.8 | TQ21: 253779.6 | TR21: 0 | TS21: 44448.22 | TT21: =TN21*4% -> 80344.032 | TU21: =TS21*10% -> 4444.822 | TV21: =TI21*8500*28 -> 714000 | TW21: =TP21-TT21-TU21-TV21 -> -615935.05 | TX21: =TN21/TM21 -> 1257.7338 | TY21: =TL21/(TQ21+TT21+TU21+TV21) -> 1.7250241 | TZ21: =TP21/(TT21+TU21+TV21) -> 0.22891381 | UD21: BD18 | UE21: 3 | UF21: 2173 | UG21: 1354 | UH21: 1554477 | UI21: 1421 | UJ21: 1561077 | UK21: 1770614 | UL21: =UJ21-UK21 -> -209537 | UM21: 352269.9 | UN21: 0 | UO21: -294037.43 | UP21: =UJ21*4% -> 62443.08 | UQ21: 0 | UR21: =UE21*8500*31 -> 790500 | US21: =UL21-UP21-UQ21-UR21 -> -1062480.1 | UT21: =UJ21/UI21 -> 1098.5764 | UU21: =UH21/(UM21+UP21+UQ21+UR21) -> 1.2897944 | UV21: =UL21/(UP21+UQ21+UR21) -> -0.24566352 | UZ21: BD18 | VA21: 3 | VB21: 416 | VC21: 210 | VD21: 222450 | VE21: 210 | VF21: 222450 | VG21: 261418 | VH21: =VF21-VG21 -> -38968 | VI21: 30330 | VJ21: 0 | VK21: -50619.51 | VL21: =VF21*5.5% -> 12234.75 | VM21: 0 | VN21: =VA21*8500*17 -> 433500 | VO21: =VH21-VL21-VM21-VN21 -> -484702.75 | VP21: =VF21/VE21 -> 1059.2857 | VQ21: =VD21/(VI21+VL21+VM21+VN21) -> 0.46726837 | VR21: =VH21/(VL21+VM21+VN21) -> -0.087424191 | VS21: 12月15-31
C22: BD07 | AJ22: BD07 | BQ22: BD07 | CR22: =CK22-CN22-CO22-CL22-CP22-CQ22 -> 0 | CV22: =CK22/(CN22+CO22+CL22+CP22+CQ22) -> #DIV/0! | CX22: BD07 | DY22: =DR22-DU22-DV22-DS22-DW22-DX22 -> 0 | EC22: =DR22/(DU22+DV22+DS22+DW22+DX22) -> #DIV/0! | EE22: BD07 | FF22: 0 | FJ22: #DIV/0! | FN22: BD07 | GS22: =GH22/(GK22+GL22+GI22+GM22+GN22) -> #DIV/0! | GV22: BD07 | HQ22: 0 | HU22: 3733 | HW22: =HP22-HS22-HT22-HQ22-HU22-HV22 -> -3733 | IA22: =HP22/(HS22+HT22+HQ22+HU22+HV22) -> 0 | ID22: BD07 | JL22: BD07 | KT22: BD07 | LR22: 0 | LU22: 0 | LX22: #DIV/0! | LY22: #DIV/0! | MB22: BD07 | MZ22: =MX22*20% -> 0 | NB22: =MV22-MY22-MZ22-MW22-NA22 -> 0 | NF22: =MJ22/(MY22+MZ22+MW22+NA22) -> #DIV/0! | NG22: =MV22/(MY22+MZ22+MW22+NA22) -> #DIV/0! | NH22: 停推8月28 | NJ22: BD07 | NK22: 1 | NM22: 27 | NO22: 658 | NP22: 236 | NQ22: 56089 | NR22: 82698 | NS22: 53075 | NT22: 257170 | NU22: 247036 | NW22: 174 | NX22: 60184 | NY22: 40807 | NZ22: 1960 | OA22: 1724 | OB22: 1300929 | OC22: 991882 | OD22: =OB22-OC22 -> 309047 | OE22: 32343 | OF22: 272264.58 | OG22: =OB22*5.5% -> 71551.095 | OH22: =OF22*20% -> 54452.916 | OI22: 114173 | OK22: =OD22-OG22-OH22-OE22-OI22 -> 36526.989 | OL22: =NR22/NP22 -> 350.41525 | OM22: =OB22/NZ22 -> 663.73929 | ON22: =NR22/(OG22+OH22+OE22+OI22) -> 0.30345661 | OO22: =OD22/(OG22+OH22+OE22+OI22) -> 1.1340342 | OP22: 停推8月31 | OS22: BD07 | OT22: 2 | OU22: 32 | OV22: 1320 | OW22: 524 | OX22: 142748 | OY22: 202847 | OZ22: 122935 | PA22: 507459 | PB22: 428530 | PC22: 2407 | PD22: 1883 | PE22: 1541337 | PF22: 1240416 | PG22: =PE22-PF22 -> 300921 | PH22: 43049 | PI22: 230722.45 | PJ22: =PE22*5.5% -> 84773.535 | PK22: =PI22*20% -> 46144.49 | PL22: 114173 | PM22: =PG22-PJ22-PK22-PH22-PL22 -> 12780.975 | PN22: =OY22/OW22 -> 387.1126 | PO22: =PE22/PC22 -> 640.35604 | PP22: =OY22/(PH22+PJ22+PK22+PL22) -> 0.70398758 | PQ22: =PG22/(PJ22+PK22+PH22+PL22) -> 1.0443568 | PU22: BD07 | PV22: 2 | PW22: 38 | PX22: 1400 | PY22: 517 | PZ22: 173672 | QA22: 257611 | QB22: 169780 | QC22: 2390 | QD22: 1873 | QE22: 1864008 | QF22: 1630716 | QG22: 233292 | QH22: 50879 | QI22: 142708.17 | QJ22: =QE22*5.5% -> 102520.44 | QK22: =QI22*20% -> 28541.634 | QL22: =PV22*6613*QG1+1 -> 396781 | QM22: =QG22-QJ22-QK22 -> 102229.93 | QN22: =PZ22/PY22 -> 335.92263 | QO22: =QE22/QC22 -> 779.91967 | QP22: =QA22/(QH22+QJ22+QK22+QL22) -> 0.44513768 | QQ22: =QG22/(QJ22+QK22) -> 1.7800115 | QT22: 5-01玩家提款：10,835.53 / 5-06玩家提款：41,653.71 / 5-10玩家提款：11,933.30 / 5-18玩家提款：27,199.84/ 5-28玩家提款：15,099.95 总提款：106,722.33 | QU22: BD07 | QV22: 3 | QW22: 2439 | QX22: 834 | QY22: 1585041 | QZ22: 972 | RA22: 2254208 | RB22: 1775889 | RC22: =RB22-RE22 -> 1711769 | RD22: =RA22-RB22 -> 478319 | RE22: 64120 | RF22: 335076.76 | RG22: =RA22*5.5% -> 123981.44 | RH22: =RF22*10% -> 33507.676 | RI22: =QV22*6613*31 -> 615009 | RJ22: =RD22-RG22-RH22 -> 320829.88 | RK22: =RA22/QZ22 -> 2319.144 | RL22: =QY22/(RE22+RG22+RH22+RI22) -> 1.8945813 | RM22: =RD22/(RG22+RH22) -> 3.0371559 | RQ22: BD07 | RR22: 3 | RS22: 1015 | RT22: 233 | RU22: 270885.23 | RV22: 319 | RW22: 446551.23 | RX22: 332661 | RY22: =RW22-RX22 -> 113890.23 | RZ22: 4190 | SA22: 0 | SB22: 79860.97 | SC22: =RW22*5.5% -> 24560.318 | SD22: =SB22*10% -> 7986.097 | SE22: =RR22*6613*30 -> 595170 | SF22: =RY22-SC22-SD22-SE22 -> -513826.18 | SG22: =RW22/RV22 -> 1399.8471 | SH22: =RU22/(RZ22+SC22+SD22+SE22) -> 0.42867935 | SI22: =RY22/(SC22+SD22+SE22) -> 0.1814358 | SM22: BD07 | SN22: 1 | SO22: 800 | SP22: 339 | SQ22: 349996 | SR22: 392 | SS22: 460396 | ST22: 534046 | SU22: =SS22-ST22 -> -73650 | SV22: 44340 | SW22: 0 | SX22: -90610.03 | SY22: =SS22*5.5% -> 25321.78 | SZ22: 0 | TA22: =SN22*8500*31 -> 263500 | TB22: =SU22-SY22-SZ22-TA22 -> -362471.78 | TC22: =SS22/SR22 -> 1174.4796 | TD22: =SQ22/(SV22+SY22+SZ22+TA22) -> 1.0505287 | TE22: =SU22/(SY22+SZ22+TA22) -> -0.25500154 | TH22: BD07 | TI22: 4 | TJ22: 1141 | TK22: 663 | TL22: 356202 | TM22: 706 | TN22: 423757 | TO22: 493230 | TP22: =TN22-TO22 -> -69473 | TQ22: 193170 | TR22: 0 | TS22: -84104.35 | TT22: =TN22*4% -> 16950.28 | TU22: 0 | TV22: =TI22*8500*28 -> 952000 | TW22: =TP22-TT22-TU22-TV22 -> -1038423.3 | TX22: =TN22/TM22 -> 600.22238 | TY22: =TL22/(TQ22+TT22+TU22+TV22) -> 0.30651044 | TZ22: =TP22/(TT22+TU22+TV22) -> -0.071699241 | UD22: BD07 | UE22: 4 | UF22: 596 | UG22: 296 | UH22: 265616 | UI22: 296 | UJ22: 265616 | UK22: 241758 | UL22: =UJ22-UK22 -> 23858 | UM22: 57200 | UN22: 0 | UO22: 12915.77 | UP22: =UJ22*4% -> 10624.64 | UQ22: =UO22*10% -> 1291.577 | UR22: =UE22*8500*18 -> 612000 | US22: =UL22-UP22-UQ22-UR22 -> -600058.22 | UT22: =UJ22/UI22 -> 897.35135 | UU22: =UH22/(UM22+UP22+UQ22+UR22) -> 0.38997163 | UV22: =UL22/(UP22+UQ22+UR22) -> 0.038239109 | UW22: 1月14-31 | UZ22: BD07 | VH22: =VF22-VG22 -> 0 | VL22: =VF22*5.5% -> 0 | VN22: =VA158456*0 -> 0 | VO22: =VH22-VL22-VM22-VN22 -> 0 | VP22: =VF22/VE22 -> #DIV/0! | VQ22: =VD22/(VI22+VL22+VM22+VN22) -> #DIV/0! | VR22: =VH22/(VL22+VM22+VN22) -> #DIV/0! | VS22: 未开始
C23: BD05 | O23: =M23-N23 -> 0 | W23: =U23-V23 -> 0 | Z23: =U23*5.5% -> 0 | AA23: =IF(Y23>0,Y23*20%,0) -> 0 | AB23: =(D23*6800)*S1 -> 0 | AC23: =(E23*3683)*S1 -> 0 | AD23: =W23-Z23-AA23-X23-AB23-AC23 -> 0 | AE23: =K23/I23 -> #DIV/0! | AF23: =U23/S23 -> #DIV/0! | AG23: =K23/(Z23+AA23+X23+AB23) -> #DIV/0! | AH23: =W23/(Z23+AA23+X23+AB23+AC23) -> #DIV/0! | AJ23: BD05 | AK23: 0 | AL23: 0 | AM23: 0 | AN23: =(AP23/AM23)/AZ1 -> #DIV/0! | AO23: 1445 | AP23: 668 | AQ23: 230944 | AR23: 340895 | AS23: 279093.68 | AT23: 963093 | AU23: 882768.72 | AV23: =AT23-AU23 -> 80324.28 | AW23: 274839 | AX23: 274839 | AY23: 209486.92 | AZ23: 3625 | BA23: 2957 | BB23: 2976104 | BC23: 2767258.4 | BD23: =BB23-BC23 -> 208845.61 | BE23: 40466 | BF23: 150003.17 | BG23: =BB23*5.5% -> 163685.72 | BH23: =IF(BF23>0,BF23*20%,0) -> 30000.634 | BI23: =(AK23*6800)*AZ1 -> 0 | BJ23: =(AL23*3683)*AZ1 -> 0 | BK23: =BD23-BG23-BH23-BE23-BI23-BJ23 -> -25306.744 | BL23: =AR23/AP23 -> 510.32186 | BM23: =BB23/AZ23 -> 820.99421 | BN23: =AR23/(BG23+BH23+BE23+BI23) -> 1.4558683 | BO23: =BD23/(BG23+BH23+BE23+BI23+BJ23) -> 0.89192189 | BP23: 停推 | BQ23: BD05 | BR23: 1 | BS23: 1 | BT23: 24 | BU23: 0.48655914 | BV23: 925 | BW23: 362 | BX23: 110684 | BY23: 206978 | BZ23: 155129 | CA23: 1651024 | CB23: 1814278.7 | CC23: -163254.72 | CD23: 306 | CE23: 182121 | CF23: 145183 | CG23: 3084 | CH23: 2722 | CI23: 4408310 | CJ23: 4408585 | CK23: =CI23-CJ23 -> -275 | CL23: 25684 | CM23: -69749.06 | CN23: =CI23*5.5% -> 242457.05 | CO23: =IF(CM23>0,CM23*20%,0) -> 0 | CP23: ='[1]BD05'!$B$4 -> 0 | CQ23: ='[1]BD05'!$C$4 -> 0 | CR23: =CK23-CN23-CO23-CL23-CP23-CQ23 -> -268416.05 | CS23: =BY23/BW23 -> 571.76243 | CT23: =CI23/CG23 -> 1429.4131 | CU23: =BY23/(CN23+CO23+CL23+CP23) -> 0.77189971 | CV23: =CK23/(CN23+CO23+CL23+CP23+CQ23) -> -0.0010255796 | CX23: BD05 | CY23: 1 | CZ23: 1 | DA23: 13 | DB23: 0.93589744 | DC23: 900 | DD23: 365 | DE23: 95026 | DF23: 150769 | DG23: 127949 | DH23: 488508 | DI23: 483413 | DJ23: =DH23-DI23 -> 5095 | DK23: 280 | DL23: 122424 | DM23: 99863 | DN23: 2780 | DO23: 2415 | DP23: 2436190 | DQ23: 2055680 | DR23: =DP23-DQ23 -> 380510 | DS23: 13498 | DT23: 338469.46 | DU23: =DP23*5.5% -> 133990.45 | DV23: =IF(DT23>0,DT23*20%,0) -> 67693.892 | DW23: ='[1]BD05'!$B$4 -> 0 | DX23: ='[1]BD05'!$C$4 -> 0 | DY23: =DR23-DU23-DV23-DS23-DW23-DX23 -> 165327.66 | DZ23: =DF23/DD23 -> 413.06575 | EA23: =DP23/DN23 -> 876.32734 | EB23: =DF23/(DU23+DV23+DS23+DW23) -> 0.70065693 | EC23: =DR23/(DU23+DV23+DS23+DW23+DX23) -> 1.7683142 | EE23: BD05 | EF23: 1 | EG23: 1 | EH23: 45 | EI23: 0.48960573 | EJ23: 2008 | EK23: 683 | EL23: 178445 | EM23: 262630 | EN23: 225118 | EO23: 868193 | EP23: 900650.58 | EQ23: -32457.58 | ER23: 531 | ES23: 209032 | ET23: 153096 | EU23: 3893 | EV23: 3210 | EW23: 3243027 | EX23: 3263870 | EY23: -20843 | EZ23: 63924 | FA23: -156325.71 | FB23: 178366.48 | FC23: 0 | FD23: 245923 | FE23: 114173 | FF23: -623229.48 | FG23: 384.52416 | FH23: 833.04059 | FI23: 0.5379409 | FJ23: -0.03460071 | FN23: BD05 | FO23: 1 | FP23: 1 | FQ23: 82 | FR23: =(FT23/FQ23)/GF1 -> 0.20513937 | FS23: 1674 | FT23: 471 | FU23: 126395 | FV23: 188394 | FW23: 123945.22 | FX23: 2446648 | FY23: 2569776.1 | FZ23: =FX23-FY23 -> -123128.07 | GA23: 333 | GB23: 126189 | GC23: 79452 | GD23: 2858 | GE23: 2387 | GF23: 4642670 | GG23: 4400787.1 | GH23: 241882.93 | GI23: 39496.56 | GJ23: 168011.52 | GK23: 255346.85 | GL23: 33602.304 | GM23: 222124 | GN23: 103124 | GO23: -411810.78 | GP23: 399.98726 | GQ23: 1624.4472 | GR23: =FV23/(GK23+GL23+GI23+GM23) -> 0.3421801 | GS23: =GH23/(GK23+GL23+GI23+GM23+GN23) -> 0.37002487 | GV23: BD05 | GW23: 2 | GX23: 0 | GY23: 23 | GZ23: =(HB23/GY23)/HL1 -> 0.80364656 | HA23: 1941 | HB23: 573 | HC23: 180863 | HD23: 369220 | HE23: 199807 | HF23: 2648823 | HG23: 2715976 | HH23: =HF23-HG23 -> -67153 | HI23: 426 | HJ23: 298492 | HK23: 142719 | HL23: 3913 | HM23: 3340 | HN23: 4519987 | HO23: 4386717.8 | HP23: 133269.24 | HQ23: 23167 | HR23: 1056.11 | HS23: 248599.29 | HT23: 4574.782 | HU23: =(GW23*6800)*31 -> 421600 | HV23: 0 | HW23: -619051.83 | HX23: 644.363 | HY23: 1155.1206 | HZ23: =HD23/(HS23+HT23+HQ23+HU23) -> 0.52901315 | IA23: =HP23/(HS23+HT23+HQ23+HU23+HV23) -> 0.19094627 | ID23: BD05 | IE23: 2 | IF23: 0 | IG23: 85 | IH23: =(IJ23/IG23)/IT1 -> 0.17001898 | II23: 1745 | IJ23: 448 | IK23: 122642 | IL23: 182247 | IM23: 150090 | IN23: 627303 | IO23: 535296.21 | IP23: =IN23-IO23 -> 92006.79 | IQ23: 351 | IR23: 145201 | IS23: 102919 | IT23: 2618 | IU23: 2170 | IV23: 1868172 | IW23: 1624309 | IX23: =IV23-IW23 -> 243863 | IY23: 10000 | IZ23: 164235.91 | JA23: =IV23*5.5% -> 102749.46 | JB23: =IZ23*20% -> 32847.182 | JC23: 228346 | JD23: 0 | JE23: =IX23-JA23-JB23-IY23-JC23 -> -130079.64 | JF23: =IL23/IJ23 -> 406.80134 | JG23: =IV23/IT23 -> 713.58747 | JH23: =IL23/(JA23+JB23+IY23+JC23) -> 0.48736619 | JI23: =IX23/(JA23+JB23+IY23+JC23) -> 0.65214012 | JL23: BD05 | JM23: 2 | JN23: 89 | JQ23: 762 | JR23: 270 | JS23: 69707 | JT23: 97607 | JU23: 61509 | JV23: 260397 | JW23: 197278 | JY23: 196 | JZ23: 74193 | KA23: 42758 | KB23: 2205 | KC23: 1935 | KD23: 2046240 | KE23: 1711450 | KF23: =KD23-KE23 -> 334790 | KG23: 9000 | KH23: 245180.44 | KI23: =KD23*5.5% -> 112543.2 | KJ23: =KH23*20% -> 49036.088 | KK23: 220980 | KM23: =KF23-KI23-KJ23-KG23-KK23 -> -56769.288 | KN23: =JT23/JR23 -> 361.50741 | KO23: =KD23/KB23 -> 928 | KP23: =JT23/(KI23+KJ23+KG23+KK23) -> 0.2492777 | KQ23: =KF23/(KI23+KJ23+KG23+KK23) -> 0.85501739 | KT23: BD05 | KU23: 3 | KW23: 257 | KY23: 1793 | KZ23: 531 | LA23: 131154 | LB23: 243725 | LC23: 133406 | LD23: 968786 | LE23: 726530 | LG23: 372 | LH23: 141314 | LI23: 105508 | LJ23: 2602 | LK23: 2071 | LL23: 2443310 | LM23: 1656845 | LN23: 786465 | LO23: 12999.82 | LP23: 671602.63 | LQ23: 134382.05 | LR23: 134320.53 | LS23: 342519 | LU23: 162243.6 | LV23: 458.99247 | LW23: 939.0123 | LX23: 0.39044641 | LY23: 1.2599136 | MB23: BD05 | MC23: 4 | ME23: 180 | MG23: 1185 | MH23: 409 | MI23: 100522 | MJ23: 168176 | MK23: 93070 | ML23: 522209 | MM23: 394850 | MO23: 293 | MP23: 118579 | MQ23: 69891 | MR23: 1992 | MS23: 1583 | MT23: 1835327 | MU23: 1431134 | MV23: =MT23-MU23 -> 404193 | MW23: 12000 | MX23: 301861.04 | MY23: =MT23*5.5% -> 100942.99 | MZ23: =MX23*20% -> 60372.208 | NA23: 552450 | NB23: =MV23-MY23-MZ23-MW23-NA23 -> -321572.19 | ND23: =MJ23/MH23 -> 411.18826 | NE23: =MT23/MR23 -> 921.3489 | NF23: =MJ23/(MY23+MZ23+MW23+NA23) -> 0.23172233 | NG23: =MV23/(MY23+MZ23+MW23+NA23) -> 0.55691979 | NJ23: BD05 | NK23: 1 | NM23: 102 | NO23: 681 | NP23: 252 | NQ23: 68562 | NR23: 95157 | NS23: 51385 | NT23: 293371 | NU23: 204195 | NW23: 180 | NX23: 68567 | NY23: 28999 | NZ23: 1757 | OA23: 1505 | OB23: 2268695 | OC23: 1565153 | OD23: =OB23-OC23 -> 703542 | OE23: 1000 | OF23: 605071.93 | OG23: =OB23*5.5% -> 124778.23 | OH23: =OF23*20% -> 121014.39 | OI23: 114173 | OK23: =OD23-OG23-OH23-OE23-OI23 -> 342576.39 | OL23: =NR23/NP23 -> 377.60714 | OM23: =OB23/NZ23 -> 1291.2322 | ON23: =NR23/(OG23+OH23+OE23+OI23) -> 0.26361791 | OO23: =OD23/(OG23+OH23+OE23+OI23) -> 1.9490555 | OS23: BD05 | OT23: 1 | OU23: 10 | OV23: 600 | OW23: 233 | OX23: 68777 | OY23: 91546 | OZ23: 51987 | PA23: 240305 | PB23: 209613 | PC23: 1481 | PD23: 1248 | PE23: 2029234 | PF23: 1454137 | PG23: =PE23-PF23 -> 575097 | PH23: 5150 | PI23: 439005.98 | PJ23: =PE23*5.5% -> 111607.87 | PK23: =PI23*20% -> 87801.196 | PL23: 114173 | PM23: =PG23-PJ23-PK23-PH23-PL23 -> 256364.93 | PN23: =OY23/OW23 -> 392.90129 | PO23: =PE23/PC23 -> 1370.1783 | PP23: =OY23/(PH23+PJ23+PK23+PL23) -> 0.2872193 | PQ23: =PG23/(PJ23+PK23+PH23+PL23) -> 1.8043274 | PU23: BD05 | PV23: 1 | PW23: 10 | PX23: 507 | PY23: 160 | PZ23: 49754 | QA23: 69375 | QB23: 44035 | QC23: 1222 | QD23: 1062 | QE23: 1993609 | QF23: 1684639 | QG23: 308970 | QH23: 5220 | QI23: 234665.46 | QJ23: =QE23*5.5% -> 109648.49 | QK23: =QI23*20% -> 46933.092 | QL23: =PV23*6613*QG1+1 -> 198391 | QM23: =QG23-QJ23-QK23 -> 152388.41 | QN23: =PZ23/PY23 -> 310.9625 | QO23: =QE23/QC23 -> 1631.4313 | QP23: =QA23/(QH23+QJ23+QK23+QL23) -> 0.1926053 | QQ23: =QG23/(QJ23+QK23) -> 1.9732205 | QT23: 5-07玩家提款：113,603.11 / 5-14玩家提款：79,966.38/ 5-24玩家提款：50,135.13/ 5-28玩家提款：63,400.58/ 5-30玩家提款：12,319.82 总提款：319,425.02 | QU23: BD05 | QV23: 2 | QW23: 639 | QX23: 153 | QY23: 229932 | QZ23: 314 | RA23: 2447441 | RB23: 1496904 | RC23: =RB23-RE23 -> 1494034 | RD23: =RA23-RB23 -> 950537 | RE23: 2870 | RF23: 884268.24 | RG23: =RA23*5.5% -> 134609.26 | RH23: =RF23*10% -> 88426.824 | RI23: =QV23*6613*31 -> 410006 | RJ23: =RD23-RG23-RH23 -> 727500.92 | RK23: =RA23/QZ23 -> 7794.3981 | RL23: =QY23/(RE23+RG23+RH23+RI23) -> 0.36157829 | RM23: =RD23/(RG23+RH23) -> 4.2618082 | RQ23: BD05 | RR23: 2 | RS23: 501 | RT23: 137 | RU23: 266112 | RV23: 332 | RW23: 2006167 | RX23: 2411047 | RY23: =RW23-RX23 -> -404880 | RZ23: 8000 | SA23: 0 | SB23: -427839.52 | SC23: =RW23*5.5% -> 110339.18 | SD23: 0 | SE23: =RR23*6613*30 -> 396780 | SF23: =RY23-SC23-SD23-SE23 -> -911999.19 | SG23: =RW23/RV23 -> 6042.6717 | SH23: =RU23/(RZ23+SC23+SD23+SE23) -> 0.51660277 | SI23: =RY23/(SC23+SD23+SE23) -> -0.7983922 | SJ23: 4月9开始 | SM23: BD05 | SN23: 2 | SO23: 650 | SP23: 190 | SQ23: 492332 | SR23: 427 | SS23: 1539947 | ST23: 1285767 | SU23: =SS23-ST23 -> 254180 | SV23: 77750 | SW23: 0 | SX23: 246905.52 | SY23: =SS23*5.5% -> 84697.085 | SZ23: =SX23*10% -> 24690.552 | TA23: =SN23*4000*31 -> 248000 | TB23: =SU23-SY23-SZ23-TA23 -> -103207.64 | TC23: =SS23/SR23 -> 3606.4333 | TD23: =SQ23/(SV23+SY23+SZ23+TA23) -> 1.1314397 | TE23: =SU23/(SY23+SZ23+TA23) -> 0.71121654 | TH23: BD05 | TI23: 4 | TJ23: 645 | TK23: 214 | TL23: 364269 | TM23: 431 | TN23: 1435252 | TO23: 1172144 | TP23: =TN23-TO23 -> 263108 | TQ23: 0 | TR23: 0 | TS23: 255303.01 | TT23: =TN23*4% -> 57410.08 | TU23: =TS23*10% -> 25530.301 | TV23: =TI23*8500*28 -> 952000 | TW23: =TP23-TT23-TU23-TV23 -> -771832.38 | TX23: =TN23/TM23 -> 3330.051 | TY23: =TL23/(TQ23+TT23+TU23+TV23) -> 0.351971 | TZ23: =TP23/(TT23+TU23+TV23) -> 0.25422527 | UD23: BD05 | UE23: 4 | UF23: 844 | UG23: 394 | UH23: 744389 | UI23: 640 | UJ23: 1771483 | UK23: 1450409 | UL23: =UJ23-UK23 -> 321074 | UM23: 52000 | UN23: 0 | UO23: 321859.18 | UP23: =UJ23*4% -> 70859.32 | UQ23: =UO23*10% -> 32185.918 | UR23: =UE23*8500*31 -> 1054000 | US23: =UL23-UP23-UQ23-UR23 -> -835971.24 | UT23: =UJ23/UI23 -> 2767.9422 | UU23: =UH23/(UM23+UP23+UQ23+UR23) -> 0.61568333 | UV23: =UL23/(UP23+UQ23+UR23) -> 0.27749477 | UZ23: BD05 | VA23: 4 | VB23: 605 | VC23: 163 | VD23: 697753 | VE23: 689 | VF23: 1361711 | VG23: 1322466 | VH23: =VF23-VG23 -> 39245 | VI23: 33940 | VJ23: 0 | VK23: 31056.82 | VL23: =VF23*5.5% -> 74894.105 | VM23: =VK23*10% -> 3105.682 | VN23: =VA23*8500*31 -> 1054000 | VO23: =VH23-VL23-VM23-VN23 -> -1092754.8 | VP23: =VF23/VE23 -> 1976.3585 | VQ23: =VD23/(VI23+VL23+VM23+VN23) -> 0.59844686 | VR23: =VH23/(VL23+VM23+VN23) -> 0.034668734
C24: BD16 | AJ24: BD16 | BO24: =BD24/(BG24+BH24) -> #DIV/0! | BQ24: BD16 | CV24: =CK24/(CN24+CO24) -> #DIV/0! | CX24: BD16 | EC24: =DR24/(DU24+DV24) -> #DIV/0! | EE24: BD16 | FJ24: #DIV/0! | FN24: BD16 | GS24: =GH24/(GK24+GL24) -> #DIV/0! | GV24: BD16 | IA24: =HP24/(HS24+HT24) -> #DIV/0! | ID24: BD16 | JI24: =IX24/(JA24+JB24) -> #DIV/0! | JL24: BD16 | KQ24: =KF24/(KI24+KJ24) -> #DIV/0! | KT24: BD16 | LY24: #DIV/0! | MB24: BD16 | NG24: =MV24/(MY24+MZ24) -> #DIV/0! | NJ24: BD16 | OG24: =OB24*5.5% -> 0 | OH24: =OF24*10% -> 0 | OI24: =NK24*6613*31 -> 0 | OO24: =OD24/(OG24+OH24) -> #DIV/0! | OS24: BD16 | PJ24: =PE24*5.5% -> 0 | PK24: =PI24*10% -> 0 | PL24: =OT24*6613*31 -> 0 | PM24: =#REF!-PJ24-PK24-PL24 -> #REF! | PQ24: =PG24/(PJ24+PK24) -> #DIV/0! | PR24: 塔卡 | PU24: BD16 | PV24: 0 | QJ24: =QE24*5.5% -> 0 | QK24: =QI24*10% -> 0 | QL24: =PV24*6613*31 -> 0 | QM24: =QG24-QJ24-QK24-QL24 -> 0 | QQ24: =QG24/(QJ24+QK24) -> #DIV/0! | QT24: 5-03大客提款：42,013 / 5-12大客提款：21,074.30 / 5-15大客提款：29,978.90 / 5-16大客提款：20,135.27/ 5-28大客提款：43,459.27/ 5-30大客提款：12,026.50 + 13,007.63 总提款：181,694.87 | QU24: BD16 | QV24: 1 | QZ24: 976 | RA24: 1017955 | RB24: 867099 | RC24: =RB24-RE24 -> 867099 | RD24: =RA24-RB24 -> 150856 | RF24: 139370.36 | RG24: =RA24*5.5% -> 55987.525 | RH24: =RF24*10% -> 13937.036 | RI24: =QV24*6613*31 -> 205003 | RJ24: =RD24-RG24-RH24 -> 80931.439 | RM24: =RD24/(RG24+RH24) -> 2.1574108 | RN24: 塔卡 | RQ24: BD16 | RR24: 2 | RV24: 273 | RW24: 1040175 | RX24: 749818 | RY24: =RW24-RX24 -> 290357 | SA24: 0 | SB24: 291754.67 | SC24: =RW24*5.5% -> 57209.625 | SD24: =SB24*10% -> 29175.467 | SE24: =RR24*6613*30 -> 396780 | SF24: =RY24-SC24-SD24-SE24 -> -192808.09 | SI24: =RY24/(SC24+SD24+SE24) -> 0.6009478 | SJ24: 塔卡 | SK24: 4月9开始 | SM24: BD16 | SU24: =SS24-ST24 -> 0 | SY24: =SS24*5.5% -> 0 | SZ24: =SX24*10% -> 0 | TA24: =SN24*4000*31 -> 0 | TB24: =SU24-SY24-SZ24-TA24 -> 0 | TE24: =SU24/(SY24+SZ24+TA24) -> #DIV/0! | TH24: BD16 | TP24: =TN24-TO24 -> 0 | TT24: =TN24*4% -> 0 | TU24: =TS24*10% -> 0 | TV24: =TI24*8500*28 -> 0 | TW24: =TP24-TT24-TU24-TV24 -> 0 | TZ24: =TP24/(TT24+TU24+TV24) -> #DIV/0! | UD24: BD16 | UZ24: BD16 | VR24: =VH24/(VL24+VM24+VN24+VJ24) -> #DIV/0!
NJ25: BD01 | OG25: =OB25*5.5% -> 0 | OH25: =OF25*10% -> 0 | OI25: =NK25*6613*0 -> 0 | OO25: =OD25/(OG25+OH25) -> #DIV/0! | OS25: BD01 | PJ25: =PE25*5.5% -> 0 | PK25: =PI25*10% -> 0 | PL25: =OT25*6613*0 -> 0 | PM25: =#REF!-PJ25-PK25-PL25 -> #REF! | PQ25: =PG25/(PJ25+PK25) -> #DIV/0! | PU25: BD01 | PV25: 0 | QJ25: =QE25*5.5% -> 0 | QK25: =QI25*10% -> 0 | QL25: =PV25*6613*0 -> 0 | QM25: =QG25-QJ25-QK25-QL25 -> 0 | QQ25: =QG25/(QJ25+QK25) -> #DIV/0! | QU25: BD01 | RC25: =RB25-RE25 -> 0 | RD25: =RA25-RB25 -> 0 | RG25: =RA25*5.5% -> 0 | RH25: =RF25*10% -> 0 | RI25: =QV25*6613*0 -> 0 | RJ25: =RD25-RG25-RH25 -> 0 | RM25: =RD25/(RG25+RH25) -> #DIV/0! | RQ25: BD01 | RY25: =RW25-RX25 -> 0 | SA25: 0 | SC25: =RW25*5.5% -> 0 | SD25: =SB25*10% -> 0 | SE25: =RR25*6613*0 -> 0 | SF25: =RY25-SC25-SD25-SE25 -> 0 | SI25: =RY25/(SC25+SD25+SE25) -> #DIV/0! | SL25: 停推 | SM25: BD01 | SN25: 0 | SS25: 757390 | ST25: 742233 | SU25: =SS25-ST25 -> 15157 | SW25: 0 | SX25: -21191.97 | SY25: =SS25*5.5% -> 41656.45 | SZ25: 0 | TA25: =SN25*8500*31 -> 0 | TB25: =SU25-SY25-SZ25-TA25 -> -26499.45 | TE25: =SU25/(SY25+SZ25+TA25) -> 0.36385722 | TF25: 塔卡 | TH25: BD01 | TI25: 4 | TN25: 836735 | TO25: 817328 | TP25: =TN25-TO25 -> 19407 | TQ25: 155050 | TR25: 0 | TS25: -42347.99 | TT25: =TN25*4% -> 33469.4 | TU25: 0 | TV25: =TI25*8500*28 -> 952000 | TW25: =TP25-TT25-TU25-TV25 -> -966062.4 | TZ25: =TP25/(TT25+TU25+TV25) -> 0.019693153 | UA25: 塔卡 | UD25: BD01 | UE25: 4 | UJ25: 601045 | UK25: 784560 | UL25: =UJ25-UK25 -> -183515 | UM25: 209380 | UN25: 0 | UO25: 236352.75 | UP25: =UJ25*4% -> 24041.8 | UQ25: =UO25*10% -> 23635.275 | UR25: =UE25*8500*31 -> 1054000 | US25: =UL25-UP25-UQ25-UR25 -> -1285192.1 | UV25: =UL25/(UP25+UQ25+UR25) -> -0.16657785 | UW25: 塔卡 | UZ25: BD01 | VA25: 4 | VF25: 146931 | VG25: 200247 | VH25: =VF25-VG25 -> -53316 | VI25: 54830 | VJ25: 0 | VK25: -57543.47 | VL25: =VF25*4% -> 5877.24 | VM25: 0 | VN25: =VA25*8500*20 -> 680000 | VO25: =VK25-VM25 -> -57543.47 | VR25: =VH25/(VL25+VM25+VN25+VJ25) -> -0.077734027 | VS25: 12月12-31
C26: 总 | D26: =SUM(D19:D23) -> 0 | E26: =SUM(E19:E23) -> 0 | F26: =SUM(F19:F23) -> 0 | G26: =(I26/F26)/S1 -> #DIV/0! | H26: =SUM(H19:H23) -> 0 | I26: =SUM(I19:I23) -> 0 | J26: =SUM(J19:J23) -> 0 | K26: =SUM(K19:K23) -> 0 | L26: =SUM(L19:L23) -> 0 | M26: =SUM(M19:M23) -> 0 | N26: =SUM(N19:N23) -> 0 | O26: =M26-N26 -> 0 | P26: =SUM(P19:P23) -> 0 | Q26: =SUM(Q19:Q23) -> 0 | R26: =SUM(R19:R23) -> 0 | S26: =SUM(S19:S23) -> 0 | T26: =SUM(T19:T23) -> 0 | U26: =SUM(U19:U23) -> 0 | V26: =SUM(V19:V23) -> 0 | W26: =SUM(W19:W23) -> 0 | ... Y26: =SUM(Y19:Y23) -> 0 | Z26: =U26*5.5% -> 0 | AA26: =IF(Y26>0,Y26*20%,0) -> 0 | AB26: =SUM(AB19:AB23) -> 0 | AC26: =SUM(AC19:AC23) -> 0 | AD26: =W26-X26-Z26-AA26-AB26-AC26 -> 0 | AE26: =K26/I26 -> #DIV/0! | AF26: =U26/S26 -> #DIV/0! | AG26: =K26/(Z26+AA26+X26+AB26) -> #DIV/0! | AH26: =W26/(Z26+AA26+X26+AB26+AC26) -> #DIV/0! | AJ26: 总 | AK26: =SUM(AK19:AK23) -> 0 | AL26: =SUM(AL19:AL23) -> 0 | AM26: =SUM(AM19:AM23) -> 0 | AN26: =(AP26/AM26)/AZ1 -> #DIV/0! | AO26: =SUM(AO19:AO23) -> 1445 | AP26: =SUM(AP19:AP23) -> 668 | AQ26: =SUM(AQ19:AQ23) -> 230944 | AR26: =SUM(AR19:AR23) -> 340895 | AS26: =SUM(AS19:AS23) -> 279093.68 | AT26: =SUM(AT19:AT23) -> 963093 | AU26: =SUM(AU19:AU23) -> 882768.72 | AV26: =AT26-AU26 -> 80324.28 | AW26: =SUM(AW19:AW23) -> 274839 | AX26: =SUM(AX19:AX23) -> 274839 | AY26: =SUM(AY19:AY23) -> 209486.92 | AZ26: =SUM(AZ19:AZ23) -> 3625 | BA26: =SUM(BA19:BA23) -> 2957 | BB26: =SUM(BB19:BB23) -> 2976104 | BC26: =SUM(BC19:BC23) -> 2767258.4 | BD26: =SUM(BD19:BD23) -> 208845.61 | ... BF26: =SUM(BF19:BF23) -> 150003.17 | BG26: =BB26*5.5% -> 163685.72 | BH26: =IF(BF26>0,BF26*20%,0) -> 30000.634 | BI26: =SUM(BI19:BI23) -> 0 | BJ26: =SUM(BJ19:BJ23) -> 0 | BK26: =BD26-BE26-BG26-BH26-BI26-BJ26 -> -25306.744 | BL26: =AR26/AP26 -> 510.32186 | BM26: =BB26/AZ26 -> 820.99421 | BN26: =AR26/(BG26+BH26+BE26+BI26) -> 1.4558683 | BO26: =BD26/(BG26+BH26+BE26+BI26+BJ26) -> 0.89192189 | BQ26: 总 | BR26: =SUM(BR19:BR23) -> 3 | BS26: =SUM(BS19:BS23) -> 1 | BT26: =SUM(BT19:BT23) -> 38 | BU26: =(BW26/BT26)/CI1 -> 0.53820034 | BV26: =SUM(BV19:BV23) -> 1586 | BW26: =SUM(BW19:BW23) -> 634 | BX26: =SUM(BX19:BX23) -> 167547 | BY26: =SUM(BY19:BY23) -> 300120 | BZ26: =SUM(BZ19:BZ23) -> 254319 | CA26: =SUM(CA19:CA23) -> 1906420 | CB26: =SUM(CB19:CB23) -> 2069556.7 | CC26: =CA26-CB26 -> -163136.72 | CD26: =SUM(CD19:CD23) -> 515 | CE26: =SUM(CE19:CE23) -> 256100 | CF26: =SUM(CF19:CF23) -> 217571 | CG26: =SUM(CG19:CG23) -> 4981 | CH26: =SUM(CH19:CH23) -> 4295 | CI26: =SUM(CI19:CI23) -> 6861620 | CJ26: =SUM(CJ19:CJ23) -> 6724433 | CK26: =SUM(CK19:CK23) -> 137187 | ... CM26: =SUM(CM19:CM23) -> -4655.47 | CN26: =CI26*5.5% -> 377389.1 | CO26: =IF(CM26>0,CM26*20%,0) -> 0 | CP26: =SUM(CP19:CP23) -> 0 | CQ26: =SUM(CQ19:CQ23) -> 0 | CR26: =CK26-CL26-CN26-CO26-CP26-CQ26 -> -270718.1 | CS26: =BY26/BW26 -> 473.37539 | CT26: =CI26/CG26 -> 1377.5587 | CU26: =BY26/(CN26+CO26+CL26+CP26) -> 0.73575937 | CV26: =CK26/(CN26+CO26+CL26+CP26+CQ26) -> 0.33632087 | CX26: 总 | CY26: =SUM(CY19:CY23) -> 3 | CZ26: =SUM(CZ19:CZ23) -> 1 | DA26: =SUM(DA19:DA23) -> 32 | DB26: =(DD26/DA26)/DP1 -> 0.57708333 | DC26: =SUM(DC19:DC23) -> 1528 | DD26: =SUM(DD19:DD23) -> 554 | DE26: =SUM(DE19:DE23) -> 146262 | DF26: =SUM(DF19:DF23) -> 225174 | DG26: =SUM(DG19:DG23) -> 184102 | DH26: =SUM(DH19:DH23) -> 898576 | DI26: =SUM(DI19:DI23) -> 876135 | DJ26: =DH26-DI26 -> 22441 | DK26: =SUM(DK19:DK23) -> 420 | DL26: =SUM(DL19:DL23) -> 179984 | DM26: =SUM(DM19:DM23) -> 144373 | DN26: =SUM(DN19:DN23) -> 4339 | DO26: =SUM(DO19:DO23) -> 3785 | DP26: =SUM(DP19:DP23) -> 4437556 | DQ26: =SUM(DQ19:DQ23) -> 3887440 | DR26: =SUM(DR19:DR23) -> 550116 | ... DT26: =SUM(DT19:DT23) -> 518985.9 | DU26: =DP26*5.5% -> 244065.58 | DV26: =IF(DT26>0,DT26*20%,0) -> 103797.18 | DW26: =SUM(DW19:DW23) -> 0 | DX26: =SUM(DX19:DX23) -> 0 | DY26: =DR26-DS26-DU26-DV26-DW26-DX26 -> 185589.24 | DZ26: =DF26/DD26 -> 406.45126 | EA26: =DP26/DN26 -> 1022.714 | EB26: =DF26/(DU26+DV26+DS26+DW26) -> 0.61771597 | EC26: =DR26/(DU26+DV26+DS26+DW26+DX26) -> 1.5091238 | EE26: 总 | EF26: =SUM(EF19:EF23) -> 2 | EG26: =SUM(EG19:EG23) -> 1 | EH26: =SUM(EH19:EH23) -> 57 | EI26: =(EK26/EH26)/EW1 -> 0.54612337 | EJ26: =SUM(EJ19:EJ23) -> 2644 | EK26: =SUM(EK19:EK23) -> 965 | EL26: =SUM(EL19:EL23) -> 240237 | EM26: =SUM(EM19:EM23) -> 368902 | EN26: =SUM(EN19:EN23) -> 294009 | EO26: 32 | EP26: =SUM(EP19:EP23) -> 3492956.6 | EQ26: =EO26-EP26 -> -3492924.6 | ER26: =SUM(ER19:ER23) -> 736 | ES26: =SUM(ES19:ES23) -> 291567 | ET26: =SUM(ET19:ET23) -> 206887 | EU26: =SUM(EU19:EU23) -> 5772 | EV26: =SUM(EV19:EV23) -> 4807 | EW26: =SUM(EW19:EW23) -> 7048658 | EX26: =SUM(EX19:EX23) -> 7291791 | EY26: =SUM(EY19:EY23) -> -243133 | ... FA26: =SUM(FA19:FA23) -> -482689.93 | FB26: =EW26*5.5% -> 387676.19 | FC26: =IF(FA26>0,FA26*20%,0) -> 0 | FD26: =SUM(FD19:FD23) -> 491846 | FE26: =SUM(FE19:FE23) -> 114173 | FF26: =EY26-EZ26-FB26-FC26-FD26-FE26 -> -1310750.2 | FG26: =EM26/EK26 -> 382.28187 | FH26: =EW26/EU26 -> 1221.1812 | FI26: =EM26/(FB26+FC26+EZ26+FD26) -> 0.38691515 | FJ26: =EY26/(FB26+FC26+EZ26+FD26+FE26) -> -0.22773425 | FN26: 总 | FO26: =SUM(FO19:FO23) -> 2 | FP26: =SUM(FP19:FP23) -> 1 | FQ26: =SUM(FQ19:FQ23) -> 95 | FR26: =(FT26/FQ26)/GF1 -> 0.26353383 | FS26: =SUM(FS19:FS23) -> 2231 | FT26: =SUM(FT19:FT23) -> 701 | FU26: =SUM(FU19:FU23) -> 178217 | FV26: =SUM(FV19:FV23) -> 272165 | FW26: =SUM(FW19:FW23) -> 186981.22 | FX26: =SUM(FX19:FX23) -> 4712311 | FY26: =SUM(FY19:FY23) -> 4984067.1 | FZ26: =FX26-FY26 -> -271756.14 | GA26: =SUM(GA19:GA23) -> 499 | GB26: =SUM(GB19:GB23) -> 184814 | GC26: =SUM(GC19:GC23) -> 127155 | GD26: =SUM(GD19:GD23) -> 4407 | GE26: =SUM(GE19:GE23) -> 3706 | GF26: =SUM(GF19:GF23) -> 8040757 | GG26: =SUM(GG19:GG23) -> 7686914.1 | GH26: =SUM(GH19:GH23) -> 353842.86 | ... GJ26: =SUM(GJ19:GJ23) -> 287003.36 | GK26: =GF26*5.5% -> 442241.64 | GL26: =GJ26*20% -> 57400.672 | GM26: =SUM(GM19:GM23) -> 444248 | GN26: =SUM(GN19:GN23) -> 103124 | GO26: =GH26-GI26-GK26-GL26-GM26-GN26 -> -736835.01 | GP26: =FV26/FT26 -> 388.2525 | GQ26: =GF26/GD26 -> 1824.5421 | GR26: =FV26/(GK26+GL26+GI26+GM26) -> 0.27559509 | GS26: =GH26/(GK26+GL26+GI26+GM26+GN26) -> 0.32442472 | GV26: 总 | GW26: =SUM(GW19:GW23) -> 3 | GX26: =SUM(GX19:GX23) -> 0 | GY26: =SUM(GY19:GY23) -> 27 | GZ26: =(HB26/GY26)/HL1 -> 0.86618877 | HA26: =SUM(HA19:HA23) -> 2352 | HB26: =SUM(HB19:HB23) -> 725 | HC26: =SUM(HC19:HC23) -> 244963.77 | HD26: =SUM(HD19:HD23) -> 492891.47 | HE26: =SUM(HE19:HE23) -> 237707 | HF26: =SUM(HF19:HF23) -> 2943183.5 | HG26: =SUM(HG19:HG23) -> 2920899 | HH26: =HF26-HG26 -> 22284.47 | HI26: =SUM(HI19:HI23) -> 539 | HJ26: =SUM(HJ19:HJ23) -> 350202 | HK26: =SUM(HK19:HK23) -> 160973 | HL26: =SUM(HL19:HL23) -> 5449 | HM26: =SUM(HM19:HM23) -> 4724 | HN26: =SUM(HN19:HN23) -> 6092793.5 | HO26: =SUM(HO19:HO23) -> 5818984.2 | HP26: =SUM(HP19:HP23) -> 273809.23 | ... HR26: =SUM(HR19:HR23) -> -115649.61 | HS26: =HN26*5.5% -> 335103.64 | HT26: =HR26*20% -> -23129.922 | HU26: =SUM(HU19:HU23) -> 639866 | HV26: =SUM(HV19:HV23) -> 0 | HW26: =HP26-HQ26-HS26-HT26-HU26-HV26 -> -701197.49 | HX26: =HD26/HB26 -> 679.8503 | HY26: =HN26/HL26 -> 1118.1489 | HZ26: =HD26/(HS26+HT26+HQ26+HU26) -> 0.50552623 | IA26: =HP26/(HS26+HT26+HQ26+HU26+HV26) -> 0.28082804 | ID26: 总 | IE26: =SUM(IE19:IE23) -> 3 | IF26: =SUM(IF19:IF23) -> 0 | IG26: =SUM(IG19:IG23) -> 101 | IH26: =(IJ26/IG26)/IT1 -> 0.18141169 | II26: =SUM(II19:II23) -> 2217 | IJ26: =SUM(IJ19:IJ23) -> 568 | IK26: =SUM(IK19:IK23) -> 151378 | IL26: =SUM(IL19:IL23) -> 220878 | IM26: =SUM(IM19:IM23) -> 182898 | IN26: =SUM(IN19:IN23) -> 730883 | IO26: =SUM(IO19:IO23) -> 625871.56 | IP26: =IN26-IO26 -> 105011.44 | IQ26: =SUM(IQ19:IQ23) -> 432 | IR26: =SUM(IR19:IR23) -> 172187 | IS26: =SUM(IS19:IS23) -> 121845 | IT26: =SUM(IT19:IT23) -> 4123 | IU26: =SUM(IU19:IU23) -> 3555 | IV26: =SUM(IV19:IV23) -> 4050262 | IW26: =SUM(IW19:IW23) -> 3133780 | IX26: =SUM(IX19:IX23) -> 916482 | ... IZ26: =SUM(IZ19:IZ23) -> 826238.9 | JA26: =IV26*5.5% -> 222764.41 | JB26: =IZ26*20% -> 165247.78 | JC26: =SUM(JC19:JC23) -> 342519 | JD26: =SUM(JD19:JD23) -> 0 | JE26: =IX26-IY26-JA26-JB26-JC26 -> 164951.01 | JF26: =IL26/IJ26 -> 388.86972 | JG26: =IV26/IT26 -> 982.35799 | JH26: =IL26/(JA26+JB26+IY26+JC26) -> 0.29390405 | JI26: =IX26/(JA26+JB26+IY26+JC26) -> 1.2194866 | JL26: 总 | JM26: =SUM(JM19:JM23) -> 3 | JN26: =SUM(JN19:JN23) -> 112 | JQ26: =SUM(JQ19:JQ23) -> 3249 | JR26: =SUM(JR19:JR23) -> 1764 | JS26: =SUM(JS19:JS23) -> 509255 | JT26: =SUM(JT19:JT23) -> 583642 | JU26: =SUM(JU19:JU23) -> 378712 | JV26: =SUM(JV19:JV23) -> 1009942 | JW26: =SUM(JW19:JW23) -> 1187769.8 | JY26: =SUM(JY19:JY23) -> 1659 | JZ26: =SUM(JZ19:JZ23) -> 543736 | KA26: =SUM(KA19:KA23) -> 348065 | KB26: =SUM(KB19:KB23) -> 5056 | KC26: =SUM(KC19:KC23) -> 3292 | KD26: =SUM(KD19:KD23) -> 4066708 | KE26: =SUM(KE19:KE23) -> 3921454 | KF26: =SUM(KF19:KF23) -> 145254 | ... KH26: =SUM(KH19:KH23) -> -121904.82 | KI26: =KD26*3.5% -> 142334.78 | KJ26: =KH26*10% -> -12190.482 | KK26: =SUM(KK19:KK23) -> 331470 | KM26: =KF26-KG26-KI26-KJ26-KK26 -> -354360.3 | KN26: =JT26/JR26 -> 330.86281 | KO26: =KD26/KB26 -> 804.33307 | KP26: =JT26/(KI26+KJ26+KG26+KK26) -> 1.1681851 | KQ26: =KF26/(KI26+KJ26+KG26+KK26) -> 0.29073227 | KT26: 总 | KU26: 5 | KW26: 351 | KY26: 3332 | KZ26: 1090 | LA26: 284337 | LB26: 456323 | LC26: 321790 | LD26: 1428669 | LE26: 1250793.3 | LG26: 811 | LH26: 312138 | LI26: 269377 | LJ26: 4858 | LK26: 3768 | LL26: 4087925 | LM26: 3274091 | LN26: 813834 | LO26: 12999.82 | LP26: 613172.51 | LQ26: 143077.38 | LR26: 61317.251 | LS26: 570865 | LU26: 25574.554 | LV26: 418.64495 | LW26: 841.48312 | LX26: 0.5788995 | LY26: 1.0324443 | MB26: 总 | MC26: =SUM(MC19:MC23) -> 6 | ME26: =SUM(ME19:ME23) -> 227 | MG26: =SUM(MG19:MG23) -> 2201 | MH26: =SUM(MH19:MH23) -> 634 | MI26: =SUM(MI19:MI23) -> 170162 | MJ26: =SUM(MJ19:MJ23) -> 264405 | MK26: =SUM(MK19:MK23) -> 146089 | ML26: =SUM(ML19:ML23) -> 744859 | MM26: =SUM(MM19:MM23) -> 599406 | MO26: =SUM(MO19:MO23) -> 482 | MP26: =SUM(MP19:MP23) -> 199854 | MQ26: =SUM(MQ19:MQ23) -> 110878 | MR26: =SUM(MR19:MR23) -> 3631 | MS26: =SUM(MS19:MS23) -> 2997 | MT26: =SUM(MT19:MT23) -> 3113478 | MU26: =SUM(MU19:MU23) -> 2492366 | MV26: =SUM(MV19:MV23) -> 621112 | ... MX26: =SUM(MX19:MX23) -> 490014.88 | MY26: =MT26*5.5% -> 171241.29 | MZ26: =MX26*20% -> 98002.976 | NA26: =SUM(NA19:NA23) -> 1064387 | NB26: =MV26-MW26-MY26-MZ26-NA26 -> -724519.27 | ND26: =MJ26/MH26 -> 417.04259 | NE26: =MT26/MR26 -> 857.47122 | NF26: =MJ26/(MY26+MZ26+MW26+NA26) -> 0.19649142 | NG26: =MV26/(MY26+MZ26+MW26+NA26) -> 0.46157667 | NJ26: 总 | NK26: =SUM(NK19:NK23) -> 8 | NM26: =SUM(NM19:NM23) -> 196 | NO26: =SUM(NO19:NO23) -> 3228 | NP26: =SUM(NP19:NP23) -> 1281 | NQ26: =SUM(NQ19:NQ23) -> 334581 | NR26: =SUM(NR19:NR23) -> 479331 | NS26: =SUM(NS19:NS23) -> 265822.71 | NT26: =SUM(NT19:NT23) -> 1338557 | NU26: =SUM(NU19:NU23) -> 1071162.7 | NW26: =SUM(NW19:NW23) -> 883 | NX26: =SUM(NX19:NX23) -> 325305 | NY26: =SUM(NY19:NY23) -> 180869.71 | NZ26: =SUM(NZ19:NZ23) -> 9237 | OA26: =SUM(OA19:OA23) -> 7954 | OB26: =SUM(OB19:OB23) -> 8281937 | OC26: =SUM(OC19:OC23) -> 6421796 | OD26: =SUM(OD19:OD23) -> 1860141 | ... OF26: =SUM(OF19:OF23) -> 1603253.9 | OG26: =OB26*3.5% -> 289867.79 | OH26: =OF26*20% -> 320650.78 | OI26: =SUM(OI19:OI23) -> 887603 | OK26: =OD26-OG26-OH26-OE26-OI26 -> 301496.42 | OL26: =NR26/NP26 -> 374.18501 | OM26: =OB26/NZ26 -> 896.60463 | ON26: =NR26/(OG26+OH26+OE26+OI26) -> 0.30753066 | OO26: =OD26/(OG26+OH26+OE26+OI26) -> 1.193435 | OS26: 总 | OT26: =SUM(OT19:OT23) -> 8 | OU26: =SUM(OU19:OU23) -> 120 | OV26: =SUM(OV19:OV23) -> 4752 | OW26: =SUM(OW19:OW23) -> 2022 | OX26: =SUM(OX19:OX23) -> 571855 | OY26: =SUM(OY19:OY23) -> 854813 | OZ26: =SUM(OZ19:OZ23) -> 472725 | PA26: =SUM(PA19:PA23) -> 2112495 | ... PF26: =SUM(PF19:PF23) -> 6183318 | PG26: =PE26-PF26 -> 1740354 | PH26: =SUM(PH19:PH23) -> 106629 | PI26: =SUM(PI19:PI23) -> 1373315.1 | PJ26: =PE26*5.5% -> 435801.96 | PK26: =PI26*20% -> 274663.03 | PL26: =SUM(PL19:PL23) -> 887603 | PM26: =PG26-PJ26-PK26-PH26-PL26 -> 35657.014 | PN26: =OY26/OW26 -> 422.75618 | PO26: =PE26/PC26 -> 785.53306 | PP26: =OY26/(PH26+PJ26+PK26+PL26) -> 0.50144572 | PQ26: =PG26/(PJ26+PK26+PH26+PL26) -> 1.0209169 | PU26: 总 | PV26: =SUM(PV19:PV25) -> 8 | PW26: =SUM(PW19:PW25) -> 122 | PX26: =SUM(PX19:PX25) -> 5005 | PY26: =SUM(PY19:PY25) -> 2061 | PZ26: =SUM(PZ19:PZ25) -> 782180 | QA26: =SUM(QA19:QA25) -> 1101426 | QB26: =SUM(QB19:QB25) -> 754034 | QC26: =SUM(QC19:QC25) -> 9861 | ... QJ26: =SUM(QJ19:QJ25) -> 459140.99 | QK26: =QI26*20% -> 204831.78 | QL26: =SUM(QL19:QL25) -> 1587125 | QM26: =SUM(QM19:QM25) -> 674669.08 | QN26: =SUM(QN19:QN25) -> 1745.8351 | QO26: =QE26/QC26 -> 846.56911 | QP26: =QA26/(QH26+QJ26+QK26+QL26) -> 0.47439949 | QQ26: =QG26/(QJ26+QK26) -> 1.972992 | QU26: 总 | QV26: =SUM(QV19:QV25) -> 16 | QW26: =SUM(QW19:QW25) -> 8969 | QX26: =SUM(QX19:QX25) -> 3036 | QY26: =SUM(QY19:QY25) -> 4866043 | QZ26: =SUM(QZ19:QZ25) -> 5018 | RA26: =SUM(RA19:RA25) -> 11224467 | RB26: =SUM(RB19:RB25) -> 8930566 | RC26: =RB26-RE26 -> 8819896 | RD26: =SUM(RD19:RD25) -> 2293901 | RE26: =SUM(RE19:RE25) -> 110670 | RF26: =SUM(RF19:RF25) -> 1850265.1 | RG26: =SUM(RG19:RG25) -> 617345.69 | RH26: =SUM(RH19:RH25) -> 185026.52 | RI26: =SUM(RI19:RI25) -> 3280048 | RJ26: =RD26-RG26-RH26 -> 1491528.8 | RK26: =RA26/QZ26 -> 2236.8408 | RL26: =QY26/(RE26+RG26+RH26+RI26) -> 1.1604909 | RM26: =RD26/(RG26+RH26) -> 2.8588989 | RQ26: 总 | RR26: =SUM(RR19:RR25) -> 17 | RS26: =SUM(RS19:RS25) -> 6105 | RT26: =SUM(RT19:RT25) -> 1840 | RU26: =SUM(RU19:RU25) -> 2870975.2 | RV26: =SUM(RV19:RV25) -> 2918 | RW26: =SUM(RW19:RW25) -> 7385767.2 | RX26: =SUM(RX19:RX25) -> 6662781 | RY26: =SUM(RY19:RY25) -> 722986.23 | ... SF26: =SUM(SF19:SF25) -> -3145299.9 | SG26: =RW26/RV26 -> 2531.106 | SH26: =RU26/(RZ26+SC26+SD26+SE26) -> 0.72278594 | SI26: =RY26/(SC26+SD26+SE26) -> 0.18690092 | SM26: 总 | SN26: =SUM(SN19:SN25) -> 16 | SO26: =SUM(SO19:SO25) -> 4623 | SP26: =SUM(SP19:SP25) -> 1886 | SQ26: =SUM(SQ19:SQ25) -> 3029142 | SR26: =SUM(SR19:SR25) -> 2724 | SS26: =SUM(SS19:SS25) -> 6327669 | ST26: =SUM(ST19:ST25) -> 5532558.2 | SU26: =SUM(SU19:SU25) -> 795110.83 | ... TB26: =SUM(TB19:TB25) -> -3561241.4 | TC26: =SS26/SR26 -> 2322.9328 | TD26: =SQ26/(SV26+SY26+SZ26+TA26) -> 0.66051621 | TE26: =SU26/(SY26+SZ26+TA26) -> 0.18251757 | TH26: 总 | TI26: =SUM(TI19:TI25) -> 25 | TJ26: =SUM(TJ19:TJ25) -> 7416 | TK26: =SUM(TK19:TK25) -> 4238 | TL26: =SUM(TL19:TL25) -> 3675903.9 | TM26: =SUM(TM19:TM25) -> 5063 | TN26: =SUM(TN19:TN25) -> 7619495.8 | TO26: =SUM(TO19:TO25) -> 6903786 | TP26: =SUM(TP19:TP25) -> 715709.8 | ... TW26: =SUM(TW19:TW25) -> -5604283.5 | TX26: =TN26/TM26 -> 1504.937 | TY26: =TL26/(TQ26+TT26+TU26+TV26) -> 0.50102804 | TZ26: =TP26/(TT26+TU26+TV26) -> 0.11324534 | UD26: 总 | UE26: =SUM(UE19:UE25) -> 25 | UF26: =SUM(UF19:UF25) -> 10657 | UG26: =SUM(UG19:UG25) -> 6778 | UH26: =SUM(UH19:UH25) -> 5124721 | UI26: =SUM(UI19:UI25) -> 7409 | UJ26: =SUM(UJ19:UJ25) -> 8856814 | UK26: =SUM(UK19:UK25) -> 9538119 | UL26: =SUM(UL19:UL25) -> -681305 | ... US26: =SUM(US19:US25) -> -7252725.4 | UT26: =UJ26/UI26 -> 1195.4129 | UU26: =UH26/UM26 -> 2.7291839 | UV26: =UL26/(UP26+UQ26+UR26) -> -0.10367698 | UZ26: 总 | VA26: =SUM(VA19:VA25) -> 21 | VB26: =SUM(VB19:VB25) -> 4302 | VC26: =SUM(VC19:VC25) -> 2190 | VD26: =SUM(VD19:VD25) -> 3002343 | VE26: =SUM(VE19:VE25) -> 2904 | VF26: =SUM(VF19:VF25) -> 5109600 | VG26: =SUM(VG19:VG25) -> 5585845 | VH26: =SUM(VH19:VH25) -> -476245 | ... VO26: =SUM(VO19:VO25) -> -4098357.7 | VP26: =VF26/VE26 -> 1759.5041 | VQ26: =VD26/VI26 -> 5.1581367 | VR26: =VH26/(VL26+VM26+VN26) -> -0.11065783
C28: 平台 | D28: 现场人数 | E28: 转线上人数 | F28: 线上人数 | G28: 人均开发 | H28: 总注册 | I28: 总开发人数 | J28: 首存金额 | K28: 首存总金额 | L28: 首提总金额 | M28: 新客总存 | N28: 新客总提 | O28: 新客存提差 | P28: 一级首存 | Q28: 一级存款 | R28: 一级提款 | S28: 充值人数 | T28: 复存人数 | U28: 存款 | V28: 提款 | W28: 存提差 | X28: 线上员工资 | Y28: 平台盈亏 | Z28: 充值 手续费3.5% | AA28: 平台 服务费20% | AB28: 现场员工资 | AC28: 转线上员工资 | AD28: 净利润 | AE28: 新客单价 | AF28: 客单价 | AG28: 支出回报率 | AH28: 投产比 | AJ28: 平台 | AK28: 现场人数 | AL28: 转线上人数 | AM28: 线上人数 | AN28: 人均开发 | AO28: 总注册 | AP28: 总开发人数 | AQ28: 首存金额 | AR28: 首存总金额 | AS28: 首提总金额 | AT28: 新客总存 | AU28: 新客总提 | AV28: 新客存提差 | AW28: 一级首存 | AX28: 一级存款 | AY28: 一级提款 | AZ28: 充值人数 | BA28: 复存人数 | BB28: 存款 | BC28: 提款 | BD28: 存提差 | BE28: 线上员工资 | BF28: 平台盈亏 | BG28: 充值 手续费3.5% | BH28: 平台 服务费20% | BI28: 现场员工资 | BJ28: 转线上员工资 | BK28: 净利润 | BL28: 新客单价 | BM28: 客单价 | BN28: 支出回报率 | BO28: 投产比 | BQ28: 平台 | BR28: 现场人数 | BS28: 现场转线上 | BT28: 线上人数 | BU28: 人均开发 | BV28: 总注册 | BW28: 总开发人数 | BX28: 首存金额 | BY28: 首存总金额 | BZ28: 首提总金额 | CA28: 新客总存 | CB28: 新客总提 | CC28: 新客存提差 | CD28: 一级首存 | CE28: 一级存款 | CF28: 一级提款 | CG28: 充值人数 | CH28: 复存人数 | CI28: 存款 | CJ28: 提款 | CK28: 存提差 | CL28: 线上人员工资 | CM28: 平台盈亏 | CN28: 充值手续费4% | CO28: 平台服务费20% | CP28: 现场人员工资 | CQ28: 现场转线上 | CR28: 净利润 | CS28: 新客客单价 | CT28: 人均客单价 | CU28: 投资回报率 | CV28: 投产比 | CX28: 平台 | CY28: 现场人数 | CZ28: 转线上人数 | DA28: 线上人数 | DB28: 人均开发 | DC28: 总注册 | DD28: 总开发人数 | DE28: 首存金额 | DF28: 首存总金额 | DG28: 首提总金额 | DH28: 新客总存 | DI28: 新客总提 | DJ28: 新客存提差 | DK28: 一级首存 | DL28: 一级存款 | DM28: 一级提款 | DN28: 充值人数 | DO28: 复存人数 | DP28: 存款 | DQ28: 提款 | DR28: 存提差 | DS28: 线上员工资 | DT28: 平台盈亏 | DU28: 充值 手续费3.5% | DV28: 平台 服务费20% | DW28: 现场员工资 | DX28: 转线上员工资 | DY28: 净利润 | DZ28: 新客单价 | EA28: 客单价 | EB28: 支出回报率 | EC28: 投产比 | EE28: 平台 | EF28: 现场人数 | EG28: 转线上人数 | EH28: 线上人数 | EI28: 人均开发 | EJ28: 总注册 | EK28: 总开发人数 | EL28: 首存金额 | EM28: 首存总金额 | EN28: 首提总金额 | EO28: 新客总存 | EP28: 新客总提 | EQ28: 新客存提差 | ER28: 一级首存 | ES28: 一级存款 | ET28: 一级提款 | EU28: 充值人数 | EV28: 复存人数 | EW28: 存款 | EX28: 提款 | EY28: 存提差 | EZ28: 线上员工资 | FA28: 平台盈亏 | FB28: 充值 手续费3.5% | FC28: 平台 服务费20% | FD28: 现场员工资 | FE28: 转线上员工资 | FF28: 净利润 | FG28: 新客单价 | FH28: 客单价 | FI28: 支出回报率 | FJ28: 投产比 | FN28: 平台 | FO28: 现场人数 | FP28: 转线上人数 | FQ28: 线上人数 | FR28: 人均开发 | FS28: 总注册 | FT28: 总开发人数 | FU28: 首存金额 | FV28: 首存总金额 | FW28: 首提总金额 | FX28: 新客总存 | FY28: 新客总提 | FZ28: 新客存提差 | GA28: 一级首存 | GB28: 一级存款 | GC28: 一级提款 | GD28: 充值人数 | GE28: 复存人数 | GF28: 存款 | GG28: 提款 | GH28: 存提差 | GI28: 线上员工资 | GJ28: 平台盈亏 | GK28: 充值 手续费3.5% | GL28: 平台 服务费20% | GM28: 现场员工资 | GN28: 转线上员工资 | GO28: 净利润 | GP28: 新客单价 | GQ28: 客单价 | GR28: 支出回报率 | GS28: 投产比 | GV28: 平台 | GW28: 现场人数 | GX28: 转线上人数 | GY28: 线上人数 | GZ28: 人均开发 | HA28: 总注册 | HB28: 总开发人数 | HC28: 首存金额 | HD28: 首存总金额 | HE28: 首提总金额 | HF28: 新客总存 | HG28: 新客总提 | HH28: 新客存提差 | HI28: 一级首存 | HJ28: 一级存款 | HK28: 一级提款 | HL28: 充值人数 | HM28: 复存人数 | HN28: 存款 | HO28: 提款 | HP28: 存提差 | HQ28: 线上员工资 | HR28: 平台盈亏 | HS28: 充值 手续费3.5% | HT28: 平台 服务费20% | HU28: 现场员工资 | HV28: 转线上员工资 | HW28: 净利润 | HX28: 新客单价 | HY28: 客单价 | HZ28: 支出回报率 | IA28: 投产比 | ID28: 平台 | IE28: 现场人数 | IF28: 转线上人数 | IG28: 线上人数 | IH28: 人均开发 | II28: 总注册 | IJ28: 总开发人数 | IK28: 首存金额 | IL28: 首存总金额 | IM28: 首提总金额 | IN28: 新客总存 | IO28: 新客总提 | IP28: 新客存提差 | IQ28: 一级首存 | IR28: 一级存款 | IS28: 一级提款 | IT28: 充值人数 | IU28: 复存人数 | IV28: 存款 | IW28: 提款 | IX28: 存提差 | IY28: 线上员工资 | IZ28: 平台盈亏 | JA28: 充值 手续费3.5% | JB28: 平台 服务费20% | JC28: 现场员工资 | JD28: 转线上员工资 | JE28: 净利润 | JF28: 新客单价 | JG28: 客单价 | JH28: 支出回报率 | JI28: 投产比 | JL28: 平台 | JM28: 现场人数 | JN28: 转线上人数 | JO28: 线上人数 | JP28: 人均开发 | JQ28: 总注册 | JR28: 总开发人数 | JS28: 首存金额 | JT28: 首存总金额 | JU28: 首提总金额 | JV28: 新客总存 | JW28: 新客总提 | JX28: 新客存提差 | JY28: 一级首存 | JZ28: 一级存款 | KA28: 一级提款 | KB28: 充值人数 | KC28: 复存人数 | KD28: 存款 | KE28: 提款 | KF28: 存提差 | KG28: 线上员工资 | KH28: 平台盈亏 | KI28: 充值 手续费3.5% | KJ28: 平台 服务费20% | KK28: 现场员工资 | KL28: 转线上员工资 | KM28: 净利润 | KN28: 新客单价 | KO28: 客单价 | KP28: 支出回报率 | KQ28: 投产比 | KT28: 平台 | KU28: 现场人数 | KW28: 线上人数 | KY28: 注册 | KZ28: 首存 | LA28: 首存金额 | LB28: 首存总存金额 | LC28: 首提总金额 | LD28: 新客总存 | LE28: 新客总提 | LG28: 一级首存 | LH28: 一级存款 | LI28: 一级提款 | LJ28: 充值人数 | LK28: 复存人数 | LL28: 存款 | LM28: 提款 | LN28: 存提差 | LO28: 线上人员工资 | LP28: 平台盈亏 | LQ28: 充值手续费4% | LR28: 平台服务费20% | LS28: 现场人员工资 | LU28: 净利润 | LV28: 新客客单价 | LW28: 人均客单价 | LX28: 投资回报率 | LY28: 投产比 | MB28: 平台 | MC28: 现场人数 | ME28: 线上人数 | MG28: 注册 | MH28: 首存 | MI28: 首存金额 | MJ28: 首存总存金额 | MK28: 首提总金额 | ML28: 新客总存 | MM28: 新客总提 | MO28: 一级首存 | MP28: 一级存款 | MQ28: 一级提款 | MR28: 充值人数 | MS28: 复存人数 | MT28: 存款 | MU28: 提款 | MV28: 存提差 | MW28: 线上人员工资 | MX28: 平台盈亏 | MY28: 充值手续费4% | MZ28: 平台服务费20% | NA28: 现场人员工资 | NB28: 净利润 | ND28: 新客客单价 | NE28: 人均客单价 | NF28: 投资回报率 | NG28: 投产比 | NJ28: 平台 | NK28: 现场人数 | NM28: 线上人数 | NO28: 注册 | NP28: 首存 | NQ28: 首存金额 | NR28: 首存总存金额 | NS28: 首提总金额 | NT28: 新客总存 | NU28: 新客总提 | NW28: 一级首存 | NX28: 一级存款 | NY28: 一级提款 | NZ28: 充值人数 | OA28: 复存人数 | OB28: 存款 | OC28: 提款 | OD28: 存提差 | OE28: 外部人员工资 | OF28: 平台盈亏 | OG28: 充值手续费4% | OH28: 平台服务费20% | OI28: 现场人员工资 | OK28: 净利润 | OL28: 新客客单价 | OM28: 人均客单价 | ON28: 投资回报率 | OO28: 投产比
C29: MM01 | O29: =M29-N29 -> 0 | W29: =U29-V29 -> 0 | Z29: =U29*4% -> 0 | AA29: =IF(Y29>0,Y29*20%,0) -> 0 | AD29: =W29-Z29-AA29-X29-AB29-AC29 -> 0 | AE29: =K29/I29 -> #DIV/0! | AF29: =U29/S29 -> #DIV/0! | AG29: =K29/(Z29+AA29+X29+AB29) -> #DIV/0! | AH29: =W29/(Z29+AA29+X29+AB29+AC29) -> #DIV/0! | AJ29: MM01 | AK29: 0 | AL29: 0 | AM29: 0 | AN29: =(AP29/AM29)/AZ1 -> #DIV/0! | AO29: 849 | AP29: 294 | AQ29: 44575.633 | AR29: 79666.467 | AS29: 29300 | AT29: =12198828/60 -> 203313.8 | AU29: =11661700/60 -> 194361.67 | AV29: =AT29-AU29 -> 8952.1333 | AW29: 52786.383 | AX29: 52786.383 | AY29: 23033.333 | AZ29: 1362 | BA29: 1068 | BB29: 789461.3 | BC29: 701952.71 | BD29: =BB29-BC29 -> 87508.587 | BE29: 19613 | BF29: =2221326.91/60 -> 37022.115 | BG29: =BB29*4% -> 31578.452 | BH29: =IF(BF29>0,BF29*20%,0) -> 7404.423 | BI29: ='[1]MM01'!$B$4 -> 0 | BJ29: ='[1]MM01'!$C$4 -> 0 | BK29: =BD29-BG29-BH29-BE29-BI29-BJ29 -> 28912.712 | BL29: =AR29/AP29 -> 270.97438 | BM29: =BB29/AZ29 -> 579.63385 | BN29: =AR29/(BG29+BH29+BE29+BI29) -> 1.3595917 | BO29: =BD29/(BG29+BH29+BE29+BI29+BJ29) -> 1.4934257 | BP29: 停推 | BQ29: MM01 | BR29: 0 | BS29: 3 | BT29: 6 | BU29: 2.327957 | BV29: 1069 | BW29: 433 | BX29: 65566.667 | BY29: 114723.33 | BZ29: 72262.65 | CA29: =20210116/60 -> 336835.27 | CB29: =16539427/60 -> 275657.12 | CC29: 61178.15 | CD29: 368 | CE29: 101696.67 | CF29: 50554.983 | CG29: 1646 | CH29: 1213 | CI29: 1136587.5 | CJ29: 870057.08 | CK29: =CI29-CJ29 -> 266530.39 | CL29: 15298 | CM29: =12701571.34/60 -> 211692.86 | CN29: =CI29*4% -> 45463.499 | CO29: =IF(CM29>0,CM29*20%,0) -> 42338.571 | CP29: 0 | CQ29: 75562.5 | CR29: =CK29-CN29-CO29-CL29-CP29-CQ29 -> 87867.816 | CS29: =BY29/BW29 -> 264.94996 | CT29: =CI29/CG29 -> 690.51486 | CU29: =BY29/(CN29+CO29+CL29+CP29) -> 1.1127377 | CV29: =CK29/(CN29+CO29+CL29+CP29+CQ29) -> 1.4918088 | CX29: MM01 | CY29: 0 | CZ29: 3 | DA29: 10 | DB29: 0.34 | DC29: 304 | DD29: 102 | DE29: 13616.25 | DF29: 19235 | DG29: 12075 | DH29: =2176800/80 -> 27210 | DI29: =1397000/80 -> 17462.5 | DJ29: =DH29-DI29 -> 9747.5 | DK29: 90 | DL29: 18103.75 | DM29: 11575 | DN29: 866 | DO29: 764 | DP29: 708167.53 | DQ29: 541958.47 | DR29: =DP29-DQ29 -> 166209.05 | DS29: 0 | DT29: =11033406.63/80 -> 137917.58 | DU29: =DP29*4% -> 28326.701 | DV29: =IF(DT29>0,DT29*20%,0) -> 27583.517 | DW29: ='[1]MM01'!$B$4 -> 0 | DX29: ='[1]MM01'!$C$4 -> 0 | DY29: =DR29-DU29-DV29-DS29-DW29-DX29 -> 110298.83 | DZ29: =DF29/DD29 -> 188.57843 | EA29: =DP29/DN29 -> 817.74541 | EB29: =DF29/(DU29+DV29+DS29+DW29) -> 0.34403372 | EC29: =DR29/(DU29+DV29+DS29+DW29+DX29) -> 2.9727849 | EE29: MM01 | EF29: 0 | EG29: 3 | EH29: 13 | EI29: 0.17617866 | EJ29: 256 | EK29: 71 | EL29: 6475 | EM29: 13975 | EN29: 6100 | EO29: 43208.75 | EP29: 31435.15 | EQ29: 11773.6 | ER29: 60 | ES29: 12537.5 | ET29: 5450 | EU29: 991 | EV29: 920 | EW29: 852838.01 | EX29: 649433.74 | EY29: 203404.27 | EZ29: 2525 | FA29: 182296.57 | FB29: 34113.52 | FC29: 36459.314 | FD29: 0 | FE29: 75562.5 | FF29: 54743.941 | FG29: 196.83099 | FH29: 860.58326 | FI29: 0.19118214 | FJ29: 1.3682485 | FN29: MM01 | FO29: 0 | FP29: 3 | FQ29: 40 | FR29: =(FT29/FQ29)/GF1 -> 0.091071429 | FS29: 393 | FT29: 102 | FU29: 16031.25 | FV29: 36037.5 | FW29: 13150 | FX29: =28572306/80 -> 357153.83 | FY29: =19135000/80 -> 239187.5 | FZ29: =FX29-FY29 -> 117966.32 | GA29: 74 | GB29: 26828.75 | GC29: 11900 | GD29: 911 | GE29: 809 | GF29: 636572.34 | GG29: 537486.88 | GH29: 99085.462 | GI29: 7775 | GJ29: =6575075.16/80 -> 82188.439 | GK29: 25462.893 | GL29: 16437.688 | GM29: 0 | GN29: 68250 | GO29: -18840.119 | GP29: 353.30882 | GQ29: 698.76217 | GR29: =FV29/(GK29+GL29+GI29+GM29) -> 0.72545704 | GS29: =GH29/(GK29+GL29+GI29+GM29+GN29) -> 0.84023722 | GV29: MM01 | GW29: 0 | GX29: 4 | GY29: 11 | GZ29: =(HB29/GY29)/HL1 -> 0.23167155 | HA29: 421 | HB29: 79 | HC29: 8568.7625 | HD29: 15756.763 | HE29: 8620.9625 | HF29: 39823.775 | HG29: 25145.963 | HH29: =HF29-HG29 -> 14677.812 | HI29: 58 | HJ29: 12574.263 | HK29: 7395.9625 | HL29: 1040 | HM29: 961 | HN29: 459629.31 | HO29: 265600.59 | HP29: 194028.73 | HQ29: 0 | HR29: 175903.37 | HS29: 18385.173 | HT29: 14624.271 | HU29: 0 | HV29: 100750 | HW29: 60269.281 | HX29: 199.45269 | HY29: 441.95126 | HZ29: =HD29/(HS29+HT29+HQ29+HU29) -> 0.47734105 | IA29: =HP29/(HS29+HT29+HQ29+HU29+HV29) -> 1.4505796 | ID29: MM01 | IE29: 3 | IF29: 0 | IG29: 31 | IH29: =(IJ29/IG29)/IT1 -> 0.12382934 | II29: 508 | IJ29: 119 | IK29: 12677.5 | IL29: 19431.25 | IM29: 10831.25 | IN29: 65886.15 | IO29: 44537.5 | IP29: =IN29-IO29 -> 21348.65 | IQ29: 93 | IR29: 13558.75 | IS29: 9331.25 | IT29: 1164 | IU29: 1045 | IV29: 527486 | IW29: 467935 | IX29: =IV29-IW29 -> 59551 | IY29: 28875 | IZ29: =2913338.5/80 -> 36416.731 | JA29: =IV29*4% -> 21099.44 | JB29: =IZ29*20% -> 7283.3462 | JC29: 75547 | JD29: 0 | JE29: =IX29-JA29-JB29-IY29-JC29 -> -73253.786 | JF29: =IL29/IJ29 -> 163.28782 | JG29: =IV29/IT29 -> 453.16667 | JH29: =IL29/(JA29+JB29+IY29+JC29) -> 0.14631438 | JI29: =IX29/(JA29+JB29+IY29+JC29) -> 0.44841004 | JL29: MM01 | JM29: 4 | JN29: 9 | JQ29: 234 | JR29: 96 | JS29: 7937.5 | JT29: 34445.625 | JU29: 21175 | JV29: 124191.98 | JW29: 48225 | JY29: 90 | JZ29: 16178.75 | KA29: 4012.5 | KB29: 1154 | KC29: 1058 | KD29: 560329.53 | KE29: 420123.83 | KF29: =KD29-KE29 -> 140205.7 | KG29: 5500 | KH29: 126180.81 | KI29: =KD29*4% -> 22413.181 | KJ29: =KH29*20% -> 25236.162 | KK29: 97500 | KM29: =KF29-KI29-KJ29-KG29-KK29 -> -10443.643 | KN29: =JT29/JR29 -> 358.80859 | KO29: =KD29/KB29 -> 485.55418 | KP29: =JT29/(KI29+KJ29+KG29+KK29) -> 0.22864769 | KQ29: =KF29/(KI29+KJ29+KG29+KK29) -> 0.93067581 | KT29: MM01 | KU29: 6 | KW29: 162 | KY29: 1189 | KZ29: 394 | LA29: 37782.188 | LB29: 59213.438 | LC29: 24103.575 | LD29: 269389.61 | LE29: 229608.29 | LG29: 301 | LH29: 48938.438 | LI29: 20710 | LJ29: 1737 | LK29: 1343 | LL29: 570757.59 | LM29: 486188.34 | LN29: 84569.25 | LO29: 15266.663 | LP29: 70785.69 | LQ29: 22830.304 | LR29: 14157.138 | LS29: 151125 | LU29: -118809.85 | LV29: 150.28791 | LW29: 328.58813 | LX29: 0.29114809 | LY29: 0.41582074 | MB29: MM01 | MC29: 6 | ME29: 90 | MG29: 1256 | MH29: 383 | MI29: 37037.5 | MJ29: 61586.775 | MK29: 30827.5 | ML29: 334461.58 | MM29: 262954.76 | MO29: 305 | MP29: 51039.275 | MQ29: 22014.375 | MR29: 1082 | MS29: 699 | MT29: 371497.58 | MU29: 289093.99 | MV29: =MT29-MU29 -> 82403.587 | MW29: =1142000/80 -> 14275 | MX29: =5547497.78/80 -> 69343.722 | MY29: =MT29*4% -> 14859.903 | MZ29: =MX29*20% -> 13868.744 | NA29: 115375 | NB29: =MV29-MY29-MZ29-MW29-NA29 -> -75975.06 | ND29: =MJ29/MH29 -> 160.80098 | NE29: =MT29/MR29 -> 343.34341 | NF29: =MJ29/(MY29+MZ29+MW29+NA29) -> 0.38885782 | NG29: =MV29/(MY29+MZ29+MW29+NA29) -> 0.52029481 | NJ29: MM01 | NK29: 4 | NM29: 13 | NO29: 653 | NP29: 183 | NQ29: 29546.25 | NR29: 21151.25 | NS29: 7254.375 | NT29: =3461100/80 -> 43263.75 | NU29: =3463123/80 -> 43289.037 | NW29: 154 | NX29: 17354.537 | NY29: 6116.875 | NZ29: 288 | OA29: 105 | OB29: 43263.75 | OC29: 43289.037 | OD29: =OB29-OC29 -> -25.2875 | OE29: 0 | OF29: =-296346.61/80 -> -3704.3326 | OG29: =OB29*4% -> 1730.55 | OH29: 0 | OI29: 87750 | OK29: =OD29-OG29-OH29-OE29-OI29 -> -89505.837 | OL29: =NR29/NP29 -> 115.5806 | OM29: =OB29/NZ29 -> 150.22135 | ON29: =NR29/(OG29+OH29+OE29+OI29) -> 0.23637818 | OO29: =OD29/(OG29+OH29+OE29+OI29) -> -0.00028260331 | OP29: 8月5号开始
BU30: =(BW30/BS30)/#REF! -> #DIV/0! | DB30: =(DD30/CZ30)/#REF! -> #DIV/0! | EI30: #DIV/0!
